Workbook

Sheet INICIO
A1: 0

Sheet DEZEMBRO19
A1: CLIENTE | B1: Data Entr | C1: Data Prod | D1: OC | E1: MATERIAL | F1: CÓDIGO | G1: ETIQUETA | H1: QUANT | I1: OK | J1: TEMPO | K1: QUANT | L1: OBSERVAÇÕES
A2: MODAZINE | B2: 43798 | C2: 43801 | D2: 1068 | E2: C. VER | F2: 2017 | G2: 33X21 | H2: 200000 | I2: OK | L2: FACA
A3: MODAZINE | B3: 43798 | C3: 43801 | D3: 1068 | E3: C.AMA | F3: 1785 | G3: 33X21 | H3: 30000 | I3: OK | L3: FACA
A4: BOI SUL | B4: 43801 | C4: 43790 | D4: 937 | E4: SYP | F4: 2631 | G4: 75X263 | H4: 5350 | I4: OK | L4: beta
A5: BOI SUL | B5: 43801 | C5: 43797 | D5: 937 | E5: BOPP BORR | F5: 2632 | G5: 103X94 | H5: 5000 | I5: OK | L5: BETA
A6: HYVA | B6: 43801 | C6: 43726 | D6: 855 | E6: TAG | F6: 2550 | G6: 100X70 | H6: 20000 | I6: OK | L6: BETA
A7: HYVA | B7: 43801 | C7: 43801 | D7: 855 | E7: COU BORR | F7: 2244 | G7: 100X60 | H7: 5000 | I7: OK | L7: FACA
A8: ESSENCIA JOVEM | B8: 43801 | C8: 43801 | D8: 1095 | E8: COUCHE | F8: 855 | G8: 50X40 | H8: 40000 | I8: OK | L8: FACA
A9: SIMONE | B9: 43801 | C9: 43801 | D9: 1101 | E9: NYLON | F9: 2600 | G9: 29X76 | H9: 5500 | I9: OK | L9: FACA
A10: DUKE | B10: 43801 | C10: 43801 | D10: 1076 | E10: COUCHE | F10: 2891 | G10: 60X60 | H10: 1000 | I10: OK | L10: BETA
A11: LAB. CESAR COSTA | B11: 43802 | C11: 43801 | D11: 942 | E11: COUCHE | F11: 2086 | G11: 45X25 | H11: 11000 | I11: OK | L11: BETA
A12: BRASSUD | B12: 43803 | C12: 43802 | D12: 847 | E12: COUCHE | F12: 1960 | G12: 35X40 | H12: 40000 | I12: OK | L12: FACA
A13: CODETECH | B13: 43804 | C13: 43802 | D13: 1087 | E13: COUCHE | F13: 869 | G13: 33X25 | H13: 50000 | I13: OK | L13: FACA
... A36: FRIZZO | B36: 43811 | C36: 43804 | D36: 1116 | E36: COUCHE | F36: 2762 | G36: 25X16 | H36: 100000 | I36: ok | L36: BETA
A37: BIOLUZ | B37: 43811 | D37: 1118 | E37: COUCHE | F37: 2664 | G37: 15X30 | H37: 30000 | I37: OK | L37: FACA
A38: CAPPELLETTI | B38: 43811 | C38: 43803 | D38: 1119 | E38: COUCHE | F38: 838 | G38: 100X40 | H38: 20000 | I38: OK | L38: FACA
A39: TEFFA | B39: 43811 | C39: 43810 | D39: 1120 | E39: COUCHE | F39: 2315 | G39: 70X25 | H39: 10000 | I39: OK | L39: BETA
A40: SECTA | B40: 43811 | C40: 43804 | D40: 1121 | E40: BOPP ACR | F40: 1599 | G40: 90X25 | H40: 5000 | I40: OK | L40: FACA
A41: SHOWCOLATS | B41: 43811 | C41: 43804 | D41: 1122 | E41: COUCHE | F41: 2664 | G41: 15X30 | H41: 200 | I41: OK | L41: FACA
A42: ALTAIR | B42: 43804 | C42: 43803 | D42: 1126 | E42: C.BORR | F42: 2438 | G42: 100X50 | H42: 15200 | I42: OK | L42: FACA
A43: ALTAIR | B43: 43804 | C43: 43803 | D43: 1126 | E43: C.BORR | F43: 2908 | G43: 50X30 | H43: 10000 | I43: OK | L43: FACA
A44: ARCO | B44: 43812 | C44: 43803 | D44: 852 | E44: COUCHE | F44: 2604 | G44: 105X55 | H44: 20800 | I44: OK | L44: SEPARAR
A45: GRAFICA DEZ | B45: 43812 | C45: 43812 | D45: 1111 | E45: COUCHE | F45: 2604 | G45: 105X55 | H45: 35000 | L45: SEPARAR
A46: FRIZZO | B46: 43812 | C46: 43805 | D46: 1106 | E46: COUCHE | F46: 869 | G46: 33X25 | H46: 204500 | I46: OK | L46: FACA
A47: ESTOQUE | B47: 43804 | C47: 43804 | D47: 1106 | E47: COUCHE | F47: 869 | G47: 33X25 | H47: 103500 | I47: OK | L47: FACA
A48: CHEIA DE CHARME | B48: 43812 | C48: 43804 | D48: 1127 | E48: COUCHE | F48: 869 | G48: 33X25 | H48: 12000 | I48: OK | L48: FACA
A49: EDEVANDRO | B49: 43812 | C49: 43812 | D49: 1128 | E49: COUCHE | F49: 2907 | G49: 50X120 | H49: 5000 | I49: OK | L49: BETA
A50: EDEVANDRO | B50: 43812 | C50: 43812 | D50: 1128 | E50: COUCHE | F50: 2328 | G50: 50X120 | H50: 5000 | I50: OK | L50: BETA
A51: DEKOS | B51: 43810 | C51: 43815 | D51: 1129 | E51: COUCHE | F51: 2102 | G51: 110X62 | H51: 19500 | I51: ok | L51: SUPERFLEXO
A52: KIPERFIL | B52: 43804 | C52: 43804 | D52: 1130 | E52: COUCHE | F52: 838 | G52: 100X40 | H52: 10000 | I52: OK | L52: FACA
A53: CBL | B53: 43805 | C53: 43805 | D53: 1131 | E53: COUCHE | F53: 1350 | G53: 50X35 | H53: 4000 | I53: OK | L53: BETA
A54: LAMINA | B54: 43814 | C54: 43810 | D54: 836 | E54: COUCHE | F54: 885 | G54: 70X50 | H54: 65000 | I54: OK | L54: FACA
A55: SHOWCOLATS | B55: 43822 | C55: 43819 | D55: 1123 | E55: COUCHE | F55: 2905 | G55: 25X25 | H55: 10000 | I55: OK | L55: SERA PRODUZIDO FORA
A56: SHOWCOLATS | B56: 43822 | C56: 43819 | D56: 1136 | E56: COUCHE | F56: 2906 | G56: 35X35 | H56: 11000 | I56: OK | L56: SERA PRODUZIDO FORA
A57: CASA E CIA | B57: 43815 | C57: 43803 | D57: 1094 | E57: C.AMA | F57: 2040 | G57: 40X30 | H57: 30000 | I57: OK | L57: BETA
... A71: FRIZZO | B71: 43816 | C71: 43816 | D71: 1139 | E71: COUCHE | F71: 2913 | G71: 100X100 | H71: 5000 | I71: OK | L71: BETA
A72: SUPERFLEXO | B72: 43815 | C72: 43816 | D72: 1185 | E72: COUCHE | F72: 1126 | G72: 100X100 | H72: 19000 | L72: SEPARAR
A73: QUALYFOODS | B73: 43816 | C73: 43810 | D73: 1140 | E73: COUCHE | F73: 1468 | G73: 100X75 | H73: 25000 | I73: ok | L73: FACA
A74: FRIZZO | B74: 43796 | C74: 43805 | D74: 1054 | E74: COUCHE | F74: 2186 | G74: 90X40 | H74: 69000 | I74: OK | L74: SEPARAR
A75: GRAFICA DEZ | B75: 43789 | C75: 43805 | D75: 1056 | E75: COUCHE | F75: 2186 | G75: 90X40 | H75: 71400 | I75: OK | L75: SERA PRODUZIDA FORA
A76: FRIZZO | B76: 43809 | C76: 43808 | D76: 1141 | E76: COUCHE | F76: 822 | G76: 50X50 | H76: 50000 | I76: OK | L76: FACA
A77: MCC | B77: 43816 | C77: 43815 | D77: 1142 | E77: TAG | F77: 1316 | G77: 95X30 | H77: 10000 | I77: OK | L77: BETA
A78: GRUPO EURO | B78: 43816 | C78: 43809 | D78: 1143 | E78: COUCHE | F78: 838 | G78: 100X40 | H78: 18000 | I78: OK | L78: FACA
A79: G3 | B79: 43809 | C79: 43809 | D79: 1145 | E79: TC | F79: 2608 | G79: 90X40 | H79: 3000 | I79: OK | L79: PERSONALIZAR
A80: SADI | B80: 43809 | C80: 43809 | D80: 1146 | E80: BOPP BORR | F80: 2916 | G80: 50X160 | H80: 5000 | I80: OK | L80: BETA
A81: CALERA | B81: 43817 | C81: 43815 | D81: 1148 | E81: BOPP AM | F81: 2715 | G81: 64X10 | H81: 5000 | I81: ok | L81: FACA
A82: HAMB. CAPPELLETTI | B82: 43817 | C82: 43811 | D82: 1149 | E82: COUCHE | F82: 2714 | G82: 33X25 | H82: 12000 | I82: OK | L82: FACA
A83: HIDRO | B83: 43817 | C83: 43812 | D83: 1150 | E83: BOPP | F83: 1095 | G83: 100X50 | H83: 200 | I83: OK | L83: FACA
A84: HIDRO | B84: 43817 | C84: 43812 | D84: 1150 | E84: BOPP | F84: 1395 | G84: 50X20 | H84: 200 | I84: OK | L84: FACA
... A118: CATAFESTA | B118: 43819 | C118: 43812 | D118: 1173 | E118: BOPP | F118: 1095 | G118: 100X50 | H118: 15000 | I118: OK | L118: FACA
A119: SUPERFLEXO | B119: 43812 | D119: 1179 | E119: CINZA | F119: 2525 | G119: 105 | H119: 1000 | I119: OK | L119: PINTAR
A120: SUPERFLEXO | B120: 43812 | D120: 1180 | E120: AMARELO | F120: 2499 | G120: 100 | H120: 1000 | I120: OK | L120: PINTAR
A121: HOSP. CIRCULO | B121: 43822 | C121: 43812 | D121: 1182 | E121: COUCHE | F121: 838 | G121: 100X40 | H121: 11000 | I121: OK | L121: FACA
A122: JULIA S CLOSET | B122: 43822 | C122: 43819 | D122: 1183 | E122: COUCHE | F122: 1104 | G122: 20X38 | H122: 4000 | I122: OK | L122: BETA
A123: SUPERFLEXO | B123: 43815 | D123: 1185 | E123: COUCHE | F123: 1126 | G123: 100X100 | H123: 18000 | L123: SERA PRODUZIDO FORA
A124: SUPERFLEXO | B124: 43815 | D124: 1186 | E124: COUCHE | F124: 1467 | G124: 85X50 | H124: 20000 | L124: SERA PRODUZIDO FORA
A125: ABBOCARE | B125: 43822 | C125: 43817 | D125: 2468 | E125: BOPP BORR | F125: 2468 | G125: 100X80 | H125: 20000 | I125: OK | L125: FACA
A126: AGRIMAR | B126: 43822 | C126: 43819 | D126: 1195 | E126: BOPP | F126: 1095 | G126: 100X50 | H126: 5000 | I126: OK | L126: BETA
A127: UNIMED | B127: 43473 | C127: 43816 | D127: 1192 | E127: COUCHE | F127: 2740 | G127: 90X36 | H127: 15000 | I127: OK | L127: FACA
A128: UNIMED | B128: 43473 | C128: 43816 | D128: 1193 | E128: COUCHE | F128: 2740 | G128: 90X36 | H128: 14000 | I128: OK | L128: FACA
A129: FRIZZO | B129: 43474 | C129: 43818 | D129: 1205 | E129: COUCHE | F129: 822 | G129: 50X50 | H129: 50000 | I129: OK | L129: FACA
A130: CATAFESTA | B130: 43473 | C130: 43818 | D130: 1190 | E130: COUCHE | F130: 822 | G130: 50X50 | H130: 81000 | I130: OK | L130: FACA
A131: MATVSAT | B131: 43819 | C131: 43819 | D131: 1217 | E131: COUCHE | F131: 1287 | G131: 105X75 | H131: 5000 | I131: OK | L131: BETA

Sheet JANEIRO20
A1: CLIENTE | B1: Data Entr | C1: Data Prod | D1: OC | E1: MATERIAL | F1: CÓDIGO | G1: ETIQUETA | H1: QUANT | I1: OK | J1: OBSERVAÇÕES | K1: TAMANHO | L1: METRO
A2: IND. MALHAS | B2: 43472 | C2: 43836 | D2: 1093 | E2: C.AMA | F2: 2061 | G2: 30X40 | H2: 30000 | I2: OK | J2: BETA | K2: 70 | L2: 645
A3: SULPACK | B3: 43472 | C3: 43836 | D3: 1184 | E3: BOPP | F3: 1401 | G3: 50X22 | H3: 9000 | I3: OK | J3: BETA | K3: 110 | L3: 108
A4: JETTA | B4: 43473 | C4: 43837 | D4: 1174 | E4: COUCHE | F4: 744 | G4: 100X70 | H4: 8000 | I4: OK | J4: BETA | K4: 105 | L4: 576
A5: JETTA | B5: 43473 | C5: 43837 | D5: 1174 | E5: COUCHE | F5: 2266 | G5: 90X25 | H5: 80000 | I5: OK | J5: FACA | K5: 95 | L5: 2240
A6: COESTER | B6: 43473 | C6: 43837 | D6: 1194 | E6: BOPP | F6: 1483 | G6: 100X40 | H6: 5000 | I6: OK | J6: FACA | K6: 105 | L6: 215
A7: LAIMED | B7: 43473 | C7: 43836 | D7: 1196 | E7: COUCHE | F7: 2927 | G7: 90X85 | H7: 5000 | I7: OK | J7: BETA | K7: 95 | L7: 440
A8: LAIMED | B8: 43473 | C8: 43836 | D8: 1196 | E8: COUCHE | F8: 2788 | G8: 50X75 | H8: 5000 | I8: OK | J8: BETA | K8: 60 | L8: 390
A9: CALERA | B9: 43473 | C9: 43837 | D9: 1197 | E9: BOPP | F9: 2490 | G9: 64X10 | H9: 30000 | I9: OK | J9: FACA | K9: 70 | L9: 396
A10: RESET | B10: 43473 | C10: 43838 | D10: 1198 | E10: COUCHE | F10: 869 | G10: 33X25 | H10: 50000 | I10: OK | J10: FACA | K10: 110 | L10: 470
A11: RESET | B11: 43473 | C11: 43838 | D11: 1198 | E11: COUCHE | F11: 855 | G11: 50X40 | H11: 46000 | I11: OK | J11: FACA | K11: 108 | L11: 840
A12: DANI | B12: 43474 | C12: 43839 | D12: 1199 | E12: COUCHE | F12: 838 | G12: 100X40 | H12: 31000 | I12: OK | J12: FACA | K12: 105 | L12: 1260
A13: G3 | B13: 43474 | C13: 43837 | D13: 1201 | E13: COUCHE | F13: 744 | G13: 100X70 | H13: 5000 | I13: OK | J13: BETA | K13: 105 | L13: 360
... A19: MUNDIAL | B19: 43478 | C19: 43839 | D19: 1208 | E19: C.BORR | F19: 2620 | G19: 100X120 | H19: 1750 | I19: OK | J19: BETA | K19: 105 | L19: 217
A20: CODETECH | B20: 43478 | C20: 43847 | D20: 1210 | E20: CINZA | F20: 2922 | G20: 100X150 | H20: 3000 | I20: OK | J20: BETA | K20: CINZA | L20: 459
A21: GRAFICA DEZ | B21: 43474 | C21: 43845 | D21: 1211 | E21: CINZA | F21: 2525 | G21: 105X1000 | H21: 1000 | I21: OK | J21: PINTAR
A22: GRAFICA DEZ | B22: 43474 | C22: 43845 | D22: 1211 | E22: AMARELO | F22: 2525 | G22: 105X1000 | H22: 1000 | I22: OK | J22: PINTAR
A23: FRIZZO | B23: 43475 | C23: 43840 | D23: 1212 | E23: COUCHE | F23: 879 | G23: 100X60 | H23: 20000 | I23: OK | J23: FACA | K23: 105 | L23: 1250
A24: FRIZZO | B24: 43475 | C24: 43843 | D24: 1213 | E24: COUCHE | F24: 2762 | G24: 25X16 | H24: 100000 | I24: OK | J24: FACA | K24: 105 | L24: 450
A25: FRIZZO | B25: 43478 | C25: 43843 | D25: 1214 | E25: COUCHE | F25: 869 | G25: 33X25 | H25: 210000 | I25: OK | J25: FACA | K25: 110 | L25: 1880
A26: MAR AZUL | B26: 43478 | C26: 43839 | D26: 1215 | E26: BOPP | F26: 2175 | G26: 30X80 | H26: 5000 | I26: OK | J26: BETA | K26: 100 | L26: 85
A27: WINELANDS | B27: 43844 | C27: 43840 | D27: 1219 | E27: COUCHE | F27: 2149 | G27: 70X40 | H27: 10000 | I27: OK | J27: BETA | K27: 75 | L27: 430
A28: CATAFESTA | B28: 43845 | C28: 43843 | D28: 1220 | E28: COUCHE | F28: 822 | G28: 50X50 | H28: 15000 | I28: OK | J28: FACA | K28: 108 | L28: 400
A29: FRIZZO | B29: 43480 | C29: 43840 | D29: 1216 | E29: COUCHE | F29: 822 | G29: 50X50 | H29: 50000 | I29: OK | J29: FACA | K29: 108 | L29: 1325 | M29: AUTOMATIZA
A30: ESTERELIZARE | B30: 43480 | C30: 43846 | D30: 1200 | E30: COUCHE | F30: 2913 | G30: 100X100 | H30: 50000 | I30: OK | J30: SERA PRODUZIDA FORA | K30: 108 | L30: 6000
A31: ESTERELIZARE | B31: 43480 | C31: 43846 | D31: 1200 | E31: COUCHE | F31: 2691 | G31: 100X50 | H31: 100000 | I31: OK | J31: SERA PRODUZIDA FORA | K31: 105 | L31: 6000
A32: GRAFICA DEZ | B32: 43480 | C32: 43846 | D32: 1209 | E32: COUCHE | F32: 2913 | G32: 100X100 | H32: 52400 | I32: OK | J32: SERA PRODUZIDA FORA
A33: GRAFICA DEZ | B33: 43480 | C33: 43846 | D33: 1209 | E33: COUCHE | F33: 2691 | G33: 100X50 | H33: 100980 | I33: OK | J33: SERA PRODUZIDA FORA
A34: OMEGA | B34: 43845 | C34: 43844 | D34: 1221 | E34: C.BORR | F34: 2586 | G34: 50X70 | H34: 50000 | I34: OK | J34: FACA | K34: 110 | L34: 1850
A35: FRIZZO | B35: 43840 | C35: 43838 | D35: 1222 | E35: VERMELHO | F35: 1548 | G35: 13X13 | H35: 50000 | I35: OK | J35: BETA
A36: FERREIRA | B36: 43840 | C36: 43839 | D36: 1227 | E36: DFAM | F36: 2935 | G36: 100X80 | H36: 10000 | I36: OK | J36: FACA
A37: GRAFICA 10 | B37: 43854 | C37: 43860 | D37: 1228 | E37: COUCHE | F37: 2805 | G37: 100X50 | H37: 10340 | I37: OK | J37: BRASILEIRINHO
A38: UNIMED | B38: 43846 | C38: 43844 | D38: 1229 | E38: COUCHE | F38: 2740 | G38: 90X36 | H38: 10000 | I38: OK | J38: FACA | K38: 100 | L38: 400
A39: MODAZINE | B39: 43482 | C39: 43846 | D39: 1206 | E39: TAG | F39: 2272 | G39: 35X62 | H39: 80000 | I39: OK | J39: SERA PRODUZIDA FORA
A40: GRAFICA DEZ | B40: 43482 | C40: 43846 | D40: 1206 | E40: TAG | F40: 2272 | G40: 35X62 | H40: 88000 | I40: OK | J40: SERA PRODUZIDA FORA
A41: MERIDIANO | B41: 43847 | C41: 43840 | D41: 1223 | E41: COUCHE | F41: 1018 | G41: 80X65 | H41: 6000 | I41: OK | J41: BETA | K41: 85 | L41: 410
A42: CODETECH | B42: 43847 | C42: 43840 | D42: 1226 | E42: COUCHE | F42: 2934 | G42: 20X40 | H42: 12000 | I42: OK | J42: BETA | K42: 90 | L42: 130
A43: MODAZINE | B43: 43853 | C43: 43846 | D43: 1230 | E43: TAG | F43: 2272 | G43: 35X62 | H43: 80000 | I43: OK | J43: SERA PRODUZIDA FORA
A44: GRAFICA DEZ | B44: 43853 | C44: 43846 | D44: 1230 | E44: TAG | F44: 2272 | G44: 35X62 | H44: 86000 | I44: OK | J44: SERA PRODUZIDA FORA
A45: SHOWCOLATS | B45: 43844 | C45: 43838 | D45: 1231 | E45: COUCHE | F45: 2937 | G45: 20X30 | H45: 300 | I45: OK | J45: BETA
A46: PLASMOSUL | B46: 43847 | C46: 43843 | D46: 1232 | E46: COUCHE | F46: 1397 | G46: 50X30 | H46: 2000 | I46: OK | J46: FACA | K46: 108 | L46: 40
A47: CATAFESTA | B47: 43846 | C47: 43839 | D47: 1233 | E47: COUCHE | F47: 2761 | G47: 100X80 | H47: 10000 | I47: OK | J47: FACA
A48: VISIOCLINICA | B48: 43847 | C48: 43843 | D48: 1234 | E48: COUCHE | F48: 2207 | G48: 75X15 | H48: 10000 | I48: OK | J48: BETA | K48: 80 | L48: 200
A49: DELTAFIRE | B49: 43850 | C49: 43843 | D49: 1235 | E49: BOPP | F49: 2771 | G49: 35X21 | H49: 25000 | I49: OK | J49: BETA | K49: 110 | L49: 200
A50: DELTAFIRE | B50: 43850 | C50: 43843 | D50: 1235 | E50: BOPP | F50: 1853 | G50: 100X35 | H50: 1000 | I50: OK | J50: BETA | K50: 105 | L50: 40
A51: DELTAFIRE | B51: 43850 | C51: 43843 | D51: 1235 | E51: BOPP | F51: 2775 | G51: 70X40 | H51: 1000 | I51: OK | J51: BETA | K51: 75 | L51: 43
A52: DILON | B52: 43850 | C52: 43838 | D52: 1236 | E52: BOPP BORR | F52: 2938 | G52: 8X25 | H52: 300 | I52: OK | J52: BETA
A53: CATAFESTA | B53: 43850 | C53: 43843 | D53: 1238 | E53: COUCHE | F53: 822 | G53: 50X50 | H53: 20000 | I53: OK | J53: FACA | K53: 108 | L53: 560
A54: VIA HOMEM | B54: 43850 | C54: 43839 | D54: 1239 | E54: AMARELO | F54: 2040 | G54: 40X30 | H54: 12000 | I54: OK | J54: BETA | K54: AMARELO | L54: 200
A55: VIA HOMEM | B55: 43850 | C55: 43844 | D55: 1239 | E55: COUCHE | F55: 2039 | G55: 40X55 | H55: 10000 | I55: OK | J55: FACA | K55: 85 | L55: 300
A56: REALITY | B56: 43850 | C56: 43844 | D56: 1240 | E56: COUCHE | F56: 838 | G56: 100X40 | H56: 20000 | I56: OK | J56: FACA | K56: 105 | L56: 860
A57: WELOSE | B57: 43851 | C57: 43843 | D57: 1241 | E57: BOPP | F57: 2568 | G57: 71X130 | H57: 1000 | I57: OK | J57: BETA | K57: 75 | L57: 135
A58: DOMAMA | B58: 43847 | C58: 43844 | D58: 1242 | E58: COUCHE | F58: 2515 | G58: 55X28 | H58: 12500 | I58: OK | J58: FACA | K58: 125 | L58: 195
A59: ACOMOLD | B59: 43850 | C59: 43844 | D59: 1243 | E59: COUCHE | F59: 838 | G59: 100X40 | H59: 5000 | I59: OK | J59: FACA
A60: ACOMOLD | B60: 43850 | C60: 43844 | D60: 1243 | E60: COUCHE | F60: 2515 | G60: 55X28 | H60: 7000 | I60: OK | J60: FACA
A61: CRIPPA | B61: 43850 | C61: 43851 | D61: 1244 | E61: COUCHE | F61: 1098 | G61: 90X80 | H61: 40000 | I61: OK | J61: FACA
A62: CATAFESTA | B62: 43850 | C62: 43847 | D62: 1245 | E62: BOPP | F62: 1363 | G62: 100X60 | H62: 5000 | I62: OK | J62: FACA
A63: ESB | B63: 43851 | C63: 43850 | D63: 1246 | E63: BOPP BORR | F63: 2329 | G63: 105X105 | H63: 3500 | I63: OK | J63: BETA
A64: OPEN WAY | B64: 43850 | C64: 43847 | D64: 1247 | E64: VERDE | F64: 1403 | G64: 100X60 | H64: 5000 | I64: OK | J64: FACA
A65: HIDRO | B65: 43850 | C65: 43847 | D65: 1248 | E65: TC | F65: 2940 | G65: 100X50 | H65: 200 | I65: OK | J65: AMOSTRA SHEILA
A66: HIDRO | B66: 43850 | C66: 43847 | D66: 1248 | E66: TC | F66: 2941 | G66: 50X20 | H66: 200 | I66: OK | J66: AMOSTRA SHEILA
A67: GRAFICA DEZ | B67: 43857 | C67: 43854 | D67: 1249 | E67: C.BORR | F67: 2162 | G67: 28X28 | H67: 14000 | I67: OK | J67: WINELANDS
A68: KELLER | B68: 43847 | C68: 43846 | D68: 1250 | E68: TERMICO | F68: 2942 | G68: 39X40 | H68: 50 | I68: OK | J68: FACA
A69: JONES | B69: 43854 | C69: 43860 | D69: 1251 | E69: TERMICO | F69: 2115 | G69: 39X40 | H69: 300 | I69: OK | J69: FACA
A70: ESTOQUE | B70: 43860 | C70: 43860 | D70: 1251 | E70: TERMICO | F70: 2115 | G70: 40X40 | H70: 15 | I70: OK
A71: BELA VISTA | B71: 43852 | C71: 43847 | D71: 1253 | E71: REMOVIVEL | F71: 2358 | G71: 100X60 | H71: 7000 | I71: OK | J71: FACA
A72: PANIZZON | B72: 43852 | C72: 43851 | D72: 1254 | E72: COUCHE | F72: 1545 | G72: 100X68 | H72: 15500 | I72: OK | J72: FACA
A73: CASA E CIA | B73: 43850 | C73: 43847 | D73: 1255 | E73: COUCHE | F73: 616 | G73: 40X30 | H73: 10000 | I73: OK | J73: BETA
A74: UNIMED | B74: 43852 | C74: 43844 | D74: 1256 | E74: COUCHE | F74: 2740 | G74: 90X36 | H74: 3000 | I74: OK | J74: FACA
A75: NATURALIFE | B75: 43883 | C75: 43846 | D75: 1257 | E75: TERMICO | F75: 2115 | G75: 39X40 | H75: 22 | I75: OK | J75: FACA
A76: BIOLUZ | B76: 43853 | C76: 43847 | D76: 1258 | E76: COUCHE | F76: 838 | G76: 100X40 | H76: 10000 | I76: OK | J76: FACA
A77: TOP LIMP | B77: 43853 | C77: 43844 | D77: 1259 | E77: COUCHE | F77: 2515 | G77: 55X28 | H77: 15000 | I77: OK | J77: FACA
A78: PEDRO SANZ | B78: 43853 | C78: 43851 | D78: 1260 | E78: BOPP | F78: 2555 | G78: 74X74 | H78: 10000 | I78: OK | J78: BETA
A79: PEDRO SANZ | B79: 43853 | C79: 43851 | D79: 1260 | E79: COUCHE | F79: 2774 | G79: 100X120 | H79: 2000 | I79: OK | J79: BETA
A80: VITAMED | B80: 43854 | C80: 43852 | D80: 1261 | E80: C.BORR | F80: 2581 | G80: 100X75 | H80: 24000 | I80: OK | J80: FACA
A81: REBITSUL | B81: 43854 | C81: 43851 | D81: 1262 | E81: COUCHE | F81: 1786 | G81: 90X25 | H81: 10500 | I81: OK | J81: FACA
A82: ARM. SÃO PEL | B82: 43845 | C82: 43845 | D82: 1265 | E82: TÉRMICA | F82: 2115 | G82: 40X40 | H82: 20 | I82: OK | J82: FACA
... A94: AKTU | B94: 43857 | C94: 43854 | D94: 1278 | E94: TERMICO | F94: 2948 | G94: 100X60 | H94: 7000 | I94: OK | J94: FACA
A95: FRIZZO | B95: 43857 | C95: 43857 | D95: 1279 | E95: COUCHE | F95: 2186 | G95: 90X40 | H95: 10000 | I95: OK | J95: BETA | K95: 95 | L95: 420
A96: FRIZZO | B96: 43857 | C96: 43857 | D96: 1281 | E96: AZUL | F96: 2945 | G96: 100X75 | H96: 1000 | I96: OK | J96: FACA
A97: FRIZZO | B97: 43857 | C97: 43857 | D97: 1281 | E97: AZUL | F97: 2946 | G97: 85X50 | H97: 1000 | I97: OK | J97: BETA
A98: GRAFICA DEZ | B98: 43853 | C98: 43853 | D98: 1282 | E98: AZUL | F98: 2525 | G98: 105X1000 | H98: 1 | I98: OK | J98: PINTAR
A99: SUSIN | B99: 43858 | C99: 43857 | D99: 1285 | E99: COUCHE | F99: 343 | G99: 50X22 | H99: 5000 | I99: OK | J99: BETA | K99: 108 | L99: 60
A100: FRIZZO | B100: 43858 | C100: 43857 | D100: 1286 | E100: COUCHE | F100: 855 | G100: 50X40 | H100: 150000 | I100: OK | J100: FACA | K100: 108 | L100: 3150
A101: FRIZZO | B101: 43858 | C101: 43860 | D101: 1287 | E101: TAG | F101: 2781 | G101: 55X75 | H101: 20000 | I101: OK | J101: BETA
A102: COMPUMIX | B102: 43858 | C102: 43857 | D102: 1288 | E102: COUCHE | F102: 2971 | G102: 100X48 | H102: 5000 | I102: OK | J102: BETA | K102: 105 | L102: 255
A103: COMPUMIX | B103: 43858 | C103: 43852 | D103: 1288 | E103: COUCHE | F103: 1468 | G103: 100X75 | H103: 5000 | I103: OK | J103: FACA | K103: 105 | L103: 390
A104: COMPUMIX | B104: 43858 | C104: 43857 | D104: 1288 | E104: COUCHE | F104: 2970 | G104: 89X23 | H104: 6000 | I104: OK | J104: BETA | K104: 95 | L104: 130
A105: SEXYFANTASY | B105: 43858 | D105: 1289 | E105: COUCHE | F105: 1087 | G105: 28X55 | H105: 60000 | I105: OK | J105: FACA | K105: 95 | L105: 1176
A106: FRIZZO | B106: 43859 | C106: 43859 | D106: 1291 | E106: COUCHE | F106: 1106 | G106: 45X35 | H106: 40000 | I106: OK | J106: BETA
A107: CASA SERRA | B107: 43859 | C107: 43858 | D107: 1292 | E107: TAG | F107: 2972 | G107: 100X40 | H107: 2500 | I107: OK | J107: BETA
A108: CASA SERRA | B108: 43859 | C108: 43858 | D108: 1292 | E108: TAG | F108: 2973 | G108: 50X40 | H108: 2000 | I108: OK | J108: BETA
A109: RR VISION | B109: 43859 | C109: 43832 | D109: 1293 | E109: BOPP | F109: 2844 | G109: 48X10 | H109: 10000 | I109: OK | J109: BETA
A110: HOSP. CIRCULO | B110: 43860 | C110: 43854 | D110: 1295 | E110: COUCHE | F110: 838 | G110: 100X40 | H110: 10000 | I110: OK | J110: FACA
A111: PROMARMO | B111: 43860 | C111: 43859 | D111: 1296 | E111: BOPP | F111: 2977 | G111: 105X200 | H111: 100 | I111: OK | J111: BETA
A112: FRIZZO | B112: 43851 | C112: 43851 | D112: 1283 | E112: COUCHE | F112: 869 | G112: 33X25 | H112: 55000 | I112: OK | J112: FACA | K112: URG
A113: FRIZZO | B113: 43852 | C113: 43852 | D113: 1298 | E113: BOPP | F113: 2172 | G113: 33X25 | H113: 60000 | I113: OK | J113: FACA | K113: URG
A114: CODETECH | B114: 43861 | C114: 43858 | D114: 1302 | E114: COUCHE | F114: 1412 | G114: 25X40 | H114: 30000 | I114: OK | J114: BETA
A115: FRIZZO | B115: 43861 | C115: 43854 | D115: 1303 | E115: COUCHE | F115: 908 | G115: 50X20 | H115: 10000 | I115: OK | J115: FACA
A116: ARCO | B116: 43861 | C116: 43857 | D116: 1307 | E116: COUCHE | F116: 1468 | G116: 100X75 | H116: 4000 | I116: OK | J116: FACA
...

Sheet FEVEREIRO20
A1: CLIENTE | B1: Data Entr | C1: Data Prod | D1: OC | E1: MATERIAL | F1: CÓDIGO | G1: ETIQUETA | H1: QUANT | I1: OK | J1: OBSERVAÇÕES | K1: TAMANHO | L1: METRO
A2: 3C | B2: 43874 | C2: 43866 | D2: 1309 | E2: REMOVIVEL | F2: 2987 | G2: 100X60 | H2: 5000 | I2: OK | J2: LARANJA
A3: GRAFICA DEZ | B3: 43874 | C3: 43866 | D3: 1314 | E3: REMOVIVEL | F3: 2381 | G3: 105X500 | H3: 500 | I3: OK | J3: LARANJA | L3: 43866
A4: DUKE | B4: 43864 | C4: 43864 | D4: 1310 | E4: COUCHE | F4: 2800 | G4: 45X45 | H4: 3000 | I4: OK | J4: BETA
A5: FRIZZO | B5: 43865 | C5: 43864 | D5: 1283 | E5: COUCHE | F5: 869 | G5: 33X25 | H5: 200000 | I5: OK | J5: FACA | K5: 110 | L5: 1880
A6: FRIZZO | B6: 43865 | C6: 43865 | D6: 1284 | E6: COUCHE | F6: 2664 | G6: 15X30 | H6: 200000 | I6: OK | J6: FACA | K6: 108 | L6: 1100
A7: IMEXPORT | B7: 43865 | C7: 43864 | D7: 1313 | E7: COUCHE | F7: 2854 | G7: 104X125 | H7: 5000 | I7: OK | J7: BETA
A8: GRAFICA DEZ | B8: 43868 | C8: 43888 | D8: 1315 | E8: TC | F8: 2749 | G8: 45X85 | H8: 11000 | I8: OK | J8: FARMBERRY
A9: G3 | B9: 43865 | C9: 43865 | D9: 1317 | E9: COUCHE | F9: 1397 | G9: 50X30 | H9: 35000 | I9: OK | J9: FACA
A10: HYVA | B10: 43866 | C10: 43864 | D10: 1320 | E10: C.BORR | F10: 2244 | G10: 100X60 | H10: 10000 | I10: OK | J10: FACA
A11: INJET | B11: 43866 | C11: 43866 | D11: 1321 | E11: B.BORR | F11: 2494 | G11: 25X25 | H11: 12400 | I11: OK | J11: BETA
A12: COMPUMIX | B12: 43866 | C12: 43865 | D12: 1333 | E12: COUCHE | F12: 1397 | G12: 50X30 | H12: 100000 | I12: OK | J12: FACA
A13: GRAFICA DEZ | B13: 43853 | C13: 43854 | D13: 1299 | E13: BOPP BORR | F13: 2669 | G13: 95X500 | H13: 4000 | I13: OK | J13: PINTAR 7 CORES
A14: FRIZZO | B14: 43867 | C14: 43864 | D14: 1326 | E14: COUCHE | F14: 1869 | G14: 33X21 | H14: 80000 | I14: OK | J14: FACA
A15: DIFLORES | B15: 43867 | C15: 43865 | D15: 1329 | E15: TAG | F15: 2993 | G15: 35X64 | H15: 30000 | I15: OK | J15: BETA
A16: FRIZZO | B16: 43867 | C16: 43875 | D16: 1330 | E16: COUCHE | F16: 2186 | G16: 90X40 | H16: 40000 | I16: OK | J16: FACA | M16: 15000 | N16: ESTOQUE
A17: PANIZZON | B17: 43864 | C17: 43864 | D17: 1334 | E17: COUCHE | F17: 1545 | G17: 100X68 | H17: 30000 | I17: OK | J17: FACA | K17: BRANCA
A18: PANIZZON | B18: 43864 | C18: 43864 | D18: 1334 | E18: COUCHE | F18: 2447 | G18: 100X68 | H18: 15000 | I18: OK | J18: FACA | K18: AMARELA
A19: PANIZZON | B19: 43864 | C19: 43881 | D19: 1334 | E19: COUCHE | F19: 2576 | G19: 100X68 | H19: 15000 | I19: OK | J19: FACA | K19: AZUL
A20: PANIZZON | B20: 43867 | C20: 43881 | D20: 1334 | E20: COUCHE | F20: 2818 | G20: 100X68 | H20: 15000 | I20: OK | J20: FACA | K20: ROSA
A21: PANIZZON | B21: 43864 | C21: 43881 | D21: 1334 | E21: COUCHE | F21: 2448 | G21: 100X68 | H21: 15000 | I21: OK | J21: FACA | K21: VERDE
A22: GRAFICA DEZ | B22: 43867 | C22: 43881 | D22: 1336 | E22: COUCHE | F22: 2525 | G22: 105X1000 | H22: 1 | I22: OK | J22: ROSA
A23: SERRANA | B23: 43867 | C23: 43867 | D23: 1335 | E23: COUCHE | F23: 1273 | G23: 55X28 | H23: 24000 | I23: OK | J23: PERSONALIZAR
A24: CORSUL | B24: 43868 | C24: 43866 | D24: 1337 | E24: COUCHE | F24: 2347 | G24: 50X150 | H24: 5000 | I24: OK | J24: BETA
A25: SCARIOT | B25: 43868 | C25: 43867 | D25: 1338 | E25: COUCHE | F25: 2064 | G25: 35X64 | H25: 20000 | I25: OK | J25: BETA
A26: BOISUL | B26: 43868 | C26: 43867 | D26: 1339 | E26: B.BORR | F26: 2632 | G26: 103X94 | H26: 5000 | I26: OK | J26: BETA
A27: BOISUL | B27: 43868 | C27: 43867 | D27: 1339 | E27: COUCHE | F27: 2039 | G27: 40X55 | H27: 5000 | I27: OK | J27: FACA
A28: GRAFICA DEZ | B28: 43868 | C28: 43881 | D28: 1341 | E28: COUCHE | F28: 2525 | G28: 105X1000 | H28: 1 | I28: OK | J28: VERDE
A29: GRAFICA DEZ | B29: 43868 | C29: 43881 | D29: 1342 | E29: COUCHE | F29: 2525 | G29: 105X1000 | H29: 1 | I29: OK | J29: VERMELHO
A30: MALH.DALANE | B30: 43874 | C30: 43873 | D30: 1343 | E30: TAG | F30: 2476 | G30: 35X60 | H30: 75000 | I30: OK | J30: BETA
A31: FRIZZO | B31: 43868 | C31: 43865 | D31: 1344 | E31: COUCHE | F31: 1468 | G31: 100X75 | H31: 5000 | I31: OK | J31: FACA
A32: VF ACESSORIOS | B32: 43868 | C32: 43864 | D32: 1346 | E32: COUCHE | F32: 1403 | G32: 100X60 | H32: 5000 | I32: OK | J32: FACA
A33: FRIZZO | B33: 43868 | C33: 43868 | D33: 1347 | E33: BOPP | F33: 785 | G33: 100X20 | H33: 5000 | I33: OK | J33: BETA
... A38: CAPPELLETTI | B38: 43871 | C38: 43868 | D38: 1351 | E38: COUCHE | F38: 2714 | G38: 33X25 | H38: 10000 | I38: OK | J38: FACA
A39: CASA E CIA | B39: 43871 | C39: 43871 | D39: 1352 | E39: COUCHE | F39: 3011 | G39: 40X30 | H39: 30000 | I39: OK | J39: BETA | K39: VERMELHO
A40: GRAFICA DEZ | B40: 43871 | C40: 43881 | D40: 1353 | E40: COUCHE | F40: 2525 | G40: 105X1.000 | H40: 4 | I40: OK | J40: PINTAR 4 CORES
A41: GRAFICA DEZ | B41: 43871 | C41: 43873 | D41: 1354 | E41: BOPP | F41: 2798 | G41: 78X30 | H41: 28400 | I41: OK | J41: RONI
A42: GRAFICA DEZ | B42: 43871 | C42: 43878 | D42: 1355 | E42: BOPP | F42: 2669 | G42: 95X1.000 | H42: 1 | I42: OK | J42: PINTAR 2 CORES | K42: FIXPAR
A43: TONIN | B43: 43871 | C43: 43868 | D43: 1356 | E43: COUCHE | F43: 3010 | G43: 100X180 | H43: 200 | I43: OK | J43: BETA
A44: PISO E TETO | B44: 43871 | C44: 43864 | D44: 1357 | E44: COUCHE | F44: 1869 | G44: 33X21 | H44: 10000 | I44: OK | J44: FACA
A45: ESTERELIZARE | B45: 43878 | C45: 43878 | D45: 3148 | E45: COUCHE | F45: 2691 | G45: 100X50 | H45: 100000 | I45: OK
A46: GRAFICA DEZ | B46: 43878 | C46: 43878 | D46: 1358 | E46: COUCHE | F46: 2691 | G46: 100X50 | H46: 106400 | I46: OK
A47: FRIZZO | B47: 43878 | C47: 43868 | D47: 1345 | E47: COUCHE | F47: 869 | G47: 33X25 | H47: 210000 | I47: OK | J47: FACA
A48: JONES | B48: 43878 | C48: 43875 | D48: 1251 | E48: TERMICO | F48: 2115 | G48: 39X40 | H48: 300 | I48: OK | J48: FACA
A49: estoque | B49: 43878 | C49: 43875 | D49: 1251 | E49: TERMICO | F49: 2115 | G49: 39X40 | H49: 100 | I49: OK | J49: FACA
A50: SPRAYJET | B50: 43868 | C50: 43868 | D50: 3149 | E50: TERMICO | F50: 3012 | G50: 100X150 | H50: 1000 | I50: OK | J50: BETA
A51: BP COMP | B51: 43873 | C51: 43880 | D51: 1360 | E51: POLIESTER | F51: 1183 | G51: 30X15 | H51: 10000 | I51: OK | J51: LABEL
A52: FRIZZO | B52: 43871 | C52: 43868 | D52: 3152 | E52: COUCHE | F52: 1869 | G52: 33X21 | H52: 80000 | I52: OK | J52: FACA
A53: FIXPAR | B53: 43874 | C53: 43878 | D53: 3156 | E53: BOPP | F53: 3013 | G53: 90X60 | H53: 2000 | I53: OK | J53: BETA | M53: COR
A54: FIXPAR | B54: 43874 | C54: 43878 | D54: 3156 | E54: BOPP | F54: 3014 | G54: 90X60 | H54: 2000 | I54: OK | J54: BETA | M54: COR
A55: POLIBOM | B55: 43873 | C55: 43866 | D55: 3159 | E55: BOPP | F55: 2807 | G55: 100x68 | H55: 10000 | I55: OK | J55: FACA
A56: POLIBOM | B56: 43873 | C56: 43866 | D56: 3159 | E56: COUCHE | F56: 2039 | G56: 40X55 | H56: 10000 | I56: OK | J56: FACA
A57: UNIMED | B57: 43874 | C57: 43866 | D57: 3164 | E57: COUCHE | F57: 2740 | G57: 90X36 | H57: 9000 | I57: OK | J57: FACA
A58: PLASMOSUL | B58: 43874 | C58: 43866 | D58: 3165 | E58: REMOVIVEL | F58: 3016 | G58: 50X30 | H58: 10000 | I58: OK | J58: FACA
A59: HOSP.CIRCULO | B59: 43874 | C59: 43866 | D59: 3168 | E59: COUCHE | F59: 838 | G59: 100X40 | H59: 10000 | I59: OK | J59: FACA
A60: CBL CABOS | B60: 43873 | C60: 43871 | D60: 3170 | E60: COUCHE | F60: 1350 | G60: 50X35 | H60: 10000 | I60: OK | J60: BETA
A61: SILVANA TORIANI | B61: 43874 | C61: 44175 | D61: 3171 | E61: BOPP | F61: 2743 | G61: 95X12 | H61: 2500 | I61: OK | J61: BETA
A62: MCC INFORMATICA | B62: 43874 | C62: 43871 | D62: 3172 | E62: TERMICO | F62: 2115 | G62: 40X40 | H62: 8 | I62: OK | J62: FACA
A63: BRASSUD | B63: 43874 | C63: 43871 | D63: 3173 | E63: COUCHE | F63: 1960 | G63: 35X40 | H63: 20000 | I63: OK | J63: FACA
A64: HOSP. BENEFICIENTE | B64: 43874 | C64: 43886 | D64: 3175 | E64: TERMICO | F64: 2875 | G64: 100X35 | H64: 10000 | I64: OK | J64: G10
A65: HOSP. BENEFICIENTE | B65: 43874 | C65: 43886 | D65: 3175 | E65: TERMICO | F65: 2876 | G65: 48X28 | H65: 21000 | I65: OK | J65: G10
A66: GRAFICA DEZ | B66: 43875 | C66: 43886 | D66: 1364 | E66: TERMICO | F66: 2875 | G66: 100X35 | H66: 10000 | I66: OK | J66: G10
... A83: INJET | B83: 43878 | C83: 43882 | D83: 3204 | E83: B.BORR | F83: 2494 | G83: 25X25 | H83: 2600 | I83: OK | J83: BETA
A84: VICENZI | B84: 43878 | C84: 43880 | D84: 3206 | E84: COUCHE | F84: 2498 | G84: 50X70 | H84: 5000 | I84: OK | J84: FACA | K84: PERSONAL
A85: TARDIAN | B85: 43878 | C85: 43873 | D85: 3207 | E85: BOPP | F85: 3029 | G85: 33X25 | H85: 15000 | I85: OK | J85: FACA | K85: PERSONAL
A86: FRIZZO | B86: 43889 | C86: 43878 | D86: 3198 | E86: COUCHE | F86: 1869 | G86: 33X21 | H86: 80000 | I86: OK | J86: FACA
A87: FRIZZO | B87: 43879 | C87: 43879 | D87: 3218 | E87: COUCHE | F87: 3038 | G87: 24X20 | H87: 15000 | I87: OK | J87: BETA
A88: COMPUMIX | B88: 43868 | C88: 43871 | D88: 3221 | E88: COUCHE | F88: 1555 | G88: 50X30 | H88: 100000 | I88: OK | J88: FACA
A89: ZBM | B89: 43879 | C89: 43878 | D89: 3208 | E89: COUCHE | F89: 3035 | G89: 100X16 | H89: 5000 | I89: OK | J89: BETA
A90: ZBM | B90: 43879 | C90: 43878 | D90: 3208 | E90: COUCHE | F90: 869 | G90: 33X25 | H90: 5000 | I90: OK | J90: FACA
A91: BLT | B91: 43879 | C91: 43878 | D91: 3209 | E91: TC | F91: 3028 | G91: 93X56 | H91: 5000 | I91: OK | J91: BETA
A92: CECATTP | B92: 43879 | C92: 43875 | D92: 3212 | E92: COUCHE | F92: 1614 | G92: 40X40 | H92: 40000 | I92: OK | J92: FACA
A93: DOLCEMONTE | B93: 43871 | C93: 43873 | D93: 3214 | E93: COUCHE | F93: 3036 | G93: 50X60 | H93: 10870 | I93: OK | J93: SUPERFLEXO
A94: AESC | B94: 43889 | C94: 43886 | D94: 3223 | E94: TERMICO | F94: 2873 | G94: 33X22 | H94: 25000 | I94: OK | J94: G10
A95: GRAFICA DEZ | B95: 43889 | C95: 43886 | D95: 1371 | E95: TERMICO | F95: 2873 | G95: 33X22 | H95: 48200 | I95: OK | J95: G10
A96: SHOWCOLATS | B96: 43889 | C96: 43880 | D96: 3224 | E96: COUCHE | F96: 3039 | G96: 70X50 | H96: 105000 | I96: OK | J96: FACA | K96: PERSONAL
A97: SHOWCOLATS | B97: 43889 | C97: 43880 | D97: 3224 | E97: COUCHE | F97: 3040 | G97: 50X40 | H97: 50000 | I97: OK | J97: FACA | K97: PERSONAL
A98: SHOWCOLATS | B98: 43889 | C98: 43888 | D98: 3224 | E98: COUCHE | F98: 794 | G98: 20X10 | H98: 105000 | I98: OK | J98: FACA
A99: SHOWCOLATS | B99: 43889 | C99: 43880 | D99: 3224 | E99: COUCHE | F99: 1869 | G99: 33X21 | H99: 100000 | I99: OK | J99: FACA
A100: FRIZZO | B100: 43872 | C100: 43871 | D100: 3233 | E100: COUCHE | F100: 3074 | G100: 32X70 | H100: 2000 | I100: OK | J100: BETA
A101: CALÇ.LABO | B101: 43880 | C101: 43878 | D101: 3229 | E101: TERMICO | F101: 3073 | G101: 90X25 | H101: 10000 | I101: OK | J101: FACA
A102: CEMTRA | B102: 43880 | C102: 43879 | D102: 3232 | E102: COUCHE | F102: 2691 | G102: 100X50 | H102: 4000 | I102: OK | J102: FACA
A103: BARRA DA SAIA | B103: 43880 | C103: 43878 | D103: 3235 | E103: COUCHE | F103: 908 | G103: 50X20 | H103: 10000 | I103: OK | J103: FACA
A104: SECTA | B104: 43880 | C104: 43875 | D104: 3239 | E104: COUCHE | F104: 1599 | G104: 90X25 | H104: 3000 | I104: OK | J104: FACA
A105: SIMONE FRANCO | B105: 43880 | C105: 43882 | D105: 3240 | E105: NYLON | F105: 2600 | G105: 29X76 | H105: 19000 | I105: OK | J105: FACA
A106: SÃO PELEGRINO | B106: 43873 | C106: 43873 | D106: 3258 | E106: TERMICO | F106: 2115 | G106: 40X40 | H106: 20 | I106: OK | J106: FACA
A107: LC SOLUCOES | B107: 43878 | C107: 43878 | D107: 3264 | E107: COUCHE | F107: 818 | G107: 50X70 | H107: 77000 | I107: OK | J107: FACA
A108: DOLCEMONTE | B108: 43881 | C108: 43879 | D108: 3245 | E108: COUCHE | F108: 992 | G108: 30X30 | H108: 25000 | I108: OK | J108: BETA
A109: DOLCEMONTE | B109: 43881 | C109: 43879 | D109: 3245 | E109: COUCHE | F109: 1960 | G109: 35X40 | H109: 9000 | I109: OK | J109: FACA
... A121: VESA | B121: 43882 | C121: 43882 | D121: 3272 | E121: C.BORR | F121: 1481 | G121: 105X105 | H121: 7950 | I121: OK | J121: BETA
A122: FRIZZO | B122: 43885 | C122: 43882 | D122: 3275 | E122: COUCHE | F122: 2759 | G122: 30X38 | H122: 30000 | I122: OK | J122: BETA | L122: 15000 | M122: 43881
A123: OMEGA | B123: 43885 | C123: 43878 | D123: 3285 | E123: C.BORR | F123: 2586 | G123: 50X70 | H123: 50000 | I123: OK | J123: FACA
A124: CAMII | B124: 43886 | C124: 43885 | D124: 3288 | E124: COUCHE | F124: 784 | G124: 30X15 | H124: 25000 | I124: OK | J124: BETA
A125: VITAMED | B125: 43886 | C125: 43875 | D125: 3291 | E125: COUCHE | F125: 838 | G125: 100X40 | H125: 25000 | I125: OK | J125: FACA
A126: GLOBALTECH | B126: 43887 | C126: 43885 | D126: 3300 | E126: COUCHE | F126: 616 | G126: 40X30 | H126: 5000 | I126: OK | J126: BETA
A127: LAÇO DE OURO | B127: 43887 | C127: 43880 | D127: 3303 | E127: C.BORR | F127: 2590 | G127: 100X40 | H127: 5000 | I127: OK | J127: FACA
A128: ASAVESSAS | B128: 43887 | C128: 43885 | D128: 3311 | E128: COUCHE | F128: 1104 | G128: 20X38 | H128: 10000 | I128: OK | J128: BETA
A129: HIDROVIL | B129: 43887 | C129: 43880 | D129: 3318 | E129: COUCHE | F129: 1098 | G129: 90X80 | H129: 5000 | I129: OK | J129: FACA
A130: RONI | B130: 43887 | C130: 43885 | D130: 3316 | E130: BOPP | F130: 2923 | G130: 80X45 | H130: 3000 | I130: OK | J130: BETA
A131: MCC INFORMATICA | B131: 43887 | C131: 43879 | D131: 3313 | E131: COUCHE | F131: 1614 | G131: 40X40 | H131: 8000 | I131: OK | J131: FACA
...

Sheet MARCO20
A1: CLIENTE | B1: Data Entr | C1: Data Prod | D1: OC | E1: MATERIAL | F1: CÓDIGO | G1: ETIQUETA | H1: QUANT | I1: OK | J1: OBSERVAÇÕES
A2: GRAFICA DEZ | B2: 43851 | C2: 43896 | D2: 1297 | E2: CASCA DE OVO | F2: 2976 | G2: 12,3X12,3 | H2: 15000 | I2: OK | J2: ATACASE
A3: HEMOVITA | B3: 43882 | C3: 43902 | D3: 3273 | E3: TERMICO | F3: 3082 | G3: 50X25 | H3: 64900 | I3: OK | J3: SEPARAR
A4: VITORIA | B4: 43900 | C4: 43902 | D4: 1404 | E4: TERMICO | F4: 3082 | G4: 50X25 | H4: 69600 | I4: OK | J4: CORTAR
A5: HEMOVITA | B5: 43882 | C5: 43900 | D5: 3273 | E5: TERMICO | F5: 3081 | G5: 100X120 | H5: 5000 | I5: OK
A6: VITORIA | B6: 43871 | C6: 43900 | D6: 1405 | E6: TERMICO | F6: 3081 | G6: 100X120 | H6: 7000 | I6: OK | J6: SEPARADA
A7: MODAZINE | B7: 43889 | C7: 43873 | D7: 3371 | E7: VERMELHA | F7: 2017 | G7: 33X21 | H7: 200000 | I7: OK | J7: FACA
A8: MODAZINE | B8: 43889 | C8: 43873 | D8: 3371 | E8: AMARELA | F8: 1785 | G8: 33X21 | H8: 155000 | I8: OK | J8: FACA
A9: CEACCATO | B9: 43893 | C9: 43892 | D9: 3363 | E9: COUCHE | F9: 3103 | G9: 90X53 | H9: 5000 | I9: OK | J9: BETA
A10: ECOMETAIS | B10: 43893 | C10: 43894 | D10: 3366 | E10: COUCHE | F10: 1007 | G10: 100X38 | H10: 30000 | I10: OK | J10: SEPARAR
A11: VITORIA | B11: 43894 | C11: 43892 | D11: 1397 | E11: COUCHE | F11: 1007 | G11: 100X38 | H11: 37000 | I11: OK | J11: CORTAR
A12: GRAFICA DEZ | B12: 43906 | C12: 43908 | D12: 1389 | E12: COUCHE | F12: 1904 | G12: 105X161 | H12: 11600 | I12: OK | J12: MODAZINE
A13: GRAFICA DEZ | B13: 43906 | C13: 43908 | D13: 1386 | E13: TAG | F13: 2272 | G13: 35X62 | H13: 167800 | I13: OK | J13: MODAZINE | K13: 47800 | L13: ESTOQ
A14: POLIBOM | B14: 43893 | C14: 43892 | D14: 3412 | E14: BOPP | F14: 2807 | G14: 100x68 | H14: 10000 | I14: OK | J14: FACA | M14: não foi dado entrada, só foi substituido para o cliente
A15: FRIZZO | B15: 43893 | C15: 43896 | D15: 3201 | E15: COUCHE | F15: 1106 | G15: 45X35 | H15: 47000 | I15: OK | J15: FACA NOVA
A16: CALSATY | B16: 43887 | C16: 43896 | D16: 3315 | E16: COUCHE | F16: 1106 | G16: 45X35 | H16: 6000 | I16: OK | J16: FACA NOVA
A17: HYVA | B17: 43866 | C17: 43893 | D17: 3382 | E17: TAG | F17: 2550 | G17: 100X70 | H17: 20000 | I17: OK | J17: BETA
A18: SUSIN | B18: 43895 | C18: 43893 | D18: 3386 | E18: COUCHE | F18: 343 | G18: 50X22 | H18: 5000 | I18: OK | J18: BETA
A19: MAR AZUL | B19: 43895 | C19: 43893 | D19: 3389 | E19: BOPP | F19: 2175 | G19: 30X80 | H19: 3000 | I19: OK | J19: BETA
A20: ZANLINE | B20: 43896 | C20: 43896 | D20: 3399 | E20: COUCHE | F20: 951 | G20: 100X150 | H20: 12190 | I20: OK | J20: SEPARAR
A21: VITORIA | B21: 43894 | C21: 43895 | D21: 1396 | E21: COUCHE | F21: 951 | G21: 100X150 | H21: 10000 | I21: OK | J21: CORTAR
A22: MODA VIVA | B22: 43896 | C22: 43896 | D22: 3405 | E22: COUCHE | F22: 2415 | G22: 33X39 | H22: 39000 | I22: OK | J22: SEPARAR
A23: VITORIA | B23: 43894 | C23: 43892 | D23: 1395 | E23: COUCHE | F23: 2415 | G23: 33X39 | H23: 25000 | I23: OK | J23: CORTAR
A24: LC SOLUCOES | B24: 43896 | C24: 43896 | D24: 3422 | E24: COUCHE | F24: 818 | G24: 50X70 | H24: 40800 | I24: OK | J24: FACA
A25: CODETECH | B25: 43896 | C25: 43896 | D25: 3430 | E25: COUCHE | F25: 1555 | G25: 50X30 | H25: 30000 | I25: OK | J25: FACA
A26: MUNDIAL | B26: 43899 | C26: 43901 | D26: 3413 | E26: C.BORR | F26: 2620 | G26: 100X120 | H26: 5250 | I26: OK | J26: VITORIA
... A34: FRIZZO | B34: 43888 | C34: 43901 | D34: 3279 | E34: COUCHE | F34: 2646 | G34: 50X35 | H34: 250000 | I34: OK | J34: GRAFICA DEZ
A35: GRAFICA DEZ | B35: 43887 | C35: 43901 | D35: 1376 | E35: COUCHE | F35: 2646 | G35: 50X35 | H35: 264400 | I35: OK
A36: GRAFICA DEZ | B36: 43889 | C36: 43894 | D36: 1372 | E36: COUCHE | F36: 2905 | G36: 25X25 | H36: 11300 | I36: OK | J36: SHOWCOLATS
A37: GRAFICA DEZ | B37: 43889 | C37: 43894 | D37: 1372 | E37: COUCHE | F37: 2906 | G37: 35X35 | H37: 30000 | I37: OK | J37: SHOWCOLATS
A38: GRAFICA DEZ | B38: 43889 | C38: 43894 | D38: 1372 | E38: COUCHE | F38: 3072 | G38: 45X45 | H38: 24000 | I38: OK | J38: SHOWCOLATS
A39: LC SOLUCOES | B39: 43899 | C39: 43894 | D39: 3429 | E39: TAG | F39: 625 | G39: 95X60 | H39: 5000 | I39: OK | J39: BETA
A40: RODER | B40: 43900 | C40: 43899 | D40: 3436 | E40: COUCHE | F40: 2209 | G40: 26X15 | H40: 20000 | I40: OK | J40: BETA
A41: RODER | B41: 43900 | C41: 43899 | D41: 3436 | E41: COUCHE | F41: 2528 | G41: 40X70 | H41: 10000 | I41: OK | J41: BETA
A42: FRIZZO | B42: 43900 | C42: 43899 | D42: 3438 | E42: COUCHE | F42: 879 | G42: 100X60 | H42: 40000 | I42: OK | J42: FACA
A43: SCUDO | B43: 43900 | C43: 43899 | D43: 3443 | E43: COUCHE | F43: 838 | G43: 100X40 | H43: 10000 | I43: OK | J43: FACA
A44: BERETTA | B44: 43900 | C44: 43900 | D44: 3449 | E44: BOPP | F44: 2490 | G44: 64X10 | H44: 6000 | I44: OK | J44: FACA
A45: BERETTA | B45: 43900 | C45: 43900 | D45: 3449 | E45: BOPP | F45: 2715 | G45: 64X10 | H45: 6000 | I45: OK | J45: FACA
A46: DOLCE VITA | B46: 43900 | C46: 43899 | D46: 3255 | E46: BOPP | F46: 3079 | G46: 40X40 | H46: 6000 | I46: OK | J46: BETA
A47: RIZZON | B47: 43901 | C47: 43900 | D47: 3455 | E47: COUCHE | F47: 1387 | G47: 100X68 | H47: 15000 | I47: OK | J47: FACA
... A49: SEXY FANTASY | B49: 43902 | C49: 43901 | D49: 3457 | E49: COUCHE | F49: 1087 | G49: 28X55 | H49: 67200 | I49: OK | J49: FACA
A50: JULIA MAZZOCHI | B50: 43902 | C50: 43902 | D50: 3458 | E50: COUCHE | F50: 838 | G50: 100X40 | H50: 20000 | I50: OK | J50: FACA | N50: AUTOMATIZA | O50: 43873
A51: JULIA MAZZOCHI | B51: 43902 | C51: 43903 | D51: 2069 | E51: COUCHE | F51: 2069 | G51: 34X25 | H51: 6000 | I51: OK | J51: BETA
A52: FRIZZO | B52: 43908 | C52: 43893 | D52: 3421 | E52: BOPP | F52: 2172 | G52: 33X25 | H52: 40000 | I52: OK | J52: FACA
A53: ARTIGIANALE | B53: 43902 | C53: 43900 | D53: 3462 | E53: COUCHE | F53: 2498 | G53: 50X70 | H53: 5000 | I53: OK | J53: FACA
A54: LC SOLUCOES | B54: 43902 | C54: 43901 | D54: 3096 | E54: BOPP | F54: 3096 | G54: 100X50 | H54: 10000 | I54: OK | J54: FACA
A55: BRASSUD | B55: 43902 | C55: 43901 | D55: 3468 | E55: COUCHE | F55: 1960 | G55: 35X40 | H55: 20000 | I55: OK | J55: FACA
A56: BRINDEC | B56: 43903 | C56: 43903 | D56: 3470 | E56: COUCHE | F56: 2515 | G56: 55X28 | H56: 50000 | I56: OK | J56: FACA
A57: WELOSE | B57: 43903 | C57: 43900 | D57: 3471 | E57: COUCHE | F57: 2396 | G57: 25X15 | H57: 15000 | I57: OK | J57: FACA
A58: VIO HOMEM | B58: 43903 | C58: 43900 | D58: 2040 | E58: AMARELA | F58: 2040 | G58: 40X30 | H58: 19300 | I58: OK | J58: VITORIA
A59: VITORIA | B59: 43901 | C59: 43900 | D59: 1408 | E59: AMARELA | F59: 2040 | G59: 40X30 | H59: 64300 | I59: OK | J59: VITORIA
A60: OMEGA | B60: 43903 | C60: 43900 | D60: 3478 | E60: VERMELHA | F60: 3125 | G60: 70X50 | H60: 5600 | I60: OK | J60: FACA
A61: TER BRASIL | B61: 43903 | C61: 43906 | D61: 3479 | E61: COUCHE | F61: 1126 | G61: 100X100 | H61: 20000 | I61: OK | J61: GV
A62: VITORIA | B62: 43902 | C62: 43903 | D62: 1412 | E62: COUCHE | F62: 1126 | G62: 100X100 | H62: 19400 | I62: OK | J62: PRONTA
... A65: VITORIA | B65: 43903 | C65: 43903 | D65: 1414 | E65: AMARELO | F65: 2756 | G65: 125X1.000 | H65: 1 | I65: OK | J65: PINTAR
A66: FRIZZO | B66: 43906 | D66: 3492 | E66: COUCHE | F66: 3128 | G66: 15X15 | H66: 300000 | I66: OK
A67: VITORIA | B67: 43903 | D67: 1419 | E67: COUCHE | F67: 3128 | G67: 15X15 | H67: 322500 | I67: OK | J67: PRONTA
A68: MALACARA | B68: 43906 | C68: 43900 | D68: 3496 | E68: TAG | F68: 1195 | G68: 50X75 | H68: 10000 | I68: OK | J68: BETA
A69: ZBM | B69: 43906 | C69: 43906 | D69: 3502 | E69: COUCHE | F69: 2811 | G69: 44X60 | H69: 5000 | I69: OK | J69: BETA
A70: ESTERELIZARE | B70: 43915 | C70: 43907 | D70: 3499 | E70: COUCHE | F70: 869 | G70: 33X25 | H70: 227500 | I70: ok | J70: FACA
A71: BIOLUZ | B71: 43907 | C71: 43901 | D71: 3503 | E71: BOPP | F71: 3131 | G71: 35X40 | H71: 12000 | I71: OK | J71: FACA
A72: PROVOQ | B72: 43902 | C72: 43901 | D72: 3500 | E72: COUCHE | F72: 1960 | G72: 35X40 | H72: 12000 | I72: OK | J72: FACA
A73: GRUPO EURO | B73: 43908 | C73: 43903 | D73: 3510 | E73: COUCHE | F73: 838 | G73: 100X40 | H73: 20000 | I73: OK | J73: FACA
A74: VF ACESSORIOS | B74: 43908 | C74: 43900 | D74: 3518 | E74: COUCHE | F74: 1438 | G74: 55X95 | H74: 5000 | I74: OK | J74: BETA
A75: RESET | B75: 43908 | C75: 43907 | D75: 3244 | E75: COUCHE | F75: 870 | G75: 100X36 | H75: 20000 | I75: OK | J75: BETA
A76: DELTA FERTIL | B76: 43908 | C76: 43907 | D76: 3524 | E76: BOPP | F76: 2771 | G76: 35X21 | H76: 15000 | I76: OK | J76: BETA
A77: GLOBALTECH | B77: 43908 | C77: 43908 | D77: 3300 | E77: COUCHE | F77: 616 | G77: 40X30 | H77: 10000 | I77: OK | J77: BETA
A78: BOI SUL | B78: 43908 | C78: 43908 | D78: 3213 | E78: TAG | F78: 2631 | G78: 75X263 | H78: 5000 | I78: OK | J78: BETA
A79: BOI SUL | B79: 43908 | C79: 43908 | D79: 3213 | E79: BOPP | F79: 2632 | G79: 103X94 | H79: 2000 | I79: OK | J79: BETA | K79: ENTREG | L79: PARC
A80: COMPUMIX | B80: 43909 | C80: 43909 | D80: 3527 | E80: COUCHE | F80: 2971 | G80: 100X48 | H80: 20000 | I80: OK
A81: VITORIA | B81: 43909 | C81: 43909 | D81: 1424 | E81: COUCHE | F81: 2971 | G81: 100X48 | H81: 24800 | I81: OK | J81: VITORIA
A82: TRACIATTI | B82: 43913 | C82: 43909 | D82: 3529 | E82: COUCHE | F82: 1292 | G82: 40X25 | H82: 50000 | I82: OK
A83: TRACIATTI | B83: 43913 | C83: 43909 | D83: 1426 | E83: COUCHE | F83: 1292 | G83: 40X25 | H83: 50000 | I83: OK | J83: VITORIA
A84: CENCI | B84: 43909 | C84: 43902 | D84: 3533 | E84: BOPP | F84: 2727 | G84: 33X21 | H84: 10000 | I84: OK | J84: FACA
A85: FRIZZO | B85: 43910 | C85: 43879 | D85: 3548 | E85: COUCHE | F85: 2186 | G85: 90X40 | H85: 53000 | I85: OK | J85: FACA
A86: CODETECH | B86: 43910 | C86: 43906 | D86: 3551 | E86: COUCHE | F86: 869 | G86: 33X25 | H86: 50000 | I86: OK | J86: FACA
A87: CODETECH | B87: 43910 | C87: 43906 | D87: 3551 | E87: COUCHE | F87: 855 | G87: 50X40 | H87: 82000 | I87: OK | J87: FACA
A88: SUPERLACK | B88: 43910 | C88: 43903 | D88: 3554 | E88: COUCHE | F88: 838 | G88: 100X40 | H88: 5000 | I88: OK | J88: FACA
A89: SUPER MARCAS | B89: 43913 | C89: 43909 | D89: 3564 | E89: COUCHE | F89: 1350 | G89: 50X35 | H89: 10000 | I89: OK | J89: BETA
A90: LC SOLUCOES | B90: 43910 | C90: 43909 | D90: 3579 | E90: BOPP | F90: 1363 | G90: 100X60 | H90: 10500 | I90: OK | J90: FACA
A91: LC SOLUCOES | B91: 43910 | C91: 43909 | D91: 3579 | E91: BOPP | F91: 1095 | G91: 100X50 | H91: 5000 | I91: OK | J91: FACA
A92: DAVIPLAST | B92: 43915 | C92: 43908 | D92: 3580 | E92: COUCHE | F92: 838 | G92: 100X40 | H92: 10000 | I92: ok | J92: FACA
A93: INJET | B93: 43907 | C93: 43908 | D93: 3583 | E93: BOPP | F93: 2494 | G93: 25X25 | H93: 10000 | I93: OK | J93: BETA
A94: PLASMOSUL | B94: 43915 | C94: 43909 | D94: 3584 | E94: REMOVIVEL | F94: 3016 | G94: 50X30 | H94: 20000 | I94: OK | J94: FACA
... A96: LAMINA | B96: 43916 | C96: 43909 | D96: 3605 | E96: COUCHE | F96: 885 | G96: 70X50 | H96: 21700 | I96: OK | J96: FACA
A97: LAMINA | B97: 43916 | C97: 43921 | D97: 3605 | E97: COUCHE | F97: 2450 | G97: 100X85 | H97: 10000 | I97: OK | J97: JUCA | K97: 43916
A98: VITORIA | B98: 43915 | C98: 43921 | D98: 1435 | E98: COUCHE | F98: 2450 | G98: 100X85 | H98: 10000 | I98: OK | J98: JUCA
A99: BANCO DE SANGUE | B99: 43913 | C99: 43909 | D99: 3609 | E99: BOPP | F99: 2467 | G99: 100X80 | H99: 4000 | I99: OK | J99: FACA
A100: FIXPAR | B100: 43920 | C100: 43910 | D100: 3623 | E100: COUCHE | F100: 753 | G100: 100X50 | H100: 100.00 | I100: OK | J100: FACA
A101: ESTERELIZARE | B101: 43915 | C101: 43921 | D101: 3499 | E101: COUCHE | F101: 2691 | G101: 100X50 | H101: 100000 | I101: OK | J101: FACA
A102: FRIZZO | B102: 3483 | D102: 3483 | E102: BOPP | F102: 2724 | G102: 25X16 | H102: 12000 | I102: OK | J102: FACA | K102: entregue 12000 | L102: OK
A103: INJET | B103: 43917 | C103: 43921 | D103: 3620 | E103: BOPP | F103: 2494 | G103: 25X25 | H103: 5000 | I103: OK | J103: BETA

Sheet JUNHO20
A1: CLIENTE | B1: Data Entr | C1: Data Prod | D1: O/F | E1: MATERIAL | F1: CÓDIGO | G1: ETIQUETA | H1: QUANT | I1: OK | J1: PRODUZIDO POR | K1: O/C | L1: VALOR
A2: MENG MORAN | B2: 43980 | C2: 43997 | D2: 3914 | E2: TC | F2: 3176 | G2: 50X90 | H2: 11700 | I2: OK | J2: G10 | K2: 1464 | L2: 1550
A3: JONES | B3: 43983 | C3: 43983 | D3: 3954 | E3: TERMICO | F3: 1442 | G3: 28X89 | H3: 25 | I3: OK | J3: LASER | L3: 300
A4: FRIZZO | B4: 43973 | D4: 3900 | E4: COUCHE | F4: 3174 | G4: 33X26 | H4: 50000 | I4: OK | J4: LASER
E5: REMOV | F5: 3175 | G5: 33X26 | H5: 44000 | I5: OK | J5: JUCA | K5: 1468 | L5: 580
A6: GLOBALTECH | B6: 43984 | C6: 43983 | D6: 3959 | E6: COUCHE | F6: 951 | G6: 100X150 | H6: 2000 | I6: OK | J6: LASER | L6: 210
A7: CODETECH | B7: 43984 | C7: 43984 | D7: 3971 | E7: BOPP | F7: 2719 | G7: 80X80 | H7: 5000 | I7: OK | J7: LASER | L7: 79
A8: AC LINK | B8: 43985 | C8: 43984 | D8: 3978 | E8: BOPP | F8: 2868 | G8: 85X10 | H8: 10000 | I8: OK | J8: LASER
E9: COUCHE | F9: 1397 | G9: 50X30 | H9: 10000 | I9: OK | J9: FACA | L9: 414
A10: SÃO CARLOS | B10: 43986 | C10: 43987 | D10: 3979 | E10: BOPP | F10: 1491 | G10: 100X23 | H10: 20000 | I10: OK | J10: JUCA | K10: 1466
E11: AMARELO | F11: 3162 | G11: 34X23 | H11: 16000 | I11: OK | J11: JUCA | K11: 1467
E12: VERMELHO | F12: 3163 | G12: 34X23 | H12: 16000 | I12: OK | J12: JUCA | K12: 1467 | L12: 668.7
A13: MAQENGE | B13: 43985 | C13: 43986 | D13: 3982 | E13: COUCHE | F13: 2720 | G13: 47X22 | H13: 25000 | I13: OK | J13: LASER | L13: 138
A14: GAMACOR | B14: 43986 | C14: 43985 | D14: 3984 | E14: COUCHE | F14: 1862 | G14: 100X35 | H14: 15000 | I14: OK | J14: LASER | L14: 358.5
A15: PLASMOSUL | B15: 43994 | C15: 43998 | D15: 3983 | E15: COUCHE | F15: 2559 | G15: 103X90 | H15: 4500 | I15: OK | J15: JUCA | K15: 1469 | L15: 415
A16: DILLIN | B16: 43987 | C16: 43984 | D16: 3985 | E16: COUCHE | F16: 1468 | G16: 100X75 | H16: 20000 | I16: OK | J16: LASER | L16: 1230
A17: BARAO | B17: 43990 | C17: 43987 | D17: 4000 | E17: COUCHE | F17: 3185 | G17: 50X100 | H17: 10400 | I17: OK | J17: LASER | L17: 240
A18: TRACIATTI | B18: 43987 | C18: 43984 | D18: 4002 | E18: COUCHE | F18: 951 | G18: 100X150 | H18: 5000 | I18: OK | J18: LASER | L18: 370
A19: BRASSUD | B19: 43987 | C19: 43984 | D19: 4009 | E19: COUCHE | F19: 1960 | G19: 35X40 | H19: 20000 | I19: OK | J19: FACA | L19: 442
A20: PETRYMAR | B20: 43997 | C20: 43984 | D20: 4010 | E20: COUCHE | F20: 753 | G20: 100X50 | H20: 20000 | I20: OK | J20: FACA | L20: 500
A21: POLIBOM | B21: 43985 | C21: 43985 | D21: 4019 | E21: COUCHE | F21: 2039 | G21: 40X55 | H21: 10500 | I21: OK | J21: FACA | L21: 171
A22: BOI SUL | B22: 43992 | C22: 43987 | D22: 4023 | E22: TAG | F22: 2631 | G22: 75X263 | H22: 5000 | I22: OK | J22: LASER
C23: 43985 | E23: COUCHE | F23: 2039 | G23: 40X55 | H23: 6000 | I23: OK | J23: FACA | L23: 938
A24: ZBM | B24: 43993 | C24: 43990 | D24: 4026 | E24: COUCHE | F24: 2811 | G24: 40X66 | H24: 5000 | I24: OK | J24: LASER
F25: 3035 | G25: 100X16 | H25: 5000 | I25: OK | J25: LASER
C26: 43985 | F26: 869 | G26: 33X25 | H26: 20000 | I26: OK | J26: FACA | L26: 148.203
A27: BANCO SANGUE | B27: 43986 | C27: 43985 | D27: 4027 | E27: BOPP | F27: 2467 | G27: 100X80 | H27: 4000 | I27: OK | J27: FACA | L27: 701.96
A28: SUPERLACK | B28: 43987 | C28: 43986 | D28: 4028 | E28: COUCHE | F28: 838 | G28: 100X40 | H28: 10000 | I28: OK | J28: FACA | L28: 134
A29: DOMAMA | B29: 43987 | C29: 43986 | D29: 4032 | E29: COUCHE | F29: 2515 | G29: 55X28 | H29: 10000 | I29: OK | J29: FACA | L29: 145
A30: RESET | B30: 43987 | C30: 43986 | D30: 4033 | E30: COUCHE | F30: 753 | G30: 100X50 | H30: 10400 | I30: OK | J30: FACA | L30: 230
A31: UP TO GO | B31: 43994 | C31: 43990 | D31: 4035 | E31: COUCHE | F31: 2971 | G31: 100X48 | H31: 200 | I31: OK | J31: LASER | L31: 5.42
A32: FRIZZO | B32: 43994 | D32: 4034 | E32: COUCHE | F32: 1126 | G32: 100X100 | H32: 5000 | I32: OK | J32: LASER | L32: 176.5
A33: SPIGOLON | B33: 43987 | C33: 43986 | D33: 4037 | E33: AMARELO | F33: 3189 | G33: 50X50 | H33: 6000 | I33: OK | J33: FACA | L33: 102.5
A34: ZANLINE | B34: 43997 | C34: 43998 | D34: 4038 | E34: COUCHE | F34: 951 | G34: 100X150 | H34: 10000 | I34: OK | J34: JUCA | K34: 1470 | L34: 670
C35: 43992 | D35: 4038 | E35: COUCHE | F35: 2266 | G35: 90X25 | H35: 7500 | I35: OK | J35: LASER | L35: 771.25
A36: ESTOQUE | B36: 43986 | C36: 43986 | D36: 0 | E36: COUCHE | F36: 838 | G36: 100X40 | H36: 17000 | I36: OK | J36: FACA
A37: HIDROQUIMICA | B37: 43997 | C37: 43992 | D37: 4041 | E37: BOPP | F37: 1255 | G37: 100X200 | H37: 5000 | I37: OK | J37: LASER | L37: 717.5
A38: VITAMED | B38: 43991 | C38: 43990 | D38: 4047 | E38: COUCHE | F38: 838 | G38: 100X40 | H38: 40000 | I38: OK | J38: FACA | L38: 1505
A39: CODETECH | B39: 43992 | C39: 43991 | D39: 4048 | E39: COUCHE | F39: 855 | G39: 50X40 | H39: 50000 | I39: OK | J39: FACA
E40: COUCHE | F40: 869 | G40: 33X25 | H40: 50000 | I40: OK | J40: FACA | L40: 675
A41: FRIZZO | B41: 43994 | C41: 43992 | D41: 4051 | E41: COUCHE | F41: 855 | G41: 50X40 | H41: 30000 | I41: OK | J41: FACA
C42: 43997 | E42: COUCHE | F42: 879 | G42: 100X60 | H42: 20000 | I42: OK | J42: FACA | L42: 681
A43: FRIZZO | B43: 43998 | C43: 43992 | D43: 4052 | E43: TAG | F43: 2781 | G43: 55X75 | H43: 20000 | I43: OK | J43: LASER | L43: 310
A44: FITAS REAL | B44: 43994 | C44: 43990 | D44: 4054 | E44: C.BORR | F44: 2438 | G44: 100X50 | H44: 10400 | I44: OK | J44: FACA | L44: 250.5
A45: ERV.CENTRAL | B45: 43994 | C45: 43991 | D45: 4059 | E45: COUCHE | F45: 869 | G45: 33X25 | H45: 40000 | I45: OK | J45: FACA | L45: 204
A46: ESTOQUE | B46: 43990 | C46: 43990 | D46: 0 | E46: COUCHE | F46: 1869 | G46: 33X21 | H46: 25000 | I46: OK | J46: SHEILA | K46: E FRIZZO
A47: DUKE | B47: 43990 | C47: 43990 | D47: 4060 | E47: COUCHE | F47: 2800 | G47: 45X45 | H47: 3000 | I47: OK | J47: LASER | L47: 104
A48: FRIZZO | B48: 43997 | C48: 43992 | D48: 4068 | E48: COUCHE | F48: 1468 | G48: 100X75 | H48: 20000 | I48: OK | J48: FACA
F49: 855 | G49: 50X40 | H49: 20000 | I49: OK | J49: FACA
F50: 908 | G50: 50X20 | H50: 10000 | I50: OK | J50: FACA | L50: 897.5
A51: SUSIN | B51: 43998 | C51: 43997 | D51: 4070 | E51: COUCHE | F51: 343 | G51: 50X22 | H51: 5000 | I51: OK | J51: LASER | L51: 175
A52: DALLE MOLLE | B52: 43992 | C52: 43992 | D52: 4013 | E52: COUCHE | F52: 3192 | G52: 33X21 | H52: 5000 | I52: OK | J52: FACA | L52: 35
A53: METALLI | B53: 43992 | C53: 43992 | D53: 4079 | E53: BOPP | F53: 1483 | G53: 100X40 | H53: 200 | I53: OK | J53: FACA | L53: 9.04
A54: RIGOTTO | B54: 43998 | C54: 43997 | D54: 4074 | E54: COUCHE | F54: 2572 | G54: 100X148 | H54: 1000 | I54: OK | J54: LASER | L54: 68.38
A55: BOSS | B55: 43998 | C55: 43997 | D55: 4085 | E55: COUCHE | F55: 753 | G55: 100X50 | H55: 5600 | I55: OK | J55: FACA | L55: 147.5
C56: 43998 | D56: 4085 | E56: BOPP | F56: 1095 | G56: 100X50 | H56: 5000 | I56: OK | J56: FACA | L56: 147.5
A57: RIVA | B57: 43999 | C57: 43999 | D57: 4082 | E57: COUCHE | F57: 2760 | G57: 100X35 | H57: 18000 | I57: OK | J57: LASER | L57: 428.4
A58: FIXPAR | C58: 44011 | D58: 4087 | E58: BOPP BORR | F58: 3096 | G58: 100X50 | H58: 9000 | I58: ok | J58: FACA | K58: 7 CORES | L58: 392.1
C59: 44008 | D59: 0 | E59: BOPP BORR | F59: 0 | G59: 107X1000 | H59: 3670 | I59: OK | J59: G10 | K59: 1471 | L59: 245
A60: COMPUMIX | B60: 44000 | C60: 43999 | D60: 4086 | E60: COUCHE | F60: 2970 | G60: 89X23 | H60: 21000 | I60: OK | J60: LASER | L60: 828
A61: SIRLEY M | B61: 43999 | C61: 43997 | D61: 4090 | E61: COUCHE | F61: 2515 | G61: 55X28 | H61: 7500 | I61: OK | J61: FACA | L61: 102.5
A62: MALACARA | B62: 44001 | C62: 43999 | D62: 4098 | E62: COUCHE | F62: 1195 | G62: 50X75 | H62: 10000 | I62: OK | J62: LASER | L62: 420
A63: CASA E CIA | B63: 44001 | C63: 44000 | D63: 4099 | E63: COUCHE | F63: 616 | G63: 40X30 | H63: 10000 | I63: OK | J63: LASER | L63: 129.6
A64: JULIANA | B64: 44004 | C64: 44004 | D64: 4100 | E64: COUCHE | F64: 2069 | G64: 34X25 | H64: 20000 | I64: OK | J64: LASER | L64: 260
A65: FOODCHAIN | B65: 44004 | C65: 44004 | D65: 4102 | E65: BOPP | F65: 3201 | G65: 33X10 | H65: 5000 | I65: OK | J65: LASER
F66: 1169 | G66: 100X30 | H66: 1000 | I66: OK | J66: LASER | L66: 36
A67: PEDRO SANZ | B67: 44004 | C67: 44000 | D67: 4104 | E67: BOPP | F67: 2555 | G67: 74X74 | H67: 10000 | I67: OK | J67: LASER | L67: 680
A68: G3 | B68: 44000 | C68: 43999 | D68: 4106 | E68: COUCHE | F68: 1397 | G68: 50X30 | H68: 35000 | I68: OK | J68: FACA | L68: 280
A69: MAR AZUL | B69: 44005 | C69: 44005 | D69: 4107 | E69: BOPP | F69: 2175 | G69: 30X80 | H69: 2000 | I69: OK | J69: LASER | L69: 70
A70: ORIGIN | B70: 44005 | C70: 44004 | D70: 4111 | E70: REMOV | F70: 2578 | G70: 60X20 | H70: 20000 | I70: OK | J70: LASER | L70: 510
A71: ECOMETAIS | B71: 44005 | C71: 44001 | D71: 4113 | E71: COUCHE | F71: 1007 | G71: 100X38 | H71: 30000 | I71: OK | J71: LASER | L71: 684
A72: VITAMED | B72: 44004 | C72: 44001 | D72: 4123 | E72: C.BORR | F72: 2581 | G72: 100X75 | H72: 29000 | I72: OK | J72: FACA | L72: 792
A73: VF ACESSORIOS | B73: 44006 | C73: 44005 | D73: 4124 | E73: COUCHE | F73: 1438 | G73: 55X95 | H73: 7500 | I73: OK | J73: LASER | L73: 345.75
A74: FRIZZO | B74: 44001 | C74: 44001 | D74: 4135 | E74: COUCHE | F74: 1468 | G74: 100X75 | H74: 5000 | I74: OK | J74: FACA | L74: 137.5
A75: OMEGA | B75: 44004 | C75: 44004 | D75: 4141 | E75: COUCHE | F75: 3125 | G75: 70X50 | H75: 10000 | I75: OK | J75: FACA | L75: 220
A76: RESET | B76: 44007 | C76: 44005 | D76: 4149 | E76: C.BORR | F76: 3207 | G76: 90X50 | H76: 3200 | I76: OK | J76: LASER
C77: 44005 | E77: C.BORR | F77: 3208 | G77: 30X15 | H77: 5000 | I77: OK | J77: LASER | L77: 113.9
A78: FRIZZO | B78: 44008 | C78: 44006 | D78: 4150 | E78: COUCHE | F78: 1467 | G78: 85X50 | H78: 5100 | I78: OK | J78: FACA | L78: 87.75
A79: INJET | B79: 44011 | C79: 44006 | D79: 4152 | E79: BOPP | F79: 2494 | G79: 25X25 | H79: 15000 | I79: OK | J79: LASER | L79: 550
A80: SEXY FANTASY | B80: 44012 | C80: 44006 | D80: 4153 | E80: COUCHE | F80: 2825 | G80: 106X85 | H80: 4000 | I80: OK | J80: LASER
E81: COUCHE | F81: 1087 | G81: 28X55 | H81: 40000 | I81: OK | J81: FACA
E82: COUCHE | F82: 2639 | G82: 15X30 | H82: 40000 | I82: OK | J82: FACA | L82: 821.86
A83: UNIMED | B83: 44012 | C83: 44007 | D83: 4154 | E83: TAG | F83: 2107 | G83: 60X30 | H83: 20000 | I83: OK | J83: LASER | L83: 756
A84: LAMINA | B84: 44027 | C84: 44004 | D84: 3848 | E84: COUCHE | F84: 885 | G84: 70X50 | H84: 30100 | I84: OK | J84: FACA | L84: 450
A85: FRIZZO | B85: 44005 | C85: 44005 | D85: 4155 | E85: COUCHE | F85: 1126 | G85: 100X100 | H85: 5200 | I85: OK | J85: FACA | L85: 176.5
A86: EST. ITALIA | B86: 44011 | C86: 44007 | D86: 4163 | E86: C.BORR | F86: 2438 | G86: 100X50 | H86: 7200 | I86: OK | J86: FACA | L86: 320
A87: OMEGA | B87: 44011 | C87: 44007 | D87: 4165 | E87: COUCHE | F87: 885 | G87: 70X50 | H87: 10500 | I87: OK | J87: FACA | K87: LAMINA | L87: 220
A88: FRIZZO | B88: 44008 | C88: 44006 | D88: 4157 | E88: COUCHE | F88: 753 | G88: 100X50 | H88: 5600 | I88: OK | J88: FACA | L88: 115
A89: FRIZZO | B89: 44005 | C89: 44006 | D89: 4171 | E89: COUCHE | F89: 1126 | G89: 100x100 | H89: 5200 | I89: OK | J89: FACA | L89: 176.5
A90: RESET | B90: 44007 | C90: 44006 | D90: 4178 | E90: COUCHE | F90: 822 | G90: 50X50 | H90: 20000 | I90: OK | J90: FACA | L90: 260
A91: EBS | B91: 44011 | C91: 44007 | D91: 4172 | E91: BOPP BORR | F91: 2329 | G91: 105X105 | H91: 4000 | I91: OK | J91: LASER | L91: 474.8
A92: DOLCEMONTE | B92: 44012 | C92: 44011 | D92: 4177 | E92: COUCHE | F92: 992 | G92: 30X30 | H92: 10000 | I92: OK
E93: COUCHE | F93: 3210 | G93: 66X25 | H93: 21000 | I93: OK
E94: BOPP | F94: 3211 | G94: 90X90 | H94: 2000 | I94: OK
E95: COUCHE | F95: 3212 | G95: 40X40 | H95: 10000 | I95: OK
E96: COUCHE | F96: 3213 | G96: 30X30 | H96: 10000 | I96: OK
E97: COUCHE | F97: 3214 | G97: 10X10 | H97: 10000 | I97: OK | L97: 577.6
A98: HYVA | B98: 44012 | C98: 44008 | D98: 4179 | E98: TAG | F98: 2550 | G98: 100X70 | H98: 10000 | I98: OK | J98: LASER | L98: 720
A99: SULPACK | B99: 44012 | C99: 44007 | D99: 4180 | E99: BOPP | F99: 1170 | G99: 100X30 | H99: 2000 | I99: OK | J99: LASER
E100: BOPP | F100: 1156 | G100: 20X20 | H100: 3000 | I100: OK | J100: LASER
...

Sheet JULHO20
A1: CLIENTE | B1: Data Entr | C1: Data Prod | D1: O/F | E1: MATERIAL | F1: CÓDIGO | G1: ETIQUETA | H1: MILHEIRO | I1: OK | J1: PRODUZIDO POR | K1: O/C | L1: VALOR
A2: BARAO | B2: 44012 | C2: 44005 | D2: 4143 | E2: COUCHE | F2: 822 | G2: 50X50 | H2: 51 | I2: OK | J2: FACA
C3: 44021 | D3: 3185 | E3: COUCHE | F3: 3185 | G3: 50X100 | H3: 56.4 | I3: OK | J3: G10 | K3: 1472
A4: POLIBOM | B4: 44012 | C4: 44013 | D4: 4194 | E4: COUCHE | F4: 3152 | G4: 100X200 | H4: 10 | I4: OK | J4: JUCA | K4: 1473
C5: 44011 | E5: COUCHE | F5: 2039 | G5: 40X55 | H5: 51 | I5: OK | J5: FACA
C6: 44011 | E6: BOPP | F6: 2807 | G6: 100X66 | H6: 10.2 | I6: OK | J6: FACA | K6: 100X68 | L6: 2524
A7: TRACIATTI | B7: 44015 | C7: 44014 | D7: 4209 | E7: NYLON | F7: 2600 | G7: 29X76 | H7: 22 | I7: OK | J7: FACA | L7: 875
A8: MAR AZUL | B8: 44014 | C8: 44014 | D8: 4212 | E8: BOPP | F8: 2175 | G8: 30X80 | H8: 2 | I8: OK | J8: lASER | L8: 70
A9: FRIZZO | B9: 44018 | C9: 44022 | D9: 4216 | E9: COUCHE | F9: 869 | G9: 33X25 | H9: 200 | I9: OK | J9: FACA | L9: 720
A10: ESTOQUE | B10: 44021 | C10: 44021 | D10: 4216 | E10: COUCHE | F10: 869 | G10: 33X25 | H10: 95 | I10: OK | J10: FACA | L10: 0
A11: CRIPPA | B11: 44014 | C11: 44013 | D11: 4220 | E11: COUCHE | F11: 1098 | G11: 90X80 | H11: 40 | I11: OK | J11: FACA | L11: 1200
A12: PETRYMAR | B12: 44018 | C12: 44018 | D12: 4222 | E12: COUCHE | F12: 753 | G12: 100X50 | H12: 20 | I12: OK | J12: FACA | L12: 500
A13: IPICARD | B13: 44014 | C13: 44013 | D13: 4224 | E13: BOPP | F13: 1911 | G13: 34X25 | H13: 5 | I13: OK | J13: FACA | K13: 33X25 | L13: 207
A14: INSINUANTE | B14: 44015 | C14: 44015 | D14: 4218 | E14: COUCHE | F14: 616 | G14: 40X30 | H14: 50 | I14: OK | J14: LASER
E15: AMARELO | F15: 2040 | G15: 40X30 | H15: 45 | I15: OK | J15: LASER | L15: 615
A16: DUKE | B16: 44019 | C16: 44014 | D16: 4232 | E16: COUCHE | F16: 2800 | G16: 45X45 | H16: 4.4 | I16: OK | J16: LASER | K16: PERS | L16: 104
A17: URSULA | B17: 44019 | C17: 44018 | D17: 4233 | E17: BOPP | F17: 3219 | G17: 109X25 | H17: 10.5 | I17: OK | J17: LASER | L17: 460
A18: AFETTO | B18: 44020 | C18: 44015 | D18: 4234 | E18: COUCHE | F18: 879 | G18: 100X60 | H18: 10 | I18: OK | J18: FACA
E19: REMOV | F19: 2983 | G19: 100X60 | H19: 25 | I19: OK | J19: FACA
E20: REMOV | F20: 3179 | G20: 80X40 | H20: 5 | I20: OK | J20: LASER | L20: 1557.5
A21: PANIZZON | B21: 44021 | C21: 44015 | D21: 4239 | E21: COUCHE | F21: 1545 | G21: 100X68 | H21: 2 | I21: OK | J21: FACA
E22: AMARELO | F22: 2447 | G22: 100X68 | H22: 3 | I22: OK | J22: FACA
E23: LARANJA | F23: 2589 | G23: 100X68 | H23: 3 | I23: OK | J23: FACA
E24: AZUL | F24: 2576 | G24: 100X68 | H24: 1 | I24: OK | J24: FACA
E25: VERDE | F25: 2448 | G25: 100X68 | H25: 3 | I25: OK | J25: FACA | L25: 616.6
A26: CORSUL | B26: 44019 | C26: 44019 | D26: 4245 | E26: COUCHE | F26: 2347 | G26: 50X150 | H26: 5 | I26: OK | J26: LASER | L26: 207.3
A27: SULPACK | B27: 44019 | C27: 44018 | D27: 4246 | E27: BOPP | F27: 1401 | G27: 50X22 | H27: 9 | I27: OK | J27: LASER | L27: 335
A28: BIOLUZ | B28: 44020 | D28: 4247 | E28: BOPP | F28: 3131 | G28: 35X40 | H28: 30 | I28: OK | J28: FACA | L28: 453.6
A29: ESTOQUE | B29: 44018 | E29: BOPP | F29: 1095 | G29: 100X50 | H29: 7.2 | I29: OK | J29: FACA | L29: 0
A30: TEODORO | B30: 44020 | C30: 44019 | D30: 4250 | E30: COUCHE | F30: 1140 | G30: 44X16 | H30: 20 | I30: OK | J30: LASER
E31: POLIESTER | F31: 1019 | G31: 34X51 | H31: 6 | I31: OK | J31: LASER | L31: 586
A32: FRIZZO | B32: 44020 | C32: 44019 | D32: 4260 | E32: TAG | F32: 2708 | G32: 33X145 | H32: 3 | I32: OK | J32: LASER | L32: 55.5
A33: FRIZZO | B33: 44021 | C33: 44019 | D33: 4261 | E33: BOPP | F33: 3129 | G33: 50X18 | H33: 8 | I33: OK | J33: LASER | L33: 71.6
A34: DI FARR | B34: 44021 | C34: 44020 | D34: 4262 | E34: COUCHE | F34: 1397 | G34: 50X30 | H34: 50 | I34: OK | J34: FACA | L34: 470
A35: BARAO | B35: 44022 | C35: 44020 | D35: 4263 | E35: COUCHE | F35: 2577 | G35: 100X40 | H35: 3 | I35: OK | J35: FACA | K35: PERS | L35: 69
A36: SIMONE FRANCO | B36: 44025 | C36: 44019 | D36: 4264 | E36: NYLON | F36: 2600 | G36: 29X76 | H36: 16.5 | I36: OK | J36: FACA | M36: 4.000 OK
A37: FRIZZO | B37: 44025 | C37: 44019 | D37: 0 | E37: COUCHE | F37: 1468 | G37: 100X75 | H37: 20 | I37: OK | J37: FACA | L37: REPOR
A38: FRIZZO | B38: 44025 | C38: 44019 | D38: 4269 | E38: BOPP | F38: 2724 | G38: 25X16 | H38: 10 | I38: OK | J38: FACA | L38: 45.5
A39: FRIZZO | B39: 44027 | C39: 44018 | D39: 4063 | E39: COUCHE | F39: 1869 | G39: 33X21 | H39: 80 | I39: OK | J39: FACA | L39: 264
A40: HOSP. SC | B40: 44029 | D40: 4271 | E40: COUCHE | F40: 843 | G40: 34X23 | H40: 200 | I40: OK | J40: FACA | K40: NOVA
B41: 44029 | E41: VERMELHO | F41: 3163 | G41: 34X23 | H41: 108 | I41: OK | J41: FACA | K41: NOVA | L41: 1412.4
A42: LAIMED | B42: 44022 | C42: 44020 | D42: 4273 | E42: COUCHE | F42: 2927 | G42: 90X85 | H42: 1 | I42: OK | J42: LASER | L42: 90.5
A43: HYVA | B43: 44026 | C43: 44020 | D43: 4276 | E43: C.BORR | F43: 1712 | G43: 50X50 | H43: 9 | I43: OK | J43: FACA | L43: 277.5
A44: ESTOQUE | B44: 44020 | C44: 44020 | D44: 4276 | E44: COUCHE | F44: 2422 | G44: 50X50 | H44: 7.5 | I44: OK | J44: FACA
A45: CODETECH | B45: 44029 | C45: 44021 | D45: 4281 | E45: BOPP | F45: 2868 | G45: 85X10 | H45: 25 | I45: OK | J45: LASER | L45: 300
A46: SPIGOLON | B46: 44022 | C46: 44021 | D46: 4280 | E46: AMARELO | F46: 3102 | G46: 33X25 | H46: 10 | I46: OK | J46: FACA
E47: TAG | F47: 3184 | G47: 47,5X35 | H47: 4 | I47: OK | J47: LASER | L47: 185.6
A48: FRIZZO | B48: 44022 | C48: 44021 | D48: 4282 | E48: TAG | F48: 3074 | G48: 32X70 | H48: 2 | I48: OK | J48: LASER | L48: 18.9
A49: NEUSA | B49: 44022 | C49: 44021 | D49: 4279 | E49: BOPP | F49: 2172 | G49: 33X25 | H49: 10 | I49: OK | J49: FACA | L49: 105
A50: MAQENGE | B50: 44026 | C50: 44022 | D50: 4290 | E50: COUCHE | F50: 2720 | G50: 47X22 | H50: 27 | I50: OK | J50: LASER | L50: 110.4
A51: WELOZE | B51: 44025 | C51: 44021 | D51: 4293 | E51: COUCHE | F51: 2396 | G51: 25X15 | H51: 15 | I51: OK | J51: LASER | L51: 36.75
A52: FRIZZO | B52: 44026 | C52: 44025 | D52: 4295 | E52: COUCHE | F52: 1545 | G52: 100X68 | H52: 20 | I52: OK | J52: FACA | L52: 483
A53: VITAMED | B53: 44026 | C53: 44022 | E53: COUCHE | F53: 838 | G53: 100X40 | H53: 43 | I53: OK | J53: FACA | L53: 1400
A54: EMBASUL | B54: 44027 | C54: 44025 | D54: 4288 | E54: COUCHE | F54: 2761 | G54: 100X80 | H54: 5 | I54: OK | J54: FACA | L54: 232
A55: BCK | B55: 44022 | C55: 44022 | D55: 4313 | E55: COUCHE | F55: 838 | G55: 100X40 | H55: 3 | I55: OK | J55: FACA | L55: 72
A56: BANCO SANGUE | B56: 44027 | D56: 4319 | E56: BOPP | F56: 2467 | G56: 100X80 | H56: 2 | I56: OK | J56: FACA
E57: COUCHE | F57: 2515 | G57: 55X28 | H57: 5 | I57: OK | J57: FACA | L57: 219.48
A58: HUGO PIETRO | B58: 44033 | C58: 44029 | D58: 4277 | E58: COUCHE | F58: 2264 | G58: 80X60 | H58: 80.5 | I58: OK | J58: LASER | L58: 1760
A59: UNIMED | B59: 44026 | C59: 44025 | D59: 4323 | E59: COUCHE | F59: 2740 | G59: 90X36 | H59: 10 | I59: OK | J59: FACA | L59: 148
A60: ZANLINE | B60: 44032 | C60: 44033 | D60: 4314 | E60: COUCHE | F60: 951 | G60: 100X150 | H60: 10 | I60: OK | J60: G10 | K60: 1476
A61: FRIZZO | B61: 44027 | C61: 44027 | D61: 4296 | E61: COUCHE | F61: 2792 | G61: 70X15 | H61: 40 | I61: OK | J61: LASER | L61: 212
A62: FRIZZO | B62: 44027 | C62: 44027 | D62: 4320 | E62: COUCHE | F62: 1139 | G62: 108X87 | H62: 10 | I62: OK | J62: LASER
C63: 44025 | E63: COUCHE | F63: 2759 | G63: 30X38 | H63: 21 | I63: OK | J63: FACA | L63: 465.5
A64: FERPLAST | B64: 44033 | C64: 44032 | D64: 4321 | E64: COUCHE | F64: 1215 | G64: 40X34 | H64: 26 | I64: OK | J64: LASER
C65: 44034 | E65: COUCHE | F65: 951 | G65: 100X150 | H65: 8.7 | I65: OK | J65: G10 | K65: 1476 | L65: 569.1
A66: OPEN WAY | B66: 44034 | C66: 44034 | D66: 4330 | E66: COUCHE | F66: 3224 | G66: 34X27 | H66: 52 | I66: OK | J66: LASER | L66: 280
A67: MCC | B67: 44034 | C67: 44032 | D67: 4329 | E67: COUCHE | F67: 2491 | G67: 100X90 | H67: 5.2 | I67: OK | J67: LASER | L67: 215
A68: G3 | B68: 44027 | C68: 44026 | D68: 4332 | E68: COUCHE | F68: 1397 | G68: 50X30 | H68: 35 | I68: OK | J68: FACA | L68: 280
A69: CODETECH | B69: 44027 | C69: 44026 | D69: 4333 | E69: COUCHE | F69: 855 | G69: 50X40 | H69: 46 | I69: OK | J69: FACA | L69: 450
A70: OMEGA | B70: 44029 | C70: 44027 | D70: 4334 | E70: C.BORR | F70: 2586 | G70: 50X70 | H70: 50 | I70: OK | J70: FACA
E71: VERMELHO | F71: 2903 | G71: 50X70 | H71: 9.76 | I71: OK | J71: FACA | L71: 959
A72: BASFIX | B72: 44033 | C72: 44032 | D72: 4339 | E72: COUCHE | F72: 822 | G72: 50X50 | H72: 40.5 | I72: OK | J72: FACA | L72: 556
A73: THUANI | B73: 44033 | C73: 44027 | D73: 4345 | E73: COUCHE | F73: 3186 | G73: 45X35 | H73: 5 | I73: OK | J73: FACA | L73: 125
A74: LAMINA | B74: 44033 | C74: 44029 | D74: 4347 | E74: COUCHE | F74: 2761 | G74: 100X80 | H74: 28.5 | I74: OK | J74: FACA
A75: TREND PET | B75: 44035 | C75: 44032 | D75: 4343 | E75: COUCHE | F75: 1454 | G75: 40X20 | H75: 5 | I75: OK | J75: LASER | L75: 32.5
A76: MAGELB | B76: 44036 | C76: 44033 | D76: 4350 | E76: BOPP.BORR | F76: 1550 | G76: 90X30 | H76: 10 | I76: OK | J76: LASER | L76: 344.7
A77: BANCO SANGUE | B77: 44034 | C77: 44028 | D77: 4354 | E77: COUCHE | F77: 2357 | G77: 55X28 | H77: 5 | I77: OK | J77: FACA | L77: 100
A78: ESTOQUE | B78: 44027 | C78: 44027 | D78: 4354 | E78: COUCHE | F78: 2515 | G78: 55X28 | H78: 10 | I78: OK | J78: FACA | L78: 0
A79: BRASSUD | B79: 44034 | C79: 44028 | D79: 1960 | E79: COUCHE | F79: 1960 | G79: 35X40 | H79: 20 | I79: OK | J79: FACA | L79: 406
A80: LC SOLUCOES | B80: 44034 | C80: 44032 | D80: 4365 | E80: COUCHE | F80: 822 | G80: 50X50 | H80: 51 | I80: OK | J80: FACA | L80: 612
A81: DOMAMA | B81: 44035 | C81: 44028 | D81: 4367 | E81: COUCHE | F81: 838 | G81: 100X40 | H81: 5 | I81: OK | J81: FACA | L81: 245
A82: CASA SERRA | B82: 44036 | C82: 44034 | D82: 4368 | E82: TAG | F82: 2973 | G82: 50X40 | H82: 6 | I82: OK | J82: LASER | L82: 99
A83: ZBM | B83: 44039 | C83: 44034 | D83: 4372 | E83: COUCHE | F83: 3035 | G83: 100X16 | H83: 5 | I83: OK | J83: LASER
E84: COUCHE | F84: 2811 | G84: 44X60 | H84: 5 | I84: OK | J84: LASER | L84: 159.85
A85: WINELANDS | B85: 44035 | C85: 44035 | D85: 4360 | E85: COUCHE | F85: 2149 | G85: 70X40 | H85: 20 | I85: OK | J85: LASER | L85: 500
A86: VITAMED | B86: 44039 | C86: 44036 | D86: 4373 | E86: COUCHE | F86: 1292 | G86: 40X25 | H86: 20 | I86: OK | J86: LASER | L86: 252
A87: SEXY FANTASY | B87: 44040 | C87: 44034 | D87: 4374 | E87: COUCHE | F87: 1087 | G87: 28X55 | H87: 60 | I87: OK | J87: FACA
C88: 44034 | E88: COUCHE | F88: 2639 | G88: 15X30 | H88: 24 | I88: OK | J88: FACA
C89: 44035 | E89: COUCHE | F89: 2825 | G89: 106X85 | H89: 2 | I89: ok | J89: LASER | L89: 800.18
A90: FOODCHAIN | B90: 44034 | D90: 4377 | E90: AMARELO | F90: 3226 | G90: 40X15 | H90: 1 | I90: OK | J90: FACA | K90: PERS
E91: VERDE | F91: 3227 | G91: 40X15 | H91: 1 | I91: OK | J91: FACA | K91: PERS
E92: AZUL | F92: 3228 | G92: 40X15 | H92: 1 | I92: OK | J92: FACA | K92: PERS | L92: 46
A93: TECNOVACUM | B93: 44034 | C93: 44034 | D93: 4380 | E93: COUCHE | F93: 2740 | G93: 90X36 | H93: 5 | I93: OK | J93: FACA
E94: VERMELHO | F94: 3230 | G94: 90X36 | H94: 5 | I94: OK | J94: FACA | L94: 205
A95: SPRAYJET | B95: 44040 | C95: 44036 | D95: 4387 | E95: TERMICO | F95: 3012 | G95: 100X150 | H95: 3 | I95: OK | J95: LASER | L95: 209.7 | M95: 2 rolos | N95: já enviados
A96: IPACOL | B96: 44040 | C96: 44037 | D96: 4389 | E96: COUCHE | F96: 950 | G96: 100X65 | H96: 17.4 | I96: OK | J96: LASER | L96: 680
A97: BARCELONA | B97: 44041 | C97: 44037 | D97: 4390 | E97: AMARELO | F97: 3231 | G97: 80X30 | H97: 5 | I97: OK | J97: LASER
E98: BOPP BORR | F98: 3232 | G98: 90X30 | H98: 5 | I98: OK | J98: LASER | L98: 355
A99: BOISUL | B99: 44041 | C99: 44039 | D99: 4393 | E99: PROMOM | F99: 2631 | G99: 75X263 | H99: 5 | I99: OK | J99: LASER
F100: 2632 | G100: 103X94 | H100: 5 | I100: OK | J100: LASER | L100: 1358.5
...

Sheet AGOSTO20
A1: CLIENTE | B1: Data Entr | C1: Data Prod | D1: O/F | E1: MATERIAL | F1: CÓDIGO | G1: ETIQUETA | H1: QUANT | I1: OK | J1: PRODUZIDO POR | K1: O/C | L1: VALOR
A2: CRIPPA | B2: 44043 | C2: 44043 | D2: 4517 | E2: COUCHE | F2: 1098 | G2: 90X80 | H2: 40 | I2: OK | J2: FACA | L2: 1200
A3: CARRARO | B3: 44046 | C3: 07/0/8 | D3: 4399 | E3: COUCHE | F3: 2263 | G3: 65X197 | H3: 11.4 | I3: OK | J3: G10 | K3: 1478 | L3: 1060
A4: VICENZI | B4: 44048 | C4: 44050 | D4: 4418 | E4: COUCHE | F4: 940 | G4: 90X20 | H4: 50.5 | I4: OK | J4: G10 | K4: 1479 | L4: 905
A5: SUPER PECAS | B5: 44048 | C5: 44050 | D5: 4443 | E5: COUCHE | F5: 1153 | G5: 25X54 | H5: 64.5 | I5: OK | J5: G10 | K5: 1480 | L5: 450
A6: CENTRA | B6: 44047 | D6: 4449 | E6: COUCHE | F6: 2691 | G6: 100X50 | H6: 5 | I6: OK | J6: FACA/LASER | K6: PICOTAR | L6: 210
A7: HYVA | B7: 44048 | C7: 44046 | D7: 4468 | E7: TAG | F7: 2550 | G7: 100X70 | H7: 10 | I7: OK | J7: LASER | L7: 405
A8: SULPACK | B8: 44048 | C8: 44047 | D8: 4480 | E8: BOPP | F8: 1170 | G8: 100X30 | H8: 5 | I8: OK | J8: LASER
E9: BOPP | F9: 1169 | G9: 100X30 | H9: 2 | I9: OK | J9: LASER
E10: BOPP | F10: 3215 | G10: 12X20 | H10: 3 | I10: OK | J10: LASER
E11: BOPP | F11: 1157 | G11: 15X15 | H11: 3 | I11: OK | J11: LASER
E12: COUCHE | F12: 838 | G12: 100X40 | H12: 1 | I12: OK | J12: FACA | L12: 629.5
A13: CEMTRA | B13: 44049 | C13: 44049 | D13: 4449 | E13: COUCHE | F13: 2691 | G13: 100X50 | H13: 5 | I13: OK | J13: FACA/LASER
F14: 2971 | G14: 100X48 | H14: 1 | I14: OK | J14: LASER | L14: 249
A15: FRIZZO | B15: 44050 | C15: 44048 | D15: 4495 | E15: COUCHE | F15: 1467 | G15: 85X50 | H15: 4.5 | I15: OK | J15: LASER | L15: 87.75
A16: FRIZZO | B16: 44050 | C16: 44055 | D16: 4493 | E16: COUCHE | F16: 2186 | G16: 90X40 | H16: 50 | I16: OK | J16: FACA | L16: 637.5
A17: FRIZZO | B17: 44049 | C17: 44047 | D17: 4494 | E17: COUCHE | F17: 1468 | G17: 100X75 | H17: 15 | I17: OK | J17: FACA | L17: 433.5
A18: ARCO COMPON. | B18: 44050 | C18: 44060 | D18: 4502 | E18: COUCHE | F18: 2604 | G18: 105X55 | H18: 21.2 | I18: OK | J18: G10 | K18: 1483 | L18: 434
B19: 44054 | C19: 44054 | F19: 2604 | G19: 105X55 | H19: 12.4 | I19: OK | J19: ESTOQUE
A20: VIA HOMEM | B20: 44050 | C20: 44063 | D20: 4505 | E20: COUCHE | F20: 2040 | G20: 40X30 | H20: 57.5 | I20: OK | J20: G10 | K20: 1482 | L20: 203
A21: MCC | B21: 44050 | C21: 44048 | D21: 4509 | E21: C.BORR | F21: 2491 | G21: 100X90 | H21: 5.2 | I21: OK | J21: LASER | L21: 226.3
A22: ENOMAK | B22: 44050 | C22: 44049 | D22: 4519 | E22: TAG | F22: 1316 | G22: 95X30 | H22: 6.25 | I22: OK | J22: LASER | L22: 143.75
A23: LAMINA | B23: 44053 | C23: 44048 | D23: 4408 | E23: COUCHE | F23: 885 | G23: 70X50 | H23: 55.3 | I23: OK | J23: FACA | L23: 450
A24: FRIZZO | B24: 44027 | C24: 44047 | D24: 4064 | E24: COUCHE | F24: 1869 | G24: 33X21 | H24: 90 | I24: OK | J24: FACA | L24: 264
A25: PLASMOSUL | B25: 44053 | C25: 44053 | D25: 4560 | E25: COUCHE | F25: 3239 | G25: 90X40 | H25: 2 | I25: OK | J25: FACA/LASER | L25: 79.8
E26: COUCHE | F26: 1186 | G26: 100X60 | H26: 2 | I26: OK | J26: LASER
A27: PLASTK | B27: 44053 | C27: 44050 | D27: 4522 | E27: COUCHE | F27: 744 | G27: 100X70 | H27: 10 | I27: OK | J27: LASER | L27: 385
A28: SERRANORTE | B28: 44054 | C28: 44049 | D28: 4524 | E28: COUCHE | F28: 2703 | G28: 55X34 | H28: 11.25 | I28: OK | J28: LASER
E29: COUCHE | F29: 753 | G29: 100X50 | H29: 10.4 | I29: OK | J29: FACA | L29: 423.25
A30: EBS | B30: 44054 | C30: 44053 | D30: 4525 | E30: B.BORR | F30: 2329 | G30: 105X105 | H30: 4 | I30: OK | J30: LASER | L30: 474.8
A31: DOLCE VITA | B31: 44054 | C31: 44056 | D31: 4527 | E31: COUCHE | F31: 3005 | G31: 90X60 | H31: 8 | I31: OK | J31: LASER
E32: COUCHE | F32: 3078 | G32: 75X27 | H32: 15 | I32: OK | J32: LASER
E33: COUCHE | F33: 3080 | G33: 50X15 | H33: 14 | I33: OK | J33: LASER | L33: 524.8
A34: GRANVIN | B34: 44050 | C34: 44047 | D34: 4534 | E34: COUCHE | F34: 2971 | G34: 100X48 | H34: 6.4 | I34: OK | J34: LASER | L34: 157.8
A35: SUPERLACK | B35: 44046 | C35: 44046 | D35: 4538 | E35: COUCHE | F35: 838 | G35: 100X40 | H35: 5 | I35: OK | J35: FACA | L35: 115
A36: CODETECH | B36: 44047 | C36: 44047 | D36: 4537 | E36: COUCHE | F36: 869 | G36: 33X25 | H36: 95 | I36: OK | J36: RETIRADO | K36: ESTOQUE | L36: 427.5
A37: BANCO SANGUE | B37: 44055 | C37: 44056 | D37: 4542 | E37: BOPP | F37: 1607 | G37: 50X50 | H37: 4.5 | I37: OK | J37: FACA
E38: BOPP | F38: 3241 | G38: 105X105 | H38: 2 | I38: OK | J38: LASER | L38: 226.72
A39: BVN | B39: 44055 | C39: 44048 | D39: 4544 | E39: COUCHE | F39: 753 | G39: 100X50 | H39: 2.4 | I39: OK | J39: FACA | L39: 76
A40: MACRUZ | B40: 44055 | C40: 44062 | D40: 4548 | E40: BOPP | F40: 3242 | G40: 100X45 | H40: 6.4 | I40: OK | J40: LASER | M40: AMOSTRAS | N40: 44057
E41: BOPP | F41: 3243 | G41: 100X45 | H41: 2 | I41: OK | J41: LASER
E42: BOPP | F42: 3244 | G42: 100X45 | H42: 2 | I42: OK | J42: LASER | L42: 2516
A43: GRANVIN | B43: 44056 | C43: 44055 | D43: 4542 | E43: COUCHE | F43: 2971 | G43: 100X48 | H43: 8 | I43: OK | J43: LASER | L43: 210.4
A44: MORELATE | B44: 44056 | C44: 44048 | D44: 4558 | E44: COUCHE | F44: 1397 | G44: 100X50 | H44: 10 | I44: OK | J44: FACA
E45: COUCHE | F45: 1468 | G45: 100X75 | H45: 5 | I45: OK | J45: FACA | L45: 373.5
A46: MOTUP | B46: 44057 | C46: 44049 | D46: 4563 | E46: COUCHE | F46: 1397 | G46: 50X30 | H46: 20 | I46: OK | J46: FACA | L46: 350
A47: GAMACOR | B47: 44057 | C47: 44057 | D47: 4567 | E47: COUCHE | F47: 1862 | G47: 100X35 | H47: 15 | I47: OK | J47: LASER | L47: 358.5
A48: AMF | B48: 44057 | C48: 44070 | D48: 4570 | E48: TAG | F48: 2781 | G48: 55X75 | H48: 16 | I48: OK | J48: LASER | L48: 310
C49: 44071 | E49: TAG | F49: 2780 | G49: 41X75 | H49: 158 | I49: OK | J49: G10 | K49: 1485 | L49: 1732.5
A50: CATAFESTA | B50: 44049 | C50: 44049 | D50: 0 | E50: BOPP | F50: 1095 | G50: 100X50 | H50: 15200 | I50: OK | J50: FACA | L50: SUBS
A51: AMF | B51: 44061 | C51: 44056 | D51: 4566 | E51: COUCHE | F51: 869 | G51: 33X25 | H51: 200 | I51: OK | J51: FACA | L51: 720
C52: 44056 | E52: COUCHE | F52: 869 | G52: 33X25 | H52: 10 | I52: OK | J52: FACA | K52: ESTOQUE | L52: 0
B53: 44055 | C53: 44055 | D53: 4566 | E53: COUCHE | F53: 869 | G53: 33x25 | H53: 105 | I53: OK | J53: FACA | K53: ESTOQUE | L53: 0
A54: ARCO CLIMA | B54: 44060 | C54: 44054 | D54: 4579 | E54: COUCHE | F54: 1468 | G54: 100X75 | H54: 6 | I54: OK | J54: FACA | L54: 185
A55: AMF | B55: 44053 | C55: 44056 | D55: 4582 | E55: COUCHE | F55: 879 | G55: 100X60 | H55: 51.1 | I55: OK | J55: FACA | L55: 1180.41
A56: HYDROL | B56: 44054 | C56: 44054 | D56: 4598 | E56: COUCHE | F56: 1126 | G56: 100X100 | H56: 4.8 | I56: OK | J56: FACA | L56: 276.96
A57: CODETECH | B57: 44057 | C57: 44055 | D57: 4605 | E57: BOPP | F57: 1395 | G57: 50X20 | H57: 4 | I57: OK | J57: FACA | L57: 38
A58: LOVATO | B58: 44062 | C58: 44057 | D58: 4597 | E58: COUCHE | F58: 1468 | G58: 100X75 | H58: 15 | I58: OK | J58: FACA | L58: 625.95
A59: AMF | B59: 44062 | C59: 44060 | D59: 4600 | E59: COUCHE | F59: 1139 | G59: 108X87 | H59: 10 | I59: OK | J59: LASER
E60: COUCHE | F60: 2759 | G60: 30X38 | H60: 21 | I60: OK | J60: FACA | L60: 465.5
A61: AMF | B61: 44062 | C61: 44055 | D61: 4601 | E61: COUCHE | F61: 1106 | G61: 45X35 | H61: 40 | I61: OK | J61: FACA | L61: 302
A62: SERRANORTE | B62: 44062 | C62: 44060 | D62: 4604 | E62: COUCHE | F62: 2703 | G62: 55X34 | H62: 11.25 | I62: OK | J62: LASER | L62: 137.25
A63: PORTAL USI | B63: 44062 | C63: 44061 | D63: 4608 | E63: COUCHE | F63: 1631 | G63: 60X60 | H63: 20.25 | I63: OK | J63: LASER | L63: 440
A64: CODETECH | B64: 44063 | C64: 44069 | D64: 4611 | E64: TERMICO | F64: 2115 | G64: 39X40 | H64: 70 | I64: OK | J64: FACA | L64: 273
A65: AMF | B65: 44063 | C65: 44062 | D65: 4623 | E65: COUCHE | F65: 3005 | G65: 90X60 | H65: 10.4 | I65: OK | J65: LASER
C66: 44062 | E66: BOPP | F66: 758 | G66: 100X20 | H66: 14 | I66: OK | J66: LASER | L66: 486.5
A67: HUGO PIETRO | B67: 44069 | C67: 44064 | D67: 4625 | E67: COUCHE | F67: 2264 | G67: 80X60 | H67: 60.2 | I67: OK | J67: LASER | L67: 1050
A68: AMF | B68: 44063 | C68: 44057 | D68: 4569 | E68: COUCHE | F68: 855 | G68: 50X40 | H68: 150 | I68: OK | J68: FACA | L68: 1147.5
A69: AMF | B69: 44056 | C69: 44056 | D69: 4633 | E69: VERMELHO | F69: 3255 | G69: 45X35 | H69: 12.5 | I69: OK | J69: FACA | L69: 101.25
A70: UNIMED | B70: 44055 | C70: 44056 | D70: 4631 | E70: COUCHE | F70: 2740 | G70: 90X36 | H70: 6 | I70: OK | J70: FACA | L70: 59.2
A71: OMEGA | B71: 44064 | C71: 44060 | D71: 4628 | E71: C.BORR | F71: 2586 | G71: 50X70 | H71: 50 | I71: OK | J71: FACA | L71: 750
A72: VF ACESSORIOS | B72: 44067 | C72: 44057 | D72: 4636 | E72: COUCHE | F72: 879 | G72: 100X60 | H72: 10.5 | I72: ok | J72: FACA | L72: 441
A73: G10 | B73: 44071 | D73: 1488 | E73: COUCHE | F73: 3160 | G73: 108X1000 | H73: 7 | J73: G10 | K73: 1488
A74: PETRYMAR | B74: 44067 | C74: 44060 | D74: 4640 | E74: COUCHE | F74: 753 | G74: 100X50 | H74: 20 | I74: OK | J74: FACA | L74: 500
A75: ABOCARE | B75: 44057 | C75: 44057 | D75: 4648 | E75: BOPP | F75: 2467 | G75: 100X80 | H75: 2 | I75: OK | J75: FACA | L75: 104
A76: BANCO SANGUE | B76: 44067 | C76: 44060 | D76: 4641 | E76: BOPP | F76: 2467 | G76: 100X80 | H76: 2 | I76: OK | J76: FACA | L76: 156
A77: LC SOLUCOES | B77: 44064 | C77: 44060 | D77: 4645 | E77: BOPP | F77: 2412 | G77: 50X40 | H77: 10 | I77: OK | J77: FACA | L77: 160
A78: RODER | B78: 44068 | C78: 44068 | D78: 4650 | E78: COUCHE | F78: 2209 | G78: 26X15 | H78: 21 | I78: ok | J78: LASER | L78: 100.8
A79: AMF | B79: 44068 | C79: 44068 | D79: 4651 | E79: COUCHE | F79: 1467 | G79: 85X50 | H79: 5.1 | I79: OK | J79: LASER
E80: COUCHE | F80: 1468 | G80: 100X75 | H80: 5 | I80: OK | J80: FACA | L80: 232.25
A81: ZBM | B81: 44068 | C81: 44069 | D81: 4652 | E81: COUCHE | F81: 2811 | G81: 44X60 | H81: 15 | I81: OK | J81: LASER | L81: 217.5
A82: SEXY FANTASY | B82: 44068 | C82: 44060 | D82: 4659 | E82: COUCHE | F82: 1087 | G82: 28X55 | H82: 60 | I82: OK | J82: FACA
E83: COUCHE | F83: 2639 | G83: 15X30 | H83: 32 | I83: OK | J83: FACA | L83: 735
A84: GLOBALTECH | B84: 44068 | C84: 44069 | D84: 4654 | E84: COUCHE | F84: 616 | G84: 40X30 | H84: 15 | I84: OK | J84: LASER | L84: 187.5
A85: SPIGOLON | B85: 44069 | C85: 44069 | D85: 4660 | E85: TAG | F85: 3184 | G85: 47X35 | H85: 6 | I85: OK | J85: LASER
E86: TAG | F86: 2433 | G86: 95X35 | H86: 3 | I86: OK | J86: LASER | L86: 233.1
A87: MAR AZUL | B87: 44069 | C87: 44069 | D87: 4661 | E87: BOPP | F87: 2175 | G87: 30X80 | H87: 2 | I87: ok | J87: LASER | L87: 70
A88: IMEXPORT | B88: 44064 | C88: 44068 | D88: 4621 | E88: COUCHE | F88: 2253 | G88: 104X25 | H88: 30 | I88: OK | J88: LASER
C89: 44074 | E89: COUCHE | F89: 2854 | G89: 104X125 | H89: 5.1 | I89: OK | J89: G10 | K89: 1491 | L89: 857
A90: UP TO GO | B90: 44063 | C90: 44061 | D90: 4669 | E90: COUCHE | F90: 753 | G90: 100X50 | H90: 4 | I90: OK | J90: FACA | L90: 110
A91: HOSP. CIRCULO | B91: 44067 | C91: 44061 | D91: 4666 | E91: COUCHE | F91: 838 | G91: 100X40 | H91: 10 | I91: OK | J91: FACA | L91: 240
A92: SORVELANDIA | B92: 44062 | C92: 44062 | D92: 4675 | E92: COUCHE | F92: 2039 | G92: 40X55 | H92: 21 | I92: OK | J92: FACA | L92: 270
A93: FIXPAR | B93: 44062 | C93: 44062 | D93: 4680 | E93: COUCHE | F93: 908 | G93: 50X20 | H93: 101.5 | I93: ok | J93: FACA | L93: 490
A94: BY GI | B94: 44064 | D94: 4679 | E94: COUCHE | F94: 1677 | G94: 33X22 | H94: 20 | I94: OK | J94: FACA | K94: ESTOQUE | L94: 104
A95: MERIDIANO | B95: 44071 | C95: 44071 | D95: 4682 | E95: COUCHE | F95: 1018 | G95: 80X65 | H95: 10.2 | I95: OK | J95: LASER | L95: 480
A96: FERPLAST | B96: 44071 | C96: 44071 | D96: 4683 | E96: COUCHE | F96: 2114 | G96: 80X45 | H96: 17 | I96: OK | J96: LASER | L96: 426
A97: HAUSSHOP | B97: 44071 | C97: 44074 | D97: 4684 | E97: COUCHE | F97: 3161 | G97: 100X115 | H97: 2.1 | I97: OK | J97: LASER | L97: 159.1
A98: DOMAMA | B98: 44064 | C98: 44063 | D98: 4693 | E98: COUCHE | F98: 838 | G98: 100X40 | H98: 8 | I98: OK | J98: FACA | L98: 48
A99: METALLI | B99: 44074 | C99: 44064 | D99: 4691 | E99: BOPP | F99: 1483 | G99: 100X40 | H99: 5 | I99: OK | J99: FACA
E100: AMARELO | F100: 3256 | G100: 100X40 | H100: 2 | I100: OK | J100: FACA
...

Sheet SETEMBRO20
A1: CLIENTE | B1: Data Entr | C1: Data Prod | D1: O/F | E1: MATERIAL | F1: CÓDIGO | G1: ETIQUETA | H1: QUANT | I1: OK | J1: PRODUZIDO POR | K1: O/C | L1: VALOR
A2: REZLER | B2: 44075 | C2: 44075 | D2: 4696 | E2: BOPP BORR | F2: 2640 | G2: 80X60 | H2: 10.4 | I2: OK | J2: LASER | L2: 395
A3: AMF | B3: 44076 | C3: 44075 | D3: 4707 | E3: COUCHE | F3: 869 | G3: 33X25 | H3: 200 | I3: OK | J3: FACA | L3: 720
A4: JS SERVS | B4: 44077 | C4: 44076 | D4: 4723 | E4: COUCHE | F4: 1173 | G4: 100X25 | H4: 18 | I4: OK | J4: LASER | L4: 351
A5: HYVA | B5: 44077 | C5: 44077 | D5: 4724 | E5: TAG | F5: 2550 | G5: 100X70 | H5: 20 | I5: OK | J5: LASER | L5: 810
A6: DUKE | B6: 44077 | C6: 44077 | D6: 4728 | E6: COUCHE | F6: 2800 | G6: 45X45 | H6: 4 | I6: OK | J6: LASER | K6: PERS | L6: 208
B7: 44077 | C7: 44077 | F7: 2891 | G7: 60X60 | H7: 2 | I7: OK | J7: LASER | K7: PERS | L7: 130
A8: IND.FER.LAZZ | B8: 44077 | C8: 44078 | D8: 4729 | E8: COUCHE | F8: 1173 | G8: 100X25 | H8: 21 | I8: OK | J8: LASER | L8: 730
A9: AMF | B9: 44082 | C9: 44077 | D9: 4643 | E9: COUCHE | F9: 879 | G9: 100X60 | H9: 50.4 | I9: OK | J9: FACA | L9: 1050
A10: HYVA | B10: 44082 | C10: 44082 | D10: 4757 | E10: TAG | F10: 2550 | G10: 100X70 | H10: 30 | I10: OK | J10: LASER | L10: 1215
A11: G3 | B11: 44082 | C11: 44082 | D11: 4759 | E11: BOPP | F11: 3139 | G11: 78X25 | H11: 5 | I11: OK | J11: LASER | L11: 108.5
A12: LC SOLUCOES | B12: 44083 | C12: 44091 | D12: 4760 | E12: COUCHE | F12: 3268 | G12: 102X34 | H12: 50 | I12: OK | J12: LASER | L12: 850
A13: MATRIMETAL | B13: 44082 | C13: 44082 | D13: 4800 | E13: COUCHE | F13: 2022 | G13: 80X30 | H13: 11 | I13: OK | J13: LASER | L13: 228
A14: BP COMP | B14: 44082 | C14: 44085 | D14: 4746 | E14: POLIESTER | F14: 1183 | G14: 30X15 | H14: 7.2 | I14: OK | J14: LABEL | K14: 1496 | L14: 1300
A15: BANCO SANGUE | B15: 44084 | C15: 44076 | D15: 4798 | E15: BOPP | F15: 1607 | G15: 50X50 | H15: 3 | I15: OK | J15: FACA | L15: 33.6
E16: BOPP | F16: 2467 | G16: 100X80 | H16: 2 | I16: OK | J16: FACA | L16: 216
A17: LAMINA | B17: 44084 | C17: 44076 | D17: 4307 | E17: COUCHE | F17: 885 | G17: 70X50 | H17: 40.6 | I17: OK | J17: FACA | L17: 600
A18: LAMINA | B18: 44084 | C18: 44082 | D18: 4833 | E18: COUCHE | F18: 855 | G18: 70X50 | H18: 35.7 | I18: OK | J18: FACA | L18: 535.5 | M18: FAZER PARA FECHA OS 80.000
A19: HOZANE | B19: 44084 | C19: 44084 | D19: 4788 | E19: COUCHE | F19: 728 | G19: 35X25 | H19: 4.5 | I19: OK | J19: LASER | L19: 42.75
A20: FLORENZA | B20: 44084 | C20: 44088 | D20: 4749 | E20: COUCHE | F20: 1862 | G20: 100X35 | H20: 10 | I20: OK | J20: LASER | L20: 210
A21: LAIMED | B21: 44076 | C21: 44076 | D21: 4808 | E21: COUCHE | F21: 1098 | G21: 90X80 | H21: 3 | I21: OK | J21: FACA | L21: 37.12
A22: HOSP.SAO CARL | B22: 44088 | C22: 44088 | D22: 4807 | E22: BOPP | F22: 1491 | G22: 100X23 | H22: 10 | I22: OK | J22: LASER
C23: 44083 | E23: AMARELO | F23: 3162 | G23: 34X23 | H23: 40 | I23: OK | J23: FACA
E24: COUCHE | F24: 843 | G24: 34X23 | H24: 120 | I24: OK | J24: FACA
E25: VERM | F25: 3163 | G25: 34X23 | H25: 120 | I25: OK | J25: FACA | L25: 1853.8
A26: STELLALBLU | B26: 44088 | C26: 44089 | D26: 4809 | E26: PROMOM | F26: 1019 | G26: 34X51 | H26: 6 | I26: OK | J26: LASER
E27: COUCHE | F27: 1924 | G27: 44X16 | H27: 4 | I27: OK | J27: LASER | L27: 210
A28: BRASSUD | B28: 44085 | C28: 44077 | D28: 4813 | E28: COUCHE | F28: 1960 | G28: 35X40 | H28: 21 | I28: OK | J28: FACA | L28: 406
A29: SEXY FANTASY | B29: 44083 | C29: 44078 | D29: 4816 | E29: COUCHE | F29: 1087 | G29: 28X55 | H29: 62.5 | I29: OK | J29: FACA
C30: 44077 | E30: COUCHE | F30: 2639 | G30: 15X30 | H30: 32 | I30: OK | J30: FACA | L30: 735
A31: TOP LIMP | B31: 44088 | D31: 4818 | E31: COUCHE | F31: 2515 | G31: 55X28 | H31: 10 | I31: OK | J31: FACA
E32: AMARELO | F32: 2765 | G32: 55X28 | H32: 5 | I32: OK | J32: FACA | L32: 60.75
A33: SULPACK | B33: 44088 | C33: 44089 | D33: 4819 | E33: BOPP | F33: 1401 | G33: 55X22 | H33: 2 | I33: OK | J33: LASER | L33: 70
C34: 44082 | E34: COUCHE | F34: 838 | G34: 100X40 | H34: 1 | I34: OK | J34: FACA | L34: 24
C35: 44082 | E35: BOPP | F35: 1395 | G35: 50X20 | H35: 7 | I35: OK | J35: FACA | L35: 180
A36: SUPER AR | B36: 44088 | C36: 44078 | D36: 4820 | E36: COUCHE | F36: 1468 | G36: 100X75 | H36: 4 | I36: OK | J36: FACA | L36: 236
A37: JC | B37: 44084 | D37: 4824 | E37: AMARELO | F37: 3273 | G37: 33X25 | H37: 3 | I37: OK | J37: FACA | K37: PERS
E38: AMARELO | F38: 3272 | G38: 33X25 | H38: 20 | I38: OK | J38: FACA | K38: PERS
E39: AMARELO | F39: 3029 | G39: 33X25 | H39: 7 | I39: OK | J39: FACA | K39: PERS | L39: 309
A40: AMF | B40: 44089 | C40: 44090 | D40: 4717 | E40: COUCHE | F40: 3264 | G40: 33X22 | H40: 30 | I40: OK | J40: G10 | K40: 1493 | L40: 135
A41: MODAZINE | B41: 44090 | C41: 44090 | D41: 4726 | E41: COUCHE | F41: 1904 | G41: 105X161 | H41: 5.92 | I41: OK | J41: G10 | K41: 1494 | L41: 67.99
B42: 44090 | C42: 44091 | D42: 4726 | E42: TAG | F42: 2272 | G42: 35X62 | H42: 109.4 | I42: OK | J42: G10 | K42: 1494 | L42: 536.4
A43: HOSP.NAVEG | B43: 44092 | C43: 44092 | D43: 4780 | E43: TERMICO | F43: 2874 | G43: 72X17 | H43: 52.8 | I43: OK | J43: G10 | K43: 1498 | L43: 553.34
A44: HOSP.S.LUZIA | B44: 44092 | C44: 44092 | D44: 4783 | E44: TERMICO | F44: 2875 | G44: 100X35 | H44: 25.5 | I44: OK | J44: G10 | K44: 1499 | L44: 345.96
A45: TR CARTUCHOS | B45: 44102 | C45: 44097 | D45: 4832 | E45: COUCHE | F45: 754 | G45: 100X30 | H45: 35 | I45: OK | J45: GV | K45: 1504 | L45: 450
A46: FIXPAR | B46: 44089 | C46: 44078 | D46: 4826 | E46: VERDE | F46: 3234 | G46: 50X20 | H46: 7 | I46: OK | J46: FACA | L46: 113.4
A47: DILLON | B47: 44089 | C47: 44089 | D47: 4823 | E47: BOPP BORR | F47: 2938 | G47: 8X25 | H47: 8200 | I47: OK | J47: LASER | L47: 0.62
A48: LUHAZ | B48: 44093 | C48: 44082 | D48: 4836 | E48: COUCHE | F48: 838 | G48: 100X40 | H48: 10 | I48: OK | J48: FACA | L48: 240
C49: 44083 | E49: COUCHE | F49: 838 | G49: 100X40 | H49: 7 | I49: OK | J49: FACA | K49: ADICIONADO
A50: MAQENGE | B50: 44090 | C50: 44091 | D50: 4838 | E50: COUCHE | F50: 2720 | G50: 47X22 | H50: 30 | I50: OK | J50: LASER | L50: 147.9
A51: UNIMED | B51: 44083 | C51: 44082 | D51: 4840 | E51: COUCHE | F51: 2740 | G51: 90X36 | H51: 2 | I51: OK | J51: FACA | K51: ROLO | L51: 29.6
A52: AMF | B52: 44097 | C52: 44095 | D52: 4715 | E52: COUCHE | F52: 1139 | G52: 108X87 | H52: 10 | I52: OK | J52: LASER
F53: 2759 | G53: 30X38 | H53: 21 | I53: OK | J53: FACA | L53: 470.65
A54: PETRYMAR | B54: 44097 | C54: 44078 | D54: 4811 | E54: COUCHE | F54: 753 | G54: 100X50 | H54: 20 | I54: OK | J54: FACA | L54: 500
A55: AMF INFO | B55: 44084 | C55: 44084 | D55: 4845 | E55: COUCHE | F55: 855 | G55: 50X40 | H55: 30 | I55: OK | J55: FACA | L55: 363.5
A56: RESET | B56: 44083 | C56: 44083 | D56: 4851 | E56: COUCHE | F56: 869 | G56: 33X25 | H56: 50 | I56: OK | J56: ESTOQUE | L56: 225
A57: SULPACK | B57: 44097 | C57: 44096 | D57: 4852 | E57: BOPP | F57: 3215 | G57: 12X20 | H57: 4 | I57: OK | J57: LASER | L57: 130
A58: SUSIN | B58: 44092 | C58: 44095 | D58: 4853 | E58: COUCHE | F58: 343 | G58: 50X22 | H58: 5 | I58: OK | J58: LASER | L58: 175
A59: MET. CDB | B59: 44085 | C59: 44085 | D59: 4862 | E59: BOPP | F59: 1483 | G59: 100X40 | H59: 6 | I59: OK | J59: FACA | L59: 271.2
A60: GALAFASSI | B60: 44085 | C60: 44084 | D60: 4865 | E60: COUCHE | F60: 838 | G60: 100X40 | H60: 10 | I60: OK | J60: FACA | L60: 215
A61: BARAO | B61: 44089 | C61: 44089 | D61: 4868 | E61: BOPP | F61: 875 | G61: 70X50 | H61: 10 | I61: OK | J61: FACA | L61: 350
A62: ANNA KARENINA | B62: 44088 | C62: 44085 | D62: 4866 | E62: COUCHE | F62: 1397 | G62: 50X30 | H62: 35 | I62: OK | J62: FACA | L62: 770
A63: MAGAZINE | B63: 44092 | C63: 44095 | D63: 4859 | E63: COUCHE | F63: 1195 | G63: 50X75 | H63: 6 | I63: OK | J63: LASER | L63: 249.48
E64: TAG | F64: 1112 | G64: 50X75 | H64: 6 | I64: OK | J64: LASER | L64: 224.52
A65: URSULA | B65: 44095 | C65: 44096 | D65: 4874 | E65: BOPP | F65: 3219 | G65: 109X25 | H65: 22.5 | I65: OK | J65: LASER | L65: 280
A66: MCC | B66: 44096 | C66: 44102 | D66: 4876 | E66: C.BORR | F66: 2491 | G66: 100X90 | H66: 10 | I66: OK | J66: LASER | L66: 410
A67: G3 | B67: 44088 | C67: 44085 | D67: 4875 | E67: COUCHE | F67: 855 | G67: 50X40 | H67: 8 | I67: OK | J67: FACA | L67: 100
A68: EUROPLAS | B68: 44089 | C68: 44089 | D68: 4880 | E68: REMOV | F68: 2548 | G68: 33X25 | H68: 70 | I68: OK | J68: FACA | L68: 560
A69: RR VISION | B69: 44085 | C69: 44085 | D69: 4889 | E69: COUCHE | F69: 1397 | G69: 50X30 | H69: 5 | I69: OK | J69: FACA | L69: 110
A70: RR VISION | B70: 44096 | C70: 44096 | D70: 4890 | E70: BOPP | F70: 2844 | G70: 48X10 | H70: 10 | I70: OK | J70: LASER | L70: 66
A71: EST. ITALIA | B71: 44096 | C71: 44097 | D71: 4891 | E71: C.BORR | F71: 2438 | G71: 100X50 | H71: 5.6 | I71: OK | J71: FACA | L71: 160
F72: 744 | G72: 100X70 | H72: 5 | I72: OK | J72: LASER | L72: 262.5
F73: 908 | G73: 50X20 | H73: 7 | I73: OK | J73: FACA | L73: 81.25
A74: GAMACOR | B74: 44096 | C74: 44097 | D74: 4894 | E74: COUCHE | F74: 1862 | G74: 100X35 | H74: 9 | I74: OK | J74: LASER | L74: 215.1
A75: LD INFORMATICA | B75: 44085 | C75: 44085 | D75: 4898 | E75: COUCHE | F75: 908 | G75: 50X20 | H75: 17.5 | I75: OK | J75: FACA | L75: 84
A76: LUCIANO | B76: 44097 | C76: 44098 | D76: 4899 | E76: TAG | F76: 1112 | G76: 50X75 | H76: 4 | I76: OK | J76: LASER | L76: 147.2
E77: COUCHE | F77: 1195 | G77: 50X75 | H77: 4 | I77: OK | J77: LASER
A78: ORIGIN | B78: 44088 | C78: 44088 | D78: 4900 | E78: COUCHE | F78: 1468 | G78: 100X75 | H78: 5 | I78: OK | J78: FACA | L78: 154.5
A79: CODETECH | B79: 44088 | C79: 44088 | D79: 4901 | E79: COUCHE | F79: 1397 | G79: 50X30 | H79: 2.5 | I79: OK | J79: FACA | L79: 18.75
A80: VIN CAS MOTTER | B80: 44097 | C80: 44102 | D80: 4907 | E80: COUCHE | F80: 3218 | G80: 80X65 | H80: 6 | I80: OK | J80: LASER | L80: 210
A81: BANCO SANGUE | B81: 44128 | C81: 44129 | D81: 4908 | E81: TERMICO | F81: 3081 | G81: 100X120 | H81: 6.5 | I81: OK | J81: GV | K81: 1507 | L81: 663
A82: CRIPPA | B82: 44092 | C82: 44091 | D82: 4910 | E82: COUCHE | F82: 1098 | G82: 90X80 | H82: 39 | I82: OK | J82: FACA | L82: 1200
A83: AMF INFO | B83: 44102 | C83: 44099 | D83: 4913 | E83: COUCHE | F83: 869 | G83: 33X25 | H83: 200 | I83: OK | J83: FACA | L83: 720
A84: AMF INFO | B84: 44098 | C84: 44104 | D84: 4914 | E84: COUCHE | F84: 2791 | G84: 95X56 | H84: 15 | I84: OK | J84: LASER | L84: 310.5
E85: COUCHE | F85: 838 | G85: 100X40 | H85: 20 | I85: OK | J85: FACA | L85: 324
A86: UNIMED | B86: 44096 | C86: 44091 | D86: 4919 | E86: COUCHE | F86: 2740 | G86: 90X36 | H86: 7 | I86: OK | J86: FACA | L86: 103.6
A87: INJET | B87: 44099 | C87: 44099 | D87: 4924 | E87: BOPP BORR | F87: 2494 | G87: 25X25 | H87: 10 | I87: OK | J87: LASER | K87: PERS 29/09 | L87: 550
A88: MAR AZUL | B88: 44099 | C88: 44102 | D88: 4931 | E88: BOPP | F88: 2175 | G88: 30X80 | H88: 3 | I88: OK | J88: LASER | L88: 111
A89: FIXPAR | B89: 44098 | C89: 44095 | D89: 4938 | E89: BOPP BORR | F89: 3096 | G89: 100X50 | H89: 3 | I89: OK | J89: FACA
E90: VERDE | F90: 3194 | G90: 100X50 | H90: 3 | I90: OK | J90: FACA
E91: CINZA | F91: 3195 | G91: 100X50 | H91: 3 | I91: OK | J91: FACA
E92: LILAS | F92: 3196 | G92: 100X50 | H92: 3 | I92: OK | J92: FACA
E93: VERM | F93: 3197 | G93: 100X50 | H93: 3 | I93: OK | J93: FACA
E94: AMAR | F94: 3198 | G94: 100X50 | H94: 3 | I94: OK | J94: FACA
E95: LARA | F95: 3199 | G95: 100X50 | H95: 3 | I95: OK | J95: FACA
E96: AZUL | F96: 3193 | G96: 100X50 | H96: 3 | I96: OK | J96: FACA
E97: AMAR | F97: 3172 | G97: 50X70 | H97: 3 | I97: OK | J97: FACA
E98: VERDE | F98: 3284 | G98: 50X70 | H98: 3 | I98: OK | J98: FACA
E99: AZUL | F99: 3171 | G99: 50X70 | H99: 3 | I99: OK | J99: FACA | L99: 1257.9
A100: ALTAIR | B100: 44099 | C100: 44096 | D100: 4934 | E100: TC | F100: 3282 | G100: 45X85 | H100: 0.5 | I100: OK | J100: PERS. | L100: 54.6
...

Sheet FACA BATIDA
B2: FACAS DE BATIDA
B3: COD | C3: FACA | D3: COL | E3: QTD/ROLO | F3: METROS
C4: 16x6 | D4: 4
C5: 25X75 | D5: 4 | E5: 500 | F5: 39
C6: 30X15 | D6: 3 | E6: 7000 | F6: 42
C7: 30X22 | D7: 3 | E7: 4500 | F7: 38
C8: 30X30 | D8: 3 | E8: 4000 | F8: 44
C9: 32x11 | D9: 3 | E9: 10000 | F9: 47
C10: 32x55 | D10: 3 | E10: 1500 | F10: 29
C11: 33X10 | D11: 3 | E11: 5000 | F11: 23
C12: 33x17 | D12: 3 | E12: 6000 | F12: 40
C13: 33X25 | D13: 3 | E13: 5000 | F13: 47
C14: 33X37 | D14: 2
C15: 33X39 | D15: 3 | E15: 2000 | F15: 28
C16: 33x49 | D16: 3 | E16: 2000 | F16: 52
C17: 35X26,5 | D17: 3 | E17: 4000 | F17: 40
C18: 40X25 | D18: 2 | E18: 2000 | F18: 28
C19: 40X34 | D19: 1 | E19: 2500 | F19: 92
C20: 40X34 | D20: 2 | E20: 2000 | F20: 37
C21: 44X60 | D21: 2 | E21: 1250 | F21: 39
C22: 45x20 | D22: 2 | E22: 3500 | F22: 40
C23: 45x25 | D23: 2 | E23: 2000 | F23: 28
C24: 50x15 | D24: 2 | E24: 4000 | F24: 36
C25: 50X18 | D25: 2 | E25: 4000 | F25: 42
C26: 50x22 | D26: 2 | E26: 3500 | F26: 44
C27: 50X25 | D27: 2 | E27: 3000 | F27: 42
C28: 52X20 | D28: 2
C29: 55X25 | D29: 1 | E29: 2000 | F29: 56
C30: 55X28 | D30: 1 | E30: 1500 | F30: 46
C31: 56X23 | D31: 1 | E31: 2000 | F31: 52
C32: 60x20 | D32: 1 | E32: 2000 | F32: 65
C33: 60X30 | D33: 1 | E33: 1250 | F33: 41
C34: 66X25 | D34: 1 | E34: 3500 | F34: 98
C35: 70X40 | D35: 1 | E35: 1000 | F35: 43
C36: 72x17 | D36: 1 | E36: 2000 | F36: 40
C37: 74X74 | D37: 1 | E37: 1000 | F37: 77
C38: 78x30 | D38: 1 | E38: 1250 | F38: 41
C39: 80X25 | D39: 1 | E39: 1500 | F39: 42
C40: 80x30 | D40: 1 | E40: 1250 | F40: 41
... C49: 90X90 | D49: 1 | E49: 500 | F49: 46
C50: 95x56 | D50: 1
C51: 100X20 | D51: 1 | E51: 2000 | F51: 46
B52: REFAZER | C52: 100X23 | D52: 1 | E52: 1500 | F52: 39 | G52: mandei fazer nova
C53: 100X30 | D53: 1 | E53: 1250 | F53: 41
C54: 100X45 | D54: 1 | E54: 1000 | F54: 48
C55: 100x70 | D55: 1 | E55: 600 | F55: 44
C56: 100x90 | D56: 1 | E56: 500 | F56: 46
C57: 100X120 | D57: 1 | E57: 350 | F57: 43
C58: 100x165 | D58: 1 | E58: 500 | F58: 84
C59: 100x169 | D59: 1 | E59: 200 | F59: 35
C60: 103X94 | D60: 1 | E60: 500 | F60: 48
C61: 103x127 | D61: 1 | E61: 1000 | F61: 130
C62: 104x25 | D62: 1 | E62: 1000 | F62: 28
C63: 104x125 | D63: 1 | E63: 300 | F63: 38
C64: 105X55 | D64: 1 | E64: 700 | F64: 40
... C68: 107x75 | D68: 1 | E68: 500 | F68: 39
C69: 107X87 | D69: 1 | E69: ??? | F69: ???
B70: FACAS REDONDAS
C71: 30mm | D71: 3 | E71: 4000 | F71: 44
C72: 40mm | D72: 2 | E72: 2000 | F72: 43
B73: FACAS DE PICOTE
B74: LACRE | C74: 100X30 | D74: 1 | E74: 1250 | F74: 41
B75: 115mm | C75: PICOTE | D75: 1
B76: FRIZZO | C76: 32X70 | D76: 3
B77: HEMOVITA | C77: 100X120 | D77: 1 | E77: 300 | F77: 37

Sheet FACAS
B2: Facas Rotativas | J2: Para cálculo
B3: COD | C3: PAPEL | D3: FACA - col | E3: VALOR | F3: PAPEL/ESP | G3: QUANT | H3: METROS | J3: M/MILHEIRO | K3: LARG PAPEL
B5: 2825 | C5: COUCHE ACRILICO | D5: 106X85 - 1 | E5: =(J5*K5*PRECOS!N21) -> 29.0675 | F5: 110/87,5 | G5: 500 | H5: 44 | J5: 87.5 | K5: 0.11
B7: 3241 | C7: BOPP ACRILICO | D7: 105x105 - 1 | E7: =(J7*K7*PRECOS!#REF!) -> #REF! | F7: 110/108 | G7: 400 | H7: 43 | J7: 108 | K7: 0.11
B9: 2604 | C9: COUCHE ACRILICO | D9: 105x55 - 1 | E9: =(J9*K9*PRECOS!#REF!) -> #REF! | F9: 110/57 | G9: 800 | H9: 46 | J9: 57 | K9: 0.11
B11: 3286 | C11: COUCHE ACRILICO | D11: 103X93 - 1 | E11: =(J11*K11*PRECOS!N21) -> 31.7251 | F11: 110/95,5 | G11: 1000 | H11: 95 | J11: 95.5 | K11: 0.11
B13: 951 | C13: COUCHE ACRILICO | D13: 100X150 - 1 | E13: =(J13*K13*PRECOS!N21) -> 48.5163 | F13: 105/153 | G13: 250 | H13: 38 | J13: 153 | K13: 0.105
B14: 2847 | C14: TERMICO | D14: 100X150 - 1 | E14: =(J14*K14*PRECOS!N22) -> 47.71305 | F14: 105/153 | G14: 250 | H14: 38 | J14: 153 | K14: 0.105
B15: 1446 | C15: BOPP ACRÍLICO | D15: 100X150 - 1 | E15: =(J15*K15*PRECOS!#REF!) -> #REF! | F15: 105/153 | G15: 250 | H15: 38 | J15: 153 | K15: 0.105
C17: BOPP BORRACHA | D17: 100X120 - PICOTE
B19: 1126 | C19: COUCHE ACRILICO | D19: 100X100 - 1 | E19: =(J19*K22*PRECOS!N21) -> 32.6613 | F19: 105/103 | G19: 400 | H19: 42 | J19: 103 | K19: 0.105
B20: 1408 | C20: BOPP ACRILICO | D20: 100X100 - 1 | E20: =(J20*K23*PRECOS!#REF!) -> #REF! | F20: 105/103 | G20: 400 | H20: 42 | J20: 103 | K20: 0.105
B22: 2761 | C22: COUCHE ACRILICO | D22: 100X80 - 1 | E22: =(J22*K22*PRECOS!N21) -> 26.3193 | F22: 105/83 | G22: 500 | H22: 42 | J22: =83/1 -> 83 | K22: 0.105
B23: 788 | C23: COUCHE BORRACHA | D23: 100X80 - 1 | E23: =(J23*K23*PRECOS!N22) -> 25.88355 | F23: 105/83 | G23: 500 | H23: 42 | J23: =83/1 -> 83 | K23: 0.105
B24: 2467 | C24: BOPP ACRILICO | D24: 100X80 - 1 | E24: =(J24*K24*PRECOS!#REF!) -> #REF! | F24: 105/83 | G24: 500 | H24: 42 | J24: =83/1 -> 83 | K24: 0.105
B25: 2468 | C25: BOPP BORRACHA | D25: 100X80 - 1 | E25: =(J25*K25*PRECOS!N23) -> 38.25885 | F25: 105/83 | G25: 500 | H25: 42 | J25: =83/1 -> 83 | K25: 0.105
B26: 2935 | C26: DFAM 430 | D26: 100X80 - 1 | E26: =(J26*K26*PRECOS!N27) -> 52.02855 | F26: 105/83 | G26: 500 | H26: 42 | J26: =83/1 -> 83 | K26: 0.105
B28: 1468 | C28: COUCHE ACRILICO | D28: 100X75 - 1 | E28: =(J28*K28*PRECOS!N21) -> 24.7338 | F28: 105/78 | G28: 500 | H28: 39 | J28: =78/1 -> 78 | K28: 0.105
B29: 2581 | C29: COUCHE BORRACHA | D29: 100X75 - 1 | E29: =(J29*K29*PRECOS!N22) -> 24.3243 | F29: 105/78 | G29: 500 | H29: 39 | J29: =78/1 -> 78 | K29: 0.105
B30: 2050 | C30: BOPP ACRILICO | D30: 100X75 - 1 | E30: =J30*K30*PRECOS!#REF! -> #REF! | F30: 105/78 | G30: 500 | H30: 39 | J30: =78/1 -> 78 | K30: 0.105
B32: 1545 | C32: COUCHE ACRILICO | D32: 100X68 - 1 | E32: =(J32*K32*PRECOS!N21) -> 22.67265 | F32: 105/71,5 | G32: 500 | H32: 36 | J32: =71.5/1 -> 71.5 | K32: 0.105
B33: 2576 | C33: COUCHE ACR COLORIDO | D33: 100X68 - 1 | E33: =(J33*K33*PRECOS!Y21) -> 24.9249 | F33: 105/71,5 | G33: 1000 | H33: 72 | J33: =71.5/1 -> 71.5 | K33: 0.105
B34: 2589 | C34: COUCHE BORR COLORIDO | D34: 100X68 - 1 | E34: =(J34*K34*PRECOS!Y22) -> 24.549525 | F34: 105/71,5 | G34: 500 | H34: 36 | J34: =71.5/1 -> 71.5 | K34: 0.105
B36: 879 | C36: COUCHE ACRILICO | D36: 100X60 - 1 | E36: =(J36*K36*PRECOS!N21) -> 19.81875 | F36: 105/62,5 | G36: 700 | H36: 44 | J36: =62.5/1 -> 62.5 | K36: 0.105
B37: 2244 | C37: COUCHE BORRACHA | D37: 100X60 - 1 | E37: =(J37*K37*PRECOS!N22) -> 19.490625 | F37: 105/62,5 | G37: 700 | H37: 44 | J37: =62.5/1 -> 62.5 | K37: 0.105
B38: 1363 | C38: BOPP ACRILICO | D38: 100X60 - 1 | E38: =(J38*K38*PRECOS!#REF!) -> #REF! | F38: 105/62,5 | G38: 700 | H38: 44 | J38: =62.5/1 -> 62.5 | K38: 0.105
B39: 2948 | C39: COUCHE TÉRMICO | D39: 100X60 - 1 | E39: =(J39*K39*PRECOS!#REF!) -> #REF! | F39: 105/62,5 | G39: 700 | H39: 44 | J39: =62.5/1 -> 62.5 | K39: 0.105
B40: 2983 | C40: COUCHE REMOVIVEL | D40: 100X60 - 1 | E40: =(J40*K40*PRECOS!#REF!) -> #REF! | F40: 105/62,5 | G40: 700 | H40: 44 | J40: =62.5/1 -> 62.5 | K40: 0.105
B41: 1403 | C41: COUCHE COLORIDO | D41: 100X60 - 1 | E41: =(J41*K41*PRECOS!Y21) -> 21.7875 | F41: 105/62,5 | G41: 700 | H41: 44 | J41: =62.5/1 -> 62.5 | K41: 0.105
B43: 753 | C43: COUCHE ACRILICO | D43: 100X50 - 1 | E43: =(J43*K43*PRECOS!N21) -> 16.8063 | F43: 105/53 | G43: 800 | H43: 42 | J43: =53/1 -> 53 | K43: 0.105
B44: 2438 | C44: COUCHE BORRACHA | D44: 100X50 - 1 | E44: =(J44*K44*PRECOS!N22) -> 16.52805 | F44: 105/53 | G44: 800 | H44: 42 | J44: =53/1 -> 53 | K44: 0.105
B45: 1376 | C45: COUCHE COLORIDO | D45: 100X50 - 1 | E45: =(J45*K45*PRECOS!Y21) -> 18.4758 | F45: 105/53 | G45: 800 | H45: 42 | J45: =53/1 -> 53 | K45: 0.105
B46: 1477 | C46: COUCHE REMOVIVEL | D46: 100X50 - 1 | E46: =(J46*K46*PRECOS!#REF!) -> #REF! | F46: 105/53 | G46: 800 | H46: 42 | J46: =53/1 -> 53 | K46: 0.105
B47: 1095 | C47: BOPP ACRILICO | D47: 100X50 - 1 | E47: =(J47*K47*PRECOS!#REF!) -> #REF! | F47: 105/53 | G47: 1000 | H47: 53 | J47: =53/1 -> 53 | K47: 0.105
B48: 3096 | C48: BOPP BORRACHA | D48: 100X50 - 1 | E48: =(J48*K48*PRECOS!N23) -> 24.43035 | F48: 105/53 | G48: 1000 | H48: 53 | J48: =53/1 -> 53 | K48: 0.105
B50: 3500 | C50: COUCHE ACRILICO | D50: 100X45 - 1 | E50: =(J50*K50*PRECOS!N27) -> 30.0888 | F50: 105/48 | G50: 1000 | H50: 48 | J50: 48 | K50: 0.105
B52: 838 | C52: COUCHE ACRILICO | D52: 100X40 - 1 | E52: =(J52*K52*PRECOS!N21) -> 13.6353 | F52: 105/43 | G52: 1000 | H52: 43 | J52: =43/1 -> 43 | K52: 0.105
B53: 2590 | C53: COUCHE BORRACHA | D53: 100X40 - 1 | E53: =(J53*K53*PRECOS!N22) -> 13.40955 | F53: 105/43 | G53: 1000 | H53: 43 | J53: =43/1 -> 43 | K53: 0.105
B54: 1483 | C54: BOPP ACRILICO | D54: 100X40 - 1 | E54: =(J54*K54*PRECOS!#REF!) -> #REF! | F54: 105/43 | G54: 1000 | H54: 43 | J54: =43/1 -> 43 | K54: 0.105
B55: 2560 | C55: BOPP BORRACHA | D55: 100X40 - 1 | E55: =(J55*K55*PRECOS!N23) -> 19.82085 | F55: 105/43 | G55: 1000 | H55: 43 | J55: =43/1 -> 43 | K55: 0.105
B56: 2051 | C56: COUCHE TERMICO | D56: 100X40 - 1 | E56: =(J56*K56*PRECOS!#REF!) -> #REF! | F56: 105/43 | G56: 1000 | H56: 43 | J56: =43/1 -> 43 | K56: 0.105
B58: 1007 | C58: COUCHE ACRILICO | D58: 100X38 - 1 | E58: =(J58*K58*PRECOS!N21) -> 12.684 | F58: 105/40 | G58: 1000 | H58: 40 | J58: 40 | K58: 0.105
B60: 1862 | C60: COUCHE ACRILICO | D60: 100X35 - 1 | E60: =(J60*K60*PRECOS!N21) -> 12.0498 | F60: 105/38 | G60: 1000 | H60: 38 | J60: 38 | K60: 0.105
B61: 2875 | C61: TERMICO | D61: 100X35 -1 | E61: =(J61*K61*PRECOS!#REF!) -> #REF! | F61: 105/38 | G61: 1000 | H61: 38 | J61: 38 | K61: 0.105
B62: 1853 | C62: BOPP ACRILICO | D62: 100X35 - 1 | E62: =(J62*K62*PRECOS!#REF!) -> #REF! | F62: 105/38 | G62: 1000 | H62: 38 | J62: 38 | K62: 0.105
B64: 1098 | C64: COUCHE ACRILICO | D64: 90X80 - 1 | E64: =(J64*K64*PRECOS!N21) -> 23.66925 | F64: 95/82,5 | G64: 500 | H64: 41 | J64: =82.5/1 -> 82.5 | K64: 0.095
B65: 607 | C65: BOPP ACRILICO | D65: 90X80 - 1 | E65: =(J65*K65*PRECOS!#REF!) -> #REF! | F65: 95/82,5 | G65: 500 | H65: 41 | J65: =82.5/1 -> 82.5 | K65: 0.095
B67: 2186 | C67: COUCHE ACRILICO | D67: 90X40 - 1 | E67: =(J67*K67*PRECOS!N21) -> 12.19325 | F67: 95/42,5 | G67: 1000 | H67: 43 | J67: =42.5/1 -> 42.5 | K67: 0.095
B68: 1210 | C68: BOPP ACRILICO | D68: 90X40 - 1 | E68: =(J68*K68*PRECOS!#REF!) -> #REF! | F68: 95/42,5 | G68: 1000 | H68: 43 | J68: =42.5/1 -> 42.5 | K68: 0.095
B70: 2740 | C70: COUCHE ACRILICO | D70: 90x36 - 1 | E70: =(J70*K70*PRECOS!N21) -> 12.08 | F70: 100/40 | G70: 1000 | H70: 40 | J70: =40/1 -> 40 | K70: 0.1
B72: 2266 | C72: COUCHE ACRILICO | D72: 90X25 - 1 | E72: =(J72*K72*PRECOS!N21) -> 8.0332 | F72: 95/28 | G72: 1500 | H72: 42 | J72: =28/1 -> 28 | K72: 0.095
B73: 1599 | C73: BOPP ACRILICO | D73: 90X25 - 1 | E73: =(J73*K73*PRECOS!#REF!) -> #REF! | F73: 95/28 | G73: 1500 | H73: 42 | J73: =28/1 -> 28 | K73: 0.095
B75: 1467 | C75: COUCHE ACRILICO | D75: 85X50 | E75: =(J75*K75*PRECOS!N21) -> 14.4054 | F75: 90/53 | G75: 800 | H75: 42 | J75: 53 | K75: 0.09
B78: 2264 | C78: COUCHE ACRILICO | D78: 80X60 - 1 | E78: =(J78*K78*PRECOS!N21) -> 16.1721 | F78: 85/63 | G78: 700 | H78: 44 | J78: 63 | K78: 0.085
B79: 684 | C79: BOPP ACRILICO | D79: 80X60 - 1 | E79: =(J79*K79*PRECOS!#REF!) -> #REF! | F79: 85/63 | G79: 700 | H79: 44 | J79: 63 | K79: 0.085
B81: 2561 | C81: COUCHE ACRILICO | D81: 77X32 - 1 | E81: =(J81*K81*PRECOS!N21) -> 8.9845 | F81: 85/35 | G81: 2500 | H81: 87.5 | J81: 35 | K81: 0.085
B83: 885 | C83: COUCHE ACRILICO | D83: 70X50 - 1 | E83: =(J83*K83*PRECOS!N21) -> 12.0045 | F83: 75/53 | G83: 700 | H83: 37 | J83: =53/1 -> 53 | K83: 0.075
B85: 2490 | C85: BOPP ACRILICO | D85: 64X10 - Jóia | E85: =(J85*K85*PRECOS!#REF!) -> #REF! | F85: 80/13 | G85: 2500 | H85: 33 | J85: =13/1 -> 13 | K85: 0.08
B86: 2715 | C86: BOPP AMARELO | D86: 64X10 - Jóia | E86: =(J86*K86*PRECOS!#REF!) -> #REF! | F86: 110/13 | G86: 2500 | H86: 33 | J86: =13/1 -> 13 | K86: 0.11
B88: 2063 | C88: COUCHE TERMICO | D88: 61X75 - Balança | E88: =(J88*K88*PRECOS!#REF!) -> #REF! | F88: 130/78 | G88: 243 | H88: 19 | J88: =19/1 -> 19 | K88: 0.065
C89: COUCHE TERMICO | D89: 61X75 - Balança | E89: =(J89*K89*PRECOS!#REF!) -> #REF! | F89: 130/78 | G89: 345 | H89: 27 | J89: =27/1 -> 27 | K89: 0.065
B91: 2804 | C91: COUCHE ACRILICO | D91: 56X23 - 1 | E91: =(J91*K91*PRECOS!N21) -> 9.4224 | F91: 60/26 | G91: 2000 | H91: 52 | J91: 52 | K91: 0.06
B93: 2515 | C93: COUCHE ACRILICO | D93: 55X28 - 2 S/E | E93: =(J93*K93*PRECOS!N21) -> 5.85125 | F93: 125/31 | G93: 2500 | H93: 39 | J93: =31/2 -> 15.5 | K93: 0.125
B94: 2357 | C94: COUCHE ACRILICO | D94: 55X28 - 1 | E94: =(J94*K94*PRECOS!N21) -> 5.6172 | F94: 60/31 | G94: 1500 | H94: 46 | J94: =31/1 -> 31 | K94: 0.06
B95: 2765 | C95: COUCHE AMARELO | D95: 55X28 - 2 S/E | E95: =(J95*K95*PRECOS!AA21) -> 6.4325 | F95: 125/31 | G95: 1250 | H95: 39 | J95: =31/2 -> 15.5 | K95: 0.125
C97: TAG TERMICO | D97: 50X105 | F97: 60/105 | G97: 300 | H97: 32
B99: 818 | C99: COUCHE ACRILICO | D99: 50X70 - 2 | E99: =(J99*K99*PRECOS!N21) -> 11.90484 | F99: 108/73 | G99: 1250 | H99: 46 | J99: =73/2 -> 36.5 | K99: 0.108
B100: 2586 | C100: COUCHE BORRACHA | D100: 50X70 - 2 | E100: =(J100*K100*PRECOS!N22) -> 11.70774 | F100: 108/73 | G100: 1250 | H100: 46 | J100: =73/2 -> 36.5 | K100: 0.108
B102: 822 | C102: COUCHE ACRILICO | D102: 50X50 - 2 | E102: =(J102*K102*PRECOS!N21) -> 8.64324 | F102: 108/53 | G102: 1500 | H102: 40 | J102: =53/2 -> 26.5 | K102: 0.108
B103: 2881 | C103: COUCHE BORRACHA | D103: 50X50 - 2 | E103: =(J103*K103*PRECOS!N22) -> 8.50014 | F103: 108/53 | G103: 1500 | H103: 40 | J103: =53/2 -> 26.5 | K103: 0.108
B104: 1712 | C104: COUCHE BORRACHA | D104: 50X50 - 1 | E104: =(J104*K104*PRECOS!N22) -> 8.50014 | F104: 108/53 | G104: 750 | H104: 40 | J104: =53/1 -> 53 | K104: 0.054
B106: 855 | C106: COUCHE ACRILICO | D106: 50X40 - 2 | E106: =(J106*K106*PRECOS!N21) -> 6.84936 | F106: 108/42 | G106: 2000 | H106: 42 | J106: =42/2 -> 21 | K106: 0.108
B107: 2412 | C107: BOPP ACRILICO | D107: 50X40 - 2 | E107: =(J107*K107*PRECOS!#REF!) -> #REF! | F107: 108/42 | G107: 2000 | H107: 42 | J107: =42/2 -> 21 | K107: 0.108
B108: 2903 | C108: COUCHE VERMELHO | D108: 50X40 - 2 | E108: =(J108*K108*PRECOS!Y21) -> 7.52976 | F108: 108/42 | G108: 2000 | H108: 42 | J108: =42/2 -> 21 | K108: 0.108
B110: 1350 | C110: COUCHE ACRILICO | D110: 50X35 - 1 | F110: 108/39 | G110: 2000 | H110: 39 | J110: 19.5 | K110: 0.108
B112: 1397 | C112: COUCHE ACRILICO | D112: 50X30 - 2 | E112: =(J112*K112*PRECOS!N21) -> 5.38164 | F112: 108/33 | G112: 2500 | H112: 42 | J112: =33/2 -> 16.5 | K112: 0.108
B113: 1555 | C113: COUCHE ACRILICO | D113: 50X30 - 1 | E113: =(J113*K113*PRECOS!N21) -> 5.4813 | F113: 55/33 | G113: 1250 | H113: 42 | J113: =33/1 -> 33 | K113: 0.055
B114: 2908 | C114: COUCHE BORRACHA | D114: 50X30 - 2 | E114: =(J114*K114*PRECOS!N22) -> 5.29254 | F114: 108/33 | G114: 2500 | H114: 42 | J114: =33/2 -> 16.5 | K114: 0.108
B115: 3016 | C115: COUCHE REMOVIVEL | D115: 50X30 - 2 | E115: =(J115*K115*PRECOS!#REF!) -> #REF! | F115: 108/33 | G115: 2500 | H115: 42 | J115: =33/2 -> 16.5 | K115: 0.108
B117: 3295 | C117: COUCHE ACRILICO | D117: 50X25 - 2 | F117: 110/28 | G117: 3000 | H117: 42 | J117: 14 | K117: 0.11
B119: 908 | C119: COUCHE ACRILICO | D119: 50X20 - 2 | E119: =(J119*K119*PRECOS!N21) -> 3.75084 | F119: 108/23 | G119: 3500 | H119: 41 | J119: =23/2 -> 11.5 | K119: 0.108
B120: 1395 | C120: BOPP ACRILICO | D120: 50X20 - 2 | E120: =(J120*K120*PRECOS!#REF!) -> #REF! | F120: 108/23 | G120: 4000 | H120: 46 | J120: =23/2 -> 11.5 | K120: 0.108
B122: 2720 | C122: COUCHE ACRILICO | D122: 47x22 - 2 | E122: =(J122*K122*PRECOS!N21) -> 3.8052 | F122: 105/24 | G122: 3000 | H122: 36 | J122: 12 | K122: 0.105
B124: 1106 | C124: COUCHE ACRILICO | D124: 45X35 - 2 | E124: =(J124*K124*PRECOS!N21) -> 5.587 | F124: 100/37 | G124: 2500 | H124: 47 | J124: =37/2 -> 18.5 | K124: 0.1
B125: 2823 | C125: COUCHE AMARELO | D125: 45X35 - 2 | E125: =(J125*K125*PRECOS!Y21) -> 6.4491 | F125: 105/37 | G125: 2500 | H125: 47 | J125: =37/2 -> 18.5 | K125: 0.105
B127: 2039 | C127: COUCHE ACRILICO | D127: 40X55 - 2 | E127: =(J127*K127*PRECOS!N21) -> 7.8822 | F127: 90/58 | G127: 1500 | H127: 44 | J127: =58/2 -> 29 | K127: 0.09
B129: 616 | C129: COUCHE ACRILICO | D129: 40X30 - 2 | E129: =(J129*K129*PRECOS!N21) -> 4.3488 | F129: 90/32 | G129: 2500 | H129: 40 | J129: 16 | K129: 0.09
B130: 2040 | C130: COUCHE AMARELO | D130: 40X30 - 2 | F130: 90/32 | G130: 2500 | H130: 40 | J130: 16 | K130: 0.09
B131: 3011 | C131: COUCHE VERMELHO | D131: 40X30 - 2 | F131: 90/32 | G131: 2500 | H131: 40 | J131: 16 | K131: 0.09
K132: 0.09
B133: 414 | C133: COUCHE ACRILICO | D133: 40X15 - 2 | E133: =(J133*K133*PRECOS!N21) -> 2.3103 | F133: 90/17 | G133: 5000 | H133: 43 | J133: =17/2 -> 8.5 | K133: 0.09
B134: 2481 | C134: COUCHE BORRACHA | D134: 40X15 - 2 | E134: =(J134*K134*PRECOS!N22) -> 2.27205 | F134: 90/17 | G134: 5000 | H134: 43 | J134: =17/2 -> 8.5 | K134: 0.09
B136: 2115 | C136: COUCHE TERMICO | D136: 39X40 - Balança | E136: =(J136*K136*PRECOS!#REF!) -> #REF! | F136: 125/43 | G136: 640 | H136: 27 | J136: 27 | K136: 0.042 | L136: 3.52
B137: 1614 | C137: COUCHE ACRILICO | D137: 40X40 - 2 | E137: =(J137*K137*PRECOS!N21) -> 5.51905 | F137: 85/43 | G137: 2000 | H137: 43 | J137: =43/2 -> 21.5 | K137: 0.085
B139: 4029 | C139: TAG 150g | D139: 35x62 - 3 | F139: 115/62 | G139: 1000 | H139: 21 | J139: 21 | K139: 0.115
B141: 1960 | C141: COUCHE ACRILICO | D141: 35X40 - 3 S/E | E141: =(J141*K141*PRECOS!N21) -> 4.7615333 | F141: 110/43 | G141: 3000 | H141: 43 | J141: =43/3 -> 14.333333 | K141: 0.11
B142: 3131 | C142: BOPP ACRILICO | D142: 35X40 - 3 S/E | E142: =(J142*K142*PRECOS!#REF!) -> #REF! | F142: 110/43 | G142: 3000 | H142: 43 | J142: =43/3 -> 14.333333 | K142: 0.11
C144: TAG PE TECH | D144: 34x51 - 3 | F144: 110/51 | G144: 3000 | H144: 51
J145: =43/2 -> 21.5
B146: 843 | C146: COUCHE ACRILICO | D146: 34x23 - 3 S/E | E146: =(J146*K146*PRECOS!N21) -> 2.718 | F146: 108/25 | G146: 5000 | H146: 42 | J146: =25/3 -> 8.3333333 | K146: 0.108
...

Sheet ABRIL20
A1: CLIENTE | B1: Data Entr | C1: Data Prod | D1: OC | E1: MATERIAL | F1: CÓDIGO | G1: ETIQUETA | H1: QUANT | I1: OK | J1: PRODUZIDO?
A2: PRO MARMO | B2: ??? | D2: 3487 | E2: BOPP | F2: 3127 | G2: 103X200 | H2: 200 | I2: OK | J2: ESPERAR | K2: ENVIADO AMOSTRA | L2: OK
A3: PORTAL USINAGEM | B3: 43913 | C3: 43935 | D3: 3571 | E3: TAG | F3: 3134 | G3: 95X39 | H3: 20000 | I3: OK | J3: LASER
A4: FRIZZO | B4: 43922 | C4: 43935 | D4: 3549 | E4: COUCHE | F4: 869 | G4: 33X25 | H4: 120000 | I4: OK | J4: FACA
A5: FRIZZO | B5: 43906 | C5: 43934 | D5: 3492 | E5: BOPP | F5: 3129 | G5: 50X18 | H5: 100000 | I5: OK
B6: 43903 | C6: 43908 | D6: 1418 | E6: BOPP | F6: 3129 | G6: 50X18 | H6: 52000 | I6: OK | J6: VITORIA
B7: 43903 | C7: 43934 | D7: 1418 | E7: BOPP | F7: 3129 | G7: 50X18 | H7: 48000 | I7: OK | J7: VITORIA
A8: DIAN | B8: 43910 | C8: 43934 | D8: 3558 | E8: COUCHE | F8: 1215 | G8: 40X34 | H8: 10000 | I8: OK
B9: 43910 | C9: 43934 | D9: 1429 | E9: COUCHE | F9: 1215 | G9: 40X34 | H9: 50000 | I9: OK | J9: VITORIA
A10: PLASMOSUL | B10: 43915 | C10: 43934 | D10: 3584 | E10: COUCHE | F10: 1186 | G10: 100X66 | H10: 9500 | I10: OK
B11: 43915 | C11: 43934 | D11: 1432 | E11: COUCHE | F11: 1186 | G11: 100X66 | H11: 9500 | I11: OK | J11: VITORIA
A12: CARRARO | B12: 43914 | C12: 43934 | D12: 3597 | E12: COUCHE | F12: 2263 | G12: 65X197 | H12: 10000 | I12: OK
B13: 43914 | C13: 43934 | D13: 1425 | E13: COUCHE | F13: 2263 | G13: 65X197 | H13: 10100 | I13: OK | J13: VITORIA
A14: RESET | B14: 43916 | C14: 43934 | D14: 3601 | E14: COUCHE | F14: 1173 | G14: 100X25 | H14: 18000 | I14: OK
B15: 43916 | C15: 43934 | D15: 1433 | E15: COUCHE | F15: 1173 | G15: 100X25 | H15: 19500 | I15: OK | J15: VITORIA
A16: JULIAS CLOSET | B16: 43916 | C16: 43934 | D16: 3608 | E16: COUCHE | F16: 1104 | G16: 20X38 | H16: 8000 | I16: OK
B17: 43916 | C17: 43934 | D17: 1434 | E17: COUCHE | F17: 1104 | G17: 20X38 | H17: 20000 | I17: OK | J17: VITORIA
A18: BARAO | B18: 43916 | C18: 43934 | D18: 3596 | E18: COUCHE | F18: 2410 | G18: 45X25 | H18: 10000 | I18: OK
B19: 43916 | C19: 43934 | D19: 1436 | E19: COUCHE | F19: 2410 | G19: 45X25 | H19: 10000 | I19: OK | J19: VITORIA
A20: FERPLAST | B20: 43920 | C20: 43934 | D20: 3630 | E20: COUCHE | F20: 1215 | G20: 40X34 | H20: 30000 | I20: OK
B21: 43910 | C21: 43934 | D21: 1429 | E21: COUCHE | F21: 1215 | G21: 40X34 | H21: 40000 | I21: OK | J21: VITORIA | P21: PAPEL | Q21: TAM | R21: M
A22: DIAN | B22: 43910 | C22: 43936 | D22: 3558 | E22: COUCHE | F22: 1513 | G22: 50X80 | H22: 1000 | I22: OK | J22: LASER | P22: COU.ACR | Q22: 110 | R22: 83
A23: G3 | B23: 43915 | C23: 43936 | D23: 3595 | E23: BOPP | F23: 3139 | G23: 78X25 | H23: 200 | I23: OK | J23: LASER | P23: BOPP | Q23: 85 | R23: 10
A24: INJET | B24: 43917 | C24: 43937 | D24: 3620 | E24: COUCHE | F24: 97 | G24: 80X90 | H24: 500 | I24: OK | J24: LASER | P24: COU.ACR | Q24: 85 | R24: 50
A25: PAPARASO | B25: 43920 | C25: 43941 | D25: 3631 | E25: COUCHE | F25: 2029 | G25: 35X30 | H25: 10000 | I25: OK | J25: LASER | N25: 2 | P25: COU.ACR | Q25: 110 | R25: 110
A26: RIO PRATA | B26: 43938 | C26: 43936 | D26: 3632 | E26: COUCHE | F26: 885 | G26: 70X50 | H26: 5600 | I26: OK | J26: FACA | P26: COU.ACR | Q26: 75 | R26: 270
A27: MCC | B27: 43941 | C27: 43938 | D27: 3658 | E27: C.BORR | F27: 2491 | G27: 100X90 | H27: 5000 | I27: OK | J27: LASER | N27: 1 | P27: COU.BORR | Q27: 105 | R27: 470
A28: PANIZZON | B28: 43938 | C28: 43937 | D28: 3569 | E28: COUCHE | F28: 1545 | G28: 100X68 | H28: 30000 | I28: OK | J28: FACA | P28: COUCHE | Q28: 105 | R28: 220
A29: MERC.MISS | B29: 43943 | C29: 43941 | D29: 3657 | E29: AMARELA | F29: 3149 | G29: 100X30 | H29: 2000 | I29: OK | J29: LASER | N29: 3 | P29: AMARELO | Q29: 105 | R29: 70
A30: ABRIL
A31: AESC | B31: 43908 | C31: 43934 | D31: 3516 | E31: TERMICO | F31: 2873 | G31: 33X22 | H31: 30000 | I31: OK
B32: 43921 | C32: 43934 | D32: 1437 | E32: TERMICO | F32: 2873 | G32: 33X22 | H32: 100000 | I32: OK | J32: VITORIA | K32: AESC
B33: 43921 | C33: 43934 | D33: 1437 | E33: TERMICO | F33: 3150 | G33: 34X23 | H33: 56000 | I33: OK | J33: VITORIA | K33: AESC
B34: 43921 | C34: 43934 | D34: 1437 | E34: TERMICO | F34: 3151 | G34: 70X30 | H34: 15000 | I34: OK | J34: VITORIA | K34: AESC
A35: GAMACOR | B35: 43927 | C35: 43934 | D35: 3568 | E35: COUCHE | F35: 1862 | G35: 100X35 | H35: 15000 | I35: OK
B36: 43913 | C36: 43934 | D36: 1430 | E36: COUCHE | F36: 1862 | G36: 100X35 | H36: 15000 | I36: OK | J36: VITORIA
A37: PORTAL USINAGEM | B37: 43934 | C37: 43934 | D37: 3571 | E37: COUCHE | F37: 1631 | G37: 60X60 | H37: 20250 | I37: OK
B38: 43913 | C38: 43934 | D38: 1431 | E38: COUCHE | F38: 1631 | G38: 60X60 | H38: 20250 | I38: OK | J38: VITORIA
A39: REZLER | B39: 43945 | C39: 43934 | D39: 3537 | E39: BOPP | F39: 2640 | G39: 80X50 | H39: 20000 | I39: OK
B40: 43910 | C40: 43934 | D40: 1428 | E40: BOPP | F40: 2640 | G40: 80X50 | H40: 20400 | I40: OK | J40: VITORIA
A41: WINELANDS | B41: 43938 | C41: 43935 | D41: 3656 | E41: COUCHE | F41: 2149 | G41: 70X40 | H41: 22800 | I41: OK
B42: 43938 | C42: 43935 | D42: 1438 | E42: COUCHE | F42: 2149 | G42: 70X40 | H42: 22800 | I42: OK | J42: G10
A43: SUPER MARCAS | B43: 43944 | C43: 43945 | D43: 3566 | E43: COUCHE | F43: 1350 | G43: 50X35 | H43: 10000 | I43: OK
A44: SUPER MARCAS | B44: 43944 | C44: 43945 | D44: 3567 | E44: COUCHE | F44: 1350 | G44: 50X35 | H44: 10000 | I44: OK
B45: 43944 | C45: 43945 | D45: 1441 | H45: 36000 | I45: OK | J45: VITORIA
A46: HOSP.SAO CARLOS | B46: 43941 | C46: 43943 | D46: 3639 | E46: BOPP | F46: 1491 | G46: 100X23 | H46: 20000 | I46: OK
B47: 43941 | C47: 43943 | D47: 1439 | H47: 20000 | I47: OK | J47: VITORIA
A48: INJET | B48: 43938 | C48: 43938 | D48: 3700 | E48: BOPP BORR | F48: 2494 | G48: 25X25 | H48: 20000 | I48: OK | K48: PERSONALIZAR
B49: 43938 | C49: 43938 | D49: 1440 | H49: 60000 | I49: OK | J49: VITORIA
A50: HOSP. SANTA ANA | B50: 43941 | C50: 43945 | D50: 3516 | E50: TERMICO | F50: 2873 | G50: 33X22 | H50: 30000 | I50: OK
B51: 43941 | C51: 43945 | D51: 1442 | H51: 50000 | I51: OK | J51: VITORIA
A52: BOI SUL | B52: 43942 | C52: 43944 | D52: 3703 | E52: BOPP BORR | F52: 2632 | G52: 103X94 | H52: 5000 | I52: OK
A53: FRIZZO | B53: 43944 | D53: 3614 | E53: BOPP | F53: 1405 | G53: 15X10 | H53: 50000 | I53: OK
D54: 1444 | H54: 100000 | I54: OK | J54: VITORIA
D55: 3614 | E55: BOPP | F55: 2724 | G55: 25X16 | H55: 50000 | I55: OK
D56: 1445 | H56: 50000 | I56: OK | J56: VITORIA
A57: POLIBOM | B57: 43944 | C57: 43945 | D57: 3152 | E57: COUCHE | F57: 3152 | G57: 100X200 | H57: 3000 | I57: OK
D58: 1446 | H58: 5000 | I58: OK | J58: VITORIA
A59: ZANLINE | B59: 43945 | C59: 43945 | D59: 3705 | E59: COUCHE | F59: 951 | G59: 100X150 | H59: 20000 | I59: OK
D60: 1447 | H60: 20000 | I60: OK | J60: VITORIA
A61: EBS DO BRASIL | B61: 43941 | C61: 43944 | D61: 3633 | E61: BOPP BORR | F61: 2329 | G61: 105X105 | H61: 5000 | I61: OK
C62: 43941 | D62: 1448 | H62: 5000 | I62: OK | J62: VITORIA
A63: HUGO PIETRO | B63: 43950 | D63: 3717 | E63: COUCHE | F63: 2264 | G63: 80X60 | H63: 45500 | I63: OK
D64: 1449 | H64: 45500 | I64: OK | J64: VITORIA
A65: FRIZZO | B65: 43931 | C65: 43943 | D65: 3615 | E65: COUCHE | F65: 855 | G65: 50X40 | H65: 150000 | I65: OK | J65: FACA | P65: COUCHE | Q65: 108 | R65: 3200
A66: LAMINA | B66: 43941 | C66: 43936 | D66: 3606 | E66: COUCHE | F66: 885 | G66: 70X50 | H66: 21700 | I66: OK | J66: FACA | L66: CONF | P66: COUCHE | Q66: 75 | R66: 1060
A67: FRIZZO | B67: 43941 | C67: 43941 | D67: 3616 | E67: COUCHE | F67: 869 | G67: 33X25 | H67: 200000 | I67: OK | J67: FACA | P67: COUCHE | Q67: 108 | R67: 1860
A68: CODETECH | B68: 43944 | C68: 43941 | D68: 3687 | E68: BOPP | F68: 2868 | G68: 85X10 | H68: 12000 | I68: OK | J68: LASER | P68: BOPP | Q68: 90 | R68: 170
A69: CODETECH | B69: 43944 | C69: 43943 | D69: 3736 | E69: BOPP | F69: 2868 | G69: 85X10 | H69: 12500 | I69: OK | J69: LASER
A70: TOP LIMP | B70: 43938 | D70: 3696 | E70: COUCHE | F70: 2515 | G70: 55X28 | H70: 10000 | I70: OK | J70: FACA
E71: AMARELO | F71: 2765 | G71: 55X28 | H71: 12500 | I71: OK | J71: FACA
A72: MAR AZUL | B72: 43945 | C72: 43943 | D72: 3692 | E72: BOPP | F72: 2175 | G72: 30X80 | H72: 2000 | I72: OK | J72: LASER
A73: DUKE | B73: 43945 | C73: 43944 | D73: 3691 | E73: COUCHE | F73: 2800 | G73: 45X45 | H73: 2000 | I73: OK | J73: LASER
C74: 43944 | F74: 2891 | G74: 60X60 | H74: 2000 | I74: OK | J74: LASER
A75: FIXPAR | B75: 43948 | C75: 43951 | D75: 3653 | E75: COUCHE | F75: 753 | G75: 100X50 | H75: 100800 | I75: OK | J75: FACA | M75: 1040 | P75: COUCHE | Q75: 105 | R75: 5300
A76: SEXY FANTASY | B76: 43948 | C76: 43944 | D76: 3697 | E76: COUCHE | F76: 1087 | G76: 28X55 | H76: 50000 | I76: OK | J76: FACA
E77: COUCHE | F77: 2825 | G77: 106X85 | H77: 3000 | I77: OK | J77: LASER
A78: VITAMED | B78: 43948 | C78: 43948 | D78: 3699 | E78: C.BORR | F78: 2581 | G78: 100X75 | H78: 25000 | I78: OK | J78: FACA | M78: 700
A79: BOI SUL | B79: 43945 | C79: 43944 | D79: 3703 | E79: SYP | F79: 2631 | G79: 75X263 | H79: 5000 | I79: OK | J79: LASER
A80: BOI SUL | B80: 43945 | C80: 43941 | D80: 3703 | E80: COUCHE | F80: 2039 | G80: 40X55 | H80: 6000 | I80: OK | J80: FACA
A81: POLIBOM | B81: 43944 | C81: 43941 | D81: 3714 | E81: COUCHE | F81: 2039 | G81: 40X55 | H81: 10500 | I81: OK | J81: FACA
A82: PANIZZON | B82: 43949 | D82: 3716 | E82: COUCHE | F82: 2448 | G82: 100X68 | H82: 10000 | I82: OK | J82: FACA | M82: 623.2
E83: COUCHE | F83: 2449 | G83: 100X68 | H83: 9000 | I83: OK | J83: FACA
A84: BRASUD | B84: 43950 | C84: 43950 | D84: 3719 | E84: COUCHE | F84: 1960 | G84: 35X45 | H84: 21000 | I84: OK | J84: FACA | M84: 454
A85: LC SOLUCOES | B85: 43950 | C85: 43948 | D85: 3721 | E85: TAG | F85: 1112 | G85: 50X75 | H85: 20000 | I85: OK | J85: LASER | M85: 310
A86: INJET | B86: 43950 | C86: 43945 | D86: 3724 | E86: COUCHE | F86: 97 | G86: 80X90 | H86: 2000 | I86: OK | J86: LASER
A87: FRIZZO | B87: 43951 | C87: 43950 | D87: 3617 | E87: COUCHE | F87: 2664 | G87: 15X30 | H87: 245000 | I87: OK | J87: FACA | M87: 560 | P87: COUCHE | Q87: 108 | R87: 1100
A88: CODETECH | B88: 43951 | C88: 43951 | D88: 3733 | E88: COUCHE | F88: 3020 | G88: 40X40 | H88: 60000 | I88: OK | J88: FACA | M88: 660
A89: PROMARMO | B89: 43951 | C89: 43949 | D89: 3487 | E89: BOPP | F89: 3127 | G89: 103X200 | H89: 3000 | I89: OK | J89: LASER | M89: 627
A90: VERITA | B90: 43955 | C90: 43949 | D90: 3735 | E90: COUCHE | F90: 3157 | G90: 105X35 | H90: 5000 | I90: OK | J90: LASER | M90: 127
A91: DELRA FIRE | B91: 43956 | C91: 43950 | D91: 3746 | E91: BOPP | F91: 2771 | G91: 35X21 | H91: 50000 | I91: OK | J91: LASER
F92: 1853 | G92: 100X35 | H92: 4000 | I92: OK | J92: LASER | M92: 475.26
A93: SUSIN | B93: 43957 | C93: 43951 | D93: 3745 | E93: COUCHE | F93: 343 | G93: 50X22 | H93: 5000 | I93: OK | J93: LASER | M93: 175
A94: TRANSFER | B94: 43957 | C94: 43951 | D94: 3749 | E94: COUCHE | F94: 1287 | G94: 105X75 | H94: 2000 | I94: OK | J94: LASER | M94: 158
A95: DOMAMA | B95: 43955 | C95: 43951 | D95: 3738 | E95: COUCHE | F95: 838 | G95: 100X40 | H95: 7000 | I95: OK | J95: FACA
F96: 2515 | G96: 55X28 | H96: 5000 | I96: OK | J96: FACA | M96: 147.25
A97: HAUSSHOP | B97: 43957 | C97: 43951 | D97: 3751 | E97: COUCHE | F97: 3161 | G97: 100X115 | H97: 2000 | I97: OK | J97: BETA | M97: 159.1

Sheet MAIO20
A1: CLIENTE | B1: Data Entr | C1: Data Prod | D1: O/F | E1: MATERIAL | F1: CÓDIGO | G1: ETIQUETA | H1: QUANT | I1: OK | J1: PRODUZIDO POR | K1: O/C | L1: VALOR
A2: BP COMPON | B2: 43955 | C2: 43955 | D2: 3641 | E2: POLIESTER | F2: 1183 | G2: 30X15 | H2: 10000 | I2: OK
B3: 43955 | D3: 1450 | H3: 10000 | I3: OK | J3: LABEL | L3: 1049.4
A4: BOI SUL | B4: 43942 | D4: 1443 | E4: BOPP BORR | F4: 2362 | G4: 103X94 | H4: 10000 | L4: CANC
A5: FRIZZO | B5: 43936 | C5: 43957 | D5: 3621 | E5: COUCHE | F5: 1468 | G5: 100X75 | H5: 20000 | I5: OK | J5: FACA
A6: MARTIPLAST | B6: 44071 | D6: 0 | E6: BOPP | F6: 0 | G6: 34X34 | H6: 200 | J6: LASER | K6: ??? | L6: AMOS
E7: BOPP REM | F7: 0 | G7: 34X34 | H7: 200 | J7: LASER | K7: ??? | L7: AMOS
A8: CRIPPA | B8: 43957 | C8: 43955 | D8: 3744 | E8: COUCHE | F8: 1098 | G8: 90X80 | H8: 40000 | I8: OK | J8: FACA | L8: 1200
A9: VITAMED | B9: 43957 | C9: 43956 | D9: 3752 | E9: COUCHE | F9: 838 | G9: 100X40 | H9: 22000 | I9: OK | J9: FACA | L9: 700
A10: FRIZZO | B10: 43958 | C10: 43956 | D10: 3761 | E10: COUCHE | F10: 1468 | G10: 100X75 | H10: 10000 | I10: OK | J10: FACA | L10: 289
A11: FLORENZA | B11: 43958 | C11: 43955 | D11: 3767 | E11: COUCHE | F11: 1862 | G11: 100X30 | H11: 10000 | I11: OK | J11: LASER | L11: 254
A12: LOJA HIP | B12: 43958 | C12: 43959 | D12: 3766 | E12: COUCHE | F12: 1556 | G12: 55X25 | H12: 21000 | I12: OK | J12: JUCA | K12: 1457 | L12: 207
A13: SULPACK | B13: 43959 | C13: 43956 | D13: 3768 | E13: BOPP | F13: 1401 | G13: 50X22 | H13: 6000 | I13: OK | J13: LASER | L13: 210
A14: UNIMED | B14: 43959 | C14: 43956 | D14: 3769 | E14: COUCHE | F14: 2740 | G14: 90X36 | H14: 10000 | I14: OK | J14: FACA | L14: 148
A15: CARGA FACIL | B15: 43962 | C15: 43957 | D15: 3779 | E15: COUCHE | F15: 940 | G15: 90X20 | H15: 5000 | I15: OK | J15: LASER | L15: 22.5
A16: IPICARD | B16: 43962 | C16: 43956 | D16: 3781 | E16: BOPP | F16: 1401 | G16: 50X22 | H16: 18000 | I16: OK | J16: LASER | L16: 288
A17: AGRO. FERR | B17: 43962 | C17: 43958 | D17: 3784 | E17: DFAM | F17: 3165 | G17: 50X10 | H17: 5000 | I17: OK | J17: LASER
C18: 43963 | E18: DFAM | F18: 2935 | G18: 100X80 | H18: 17450 | I18: OK | J18: JUCA | K18: 1458 | L18: 1874
A19: FRIZZO | B19: 43963 | C19: 43959 | D19: 3789 | E19: C.BORR | F19: 3168 | G19: 100X76 | H19: 10000 | I19: OK | J19: LASER | L19: 275.5
A20: BP COMPON | B20: 43963 | C20: 43963 | D20: 3791 | E20: POLIESTER | F20: 1183 | G20: 30X15 | H20: 9000 | I20: OK
D21: 1453 | H21: 9000 | I21: OK | J21: LABEL | L21: 912.6
A22: BANCO SANGUE | B22: 43963 | C22: 43956 | D22: 3792 | E22: BOPP | F22: 2557 | G22: 55X28 | H22: 15500 | I22: OK | J22: FACA | L22: 187.5
A23: INJET | B23: 43963 | C23: 43955 | D23: 3793 | E23: BOPP | F23: 2494 | G23: 25X25 | H23: 15000 | I23: OK | J23: LASER | L23: 550
A24: IMPACOL | B24: 43963 | C24: 43958 | D24: 3801 | E24: COUCHE | F24: 950 | G24: 100X65 | H24: 17000 | I24: OK | J24: JUCA | K24: 1455 | L24: 680
A25: CODETECH | B25: 43964 | C25: 43957 | D25: 3802 | E25: COUCHE | F25: 2690 | G25: 33X25 | H25: 50000 | I25: OK | J25: FACA | L25: 225
A26: G3 | B26: 43964 | C26: 43963 | D26: 3808 | E26: BOPP | F26: 3139 | G26: 78X25 | H26: 5000 | I26: OK | J26: LASER | L26: 108.5
A27: ZANETTI | B27: 43964 | C27: 43959 | D27: 3809 | E27: COUCHE | F27: 1677 | G27: 33X22 | H27: 30000 | I27: OK | J27: JUCA | K27: 1456 | L27: 138
A28: BASFIX | B28: 43964 | C28: 43964 | D28: 3810 | E28: COUCHE | F28: 2733 | G28: 100X75 | H28: 5000 | I28: OK | J28: FACA | K28: PERSONAL
E29: COUCHE | F29: 1468 | G29: 100X75 | H29: 11000 | I29: OK | J29: FACA | L29: 711
A30: FRIZZO | B30: 43959 | C30: 43958 | D30: 3798 | E30: COUCHE | F30: 1545 | G30: 100X68 | H30: 20000 | I30: OK | J30: FACA | L30: 483
A31: FRIZZO | B31: 43964 | C31: 43963 | D31: 3799 | E31: COUCHE | F31: 1139 | G31: 108X87 | H31: 9800 | I31: OK | J31: LASER | L31: 362.5
A32: LESI | B32: 43966 | C32: 43958 | D32: 3824 | E32: BOPP | F32: 1599 | G32: 90X25 | H32: 5000 | I32: OK | J32: FACA | L32: 211
A33: SÃO CARLOS | B33: 43962 | C33: 43963 | D33: 3774 | E33: COUCHE | F33: 3162 | G33: 34X23 | H33: 20000 | I33: OK | J33: JUCA | K33: 1459
F34: 3163 | G34: 34X23 | H34: 20000 | I34: OK | J34: JUCA | K34: 1459 | L34: 322.8
A35: LC | B35: 43963 | C35: 43962 | D35: 3830 | E35: BOPP | F35: 3095 | G35: 100X60 | H35: 10000 | I35: OK | J35: FACA | L35: 508
A36: LC | B36: 43963 | C36: 43962 | D36: 3096 | E36: BOPP | F36: 3096 | G36: 100X50 | H36: 20000 | I36: OK | J36: FACA | L36: 970
A37: RR VISION | B37: 43965 | C37: 43964 | D37: 3829 | E37: BOPP | F37: 2844 | G37: 48X10 | H37: 10000 | I37: OK | J37: LASER | L37: 66
A38: BRICASA | B38: 43965 | C38: 43959 | D38: 3818 | E38: C.BORR | F38: 2481 | G38: 40X15 | H38: 505000 | I38: OK | J38: FACA | L38: 1935
A39: FOODCHAIN | B39: 43966 | C39: 43959 | D39: 3833 | E39: BOPP | F39: 2172 | G39: 33X25 | H39: 30000 | I39: OK | J39: FACA | L39: 327
A40: G3 | B40: 43959 | C40: 43959 | D40: 3842 | E40: COUCHE | F40: 1397 | G40: 50X30 | H40: 35000 | I40: OK | J40: FACA | L40: 280
A41: LAMINA | B41: 43963 | C41: 43962 | D41: 3607 | E41: COUCHE | F41: 885 | G41: 70X50 | H41: 23100 | I41: OK | J41: FACA | L41: 300
A42: CODETECH | B42: 43970 | D42: 3841 | E42: TAG | F42: 1316 | G42: 95X30 | H42: 2000 | I42: OK | J42: LASER
F43: 3170 | G43: 70X30 | H43: 1000 | I43: OK | J43: LASER | L43: 45.4
A44: FRIZZO | B44: 43964 | C44: 43964 | D44: 3788 | E44: COUCHE | F44: 2186 | G44: 90X40 | H44: 33000 | I44: OK | J44: FACA | L44: 771.5
A45: ESTOQUE | B45: 43962 | C45: 43963 | D45: 0 | E45: COUCHE | F45: 838 | G45: 100X40 | H45: 19000 | I45: OK | J45: FACA
A46: FRIZZO | B46: 43964 | C46: 43964 | D46: 3859 | E46: COUCHE | F46: 2186 | G46: 90X40 | H46: 50000 | I46: OK | J46: FACA | L46: 637.5
A47: HOSP.CIRCULO | B47: 43971 | C47: 43963 | D47: 3863 | E47: COUCHE | F47: 838 | G47: 100X40 | H47: 5000 | I47: OK | J47: FACA | L47: 120
A48: SULPACK | B48: 43964 | C48: 43964 | D48: 3874 | E48: BOPP | F48: 1401 | G48: 50X22 | H48: 12000 | I48: OK | J48: LASER | L48: 234
A49: EBS | B49: 43969 | C49: 43966 | D49: 3854 | E49: BOPP | F49: 2329 | G49: 105X105 | H49: 6000 | I49: OK | J49: LASER/FACA | L49: 712.2
A50: FIXPAR | B50: 43966 | C50: 43964 | D50: 3872 | E50: AZUL | F50: 3171 | G50: 50X70 | H50: 3000 | I50: OK | J50: FACA
E51: AMARELO | F51: 3172 | G51: 50X70 | H51: 3000 | I51: OK | J51: FACA | L51: 130.8
A52: UNIMED | B52: 43966 | C52: 43964 | D52: 3873 | E52: COUCHE | F52: 2740 | G52: 90X36 | H52: 10000 | I52: OK | J52: FACA | L52: 433
A53: FRIZZO | B53: 43971 | C53: 43963 | D53: 1328 | E53: COUCHE | F53: 1869 | G53: 33X21 | H53: 80000 | I53: OK | J53: FACA | L53: CONF
A54: HYVA | B54: 43971 | C54: 43965 | D54: 3875 | E54: C.BORR | F54: 2244 | G54: 100X60 | H54: 10500 | I54: OK | J54: FACA
E55: C.BORR | F55: 1712 | G55: 50X50 | H55: 7500 | I55: OK | J55: FACA
E56: TAG | F56: 2550 | G56: 100X70 | H56: 7900 | I56: OK | J56: LASER | L56: 1214.25
A57: SEXY FANTASY | B57: 43966 | C57: 43964 | D57: 3877 | E57: COUCHE | F57: 1087 | G57: 28X55 | H57: 60000 | I57: OK | J57: FACA | L57: 630
A58: PETRYMAR | B58: 43969 | C58: 43965 | D58: 3881 | E58: COUCHE | F58: 753 | G58: 100X50 | H58: 20000 | I58: OK | J58: FACA | L58: 500
A59: CEMTRA | B59: 43969 | C59: 43965 | D59: 3883 | E59: COUCHE | F59: 2691 | G59: 100X50 | H59: 3000 | I59: OK | J59: FACA/LASER | K59: PICOTE | L59: 126
A60: CODETECH | B60: 43971 | C60: 43966 | D60: 3885 | E60: COUCHE | F60: 855 | G60: 50X40 | H60: 50000 | I60: OK | J60: FACA | L60: 450
A61: MA ACESS | B61: 43971 | C61: 43973 | D61: 3884 | E61: COUCHE | F61: 2561 | G61: 77X32 | H61: 100000 | I61: OK | J61: LASER | L61: 1000
A62: FRIZZO | B62: 43972 | C62: 43966 | D62: 3887 | E62: BOPP | F62: 758 | G62: 100X20 | H62: 10000 | I62: OK | J62: LASER
C63: 43966 | E63: COUCHE | F63: 1786 | G63: 90X25 | H63: 10000 | I63: OK | J63: FACA | L63: 475.5
A64: FRIZZO | B64: 43966 | C64: 43966 | D64: 3899 | E64: COUCHE | F64: 869 | G64: 33X25 | H64: 10000 | I64: OK | J64: FACA
E65: REMOV | F65: 2548 | G65: 33X25 | H65: 10000 | I65: OK | J65: FACA | L65: 95
A66: TOP LIMP | B66: 43966 | D66: 3901 | E66: COUCHE | F66: 2515 | G66: 55X28 | H66: 10000 | I66: OK | J66: FACA
E67: AMARELA | F67: 2765 | G67: 55X28 | H67: 10000 | I67: OK | J67: FACA | L67: 287.5
A68: DUKE | B68: 43880 | C68: 43972 | D68: 3911 | E68: COUCHE | F68: 2891 | G68: 60X60 | H68: 3000 | I68: OK | J68: LASER
E69: COUCHE | F69: 2800 | G69: 45X45 | H69: 3000 | I69: OK | J69: LASER | L69: 351
A70: FIXPAR | B70: 43971 | C70: 43971 | D70: 3912 | E70: BOPP | F70: 2957 | G70: 90X60 | H70: 2100 | I70: OK | J70: LASER
E71: AZUL | F71: 2952 | G71: 90X60 | H71: 2100 | I71: OK | J71: LASER
E72: VERDE | F72: 2950 | G72: 90X60 | H72: 2100 | I72: OK | J72: LASER
E73: AMAR | F73: 2951 | G73: 90X60 | H73: 2100 | I73: OK | J73: LASER
E74: VERM | F74: 2953 | G74: 90X60 | H74: 2100 | I74: OK | J74: LASER
E75: LARANJA | F75: 2954 | G75: 90X60 | H75: 2100 | I75: OK | J75: LASER | L75: 665.7
A76: UP TO GO | B76: 43972 | C76: 43978 | D76: 3897 | E76: COUCHE | F76: 2791 | G76: 95X56 | H76: 200 | I76: OK | J76: LASER
E77: COUCHE | F77: 3173 | G77: 32X16 | H77: 200 | I77: OK | J77: LASER | L77: 6.18
A78: BOSS | B78: 43976 | C78: 43978 | D78: 3919 | E78: BOPP | F78: 1619 | G78: 80X40 | H78: 5000 | I78: OK | J78: LASER | L78: 211.5
A79: BOI SUL | B79: 43970 | C79: 43970 | D79: 1443 | E79: BOPP BORR | F79: 2632 | G79: 103X94 | H79: 5000 | I79: OK | J79: SEPARADO
A80: JULIANA | B80: 43971 | C80: 43971 | D80: 3924 | E80: COUCHE | F80: 838 | G80: 100X40 | H80: 19000 | I80: OK | J80: FACA | L80: 340
A81: BANCO SANGUE | B81: 43971 | C81: 43971 | D81: 3926 | E81: BOPP | F81: 1607 | G81: 50X50 | H81: 4500 | I81: OK | J81: FACA | L81: 55.9
A82: COMLINK | B82: 43977 | C82: 43978 | D82: 3927 | E82: COUCHE | F82: 908 | G82: 50X20 | H82: 10500 | I82: OK | J82: FACA
E83: BOPP | F83: 3178 | G83: 20X8 | H83: 20000 | I83: OK | J83: LASER | L83: 139.8
A84: NUBITECH | B84: 43978 | C84: 43979 | D84: 3928 | E84: COUCHE | F84: 1126 | G84: 100X100 | H84: 1600 | I84: OK | J84: LASER
E85: COUCHE | F85: 908 | G85: 50X20 | H85: 10500 | I85: OK | J85: FACA | L85: 257.2
A86: CODETECH | B86: 43973 | C86: 43971 | D86: 3933 | E86: COUCHE | F86: 1555 | G86: 50X30 | H86: 20000 | I86: OK | J86: FACA | L86: 150
A87: G3 | B87: 43979 | C87: 43979 | D87: 3931 | E87: BOPP | F87: 3139 | G87: 78X25 | H87: 5000 | I87: OK | J87: LASER | L87: 108.5
A88: NATAL | B88: 43978 | C88: 43979 | D88: 3939 | E88: COUCHE | F88: 1126 | G88: 100X100 | H88: 1000 | I88: OK | J88: LASER | L88: 46.3
A89: CALERA | B89: 43976 | C89: 43973 | D89: 3942 | E89: BOPP | F89: 2490 | G89: 64X10 | H89: 22500 | I89: OK | J89: FACA | L89: 540
A90: JOIA REAL | B90: 43977 | C90: 43973 | D90: 3946 | E90: COUCHE | F90: 753 | G90: 100X50 | H90: 6400 | I90: OK | J90: FACA | L90: 145
A91: RUBINETTOS | B91: 43980 | C91: 43976 | D91: 3945 | E91: COUCHE | F91: 2740 | G91: 90X36 | H91: 20000 | I91: OK | J91: FACA | L91: 460
A92: AMARAL | B92: 43973 | C92: 43973 | D92: 3948 | E92: COUCHE | F92: 2515 | G92: 55X28 | H92: 7500 | I92: OK | J92: FACA | L92: 115.75
A93: CODETECH | B93: 43980 | C93: 43979 | D93: 3949 | E93: COUCHE | F93: 616 | G93: 40X30 | H93: 5000 | I93: OK | J93: LASER
E94: AZUL | F94: 2819 | G94: 50X40 | H94: 10000 | I94: OK | J94: FACA
C95: 43973 | E95: COUCHE | F95: 1397 | G95: 50X30 | H95: 20000 | I95: OK | J95: FACA | L95: 297.5
A96: VLP | B96: 43980 | C96: 43979 | D96: 3953 | E96: COUCHE | F96: 744 | G96: 100X70 | H96: 3000 | I96: OK | J96: LASER | L96: 100.2
A97: JONES | B97: 43980 | C97: 43980 | D97: 3954 | E97: TERMICO | F97: 1442 | G97: 28X89 | H97: 5 | I97: OK | J97: LASER | L97: 60
A98: MATRIMETAL | B98: 43979 | C98: 43978 | D98: 3961 | E98: COUCHE | F98: 869 | G98: 33X25 | H98: 15000 | I98: OK | J98: FACA | L98: 114
A99: CASA E CIA | B99: 43979 | D99: 3963 | E99: COUCHE | F99: 2039 | G99: 40X55 | H99: 40500 | I99: OK | J99: FACA | L99: 480
A100: PANIZZON | B100: 43980 | C100: 43980 | D100: 3969 | E100: CINZA | F100: 2449 | G100: 100X68 | H100: 11700 | I100: OK | J100: FACA | L100: 478
...

Sheet OUTUBRO20
A1: CLIENTE | B1: Data Entr | C1: Data Prod | D1: O/F | E1: MATERIAL | F1: CÓDIGO | G1: ETIQUETA | H1: QUANT | I1: OK | J1: PRODUZIDO POR | K1: O/C | L1: VALOR
A2: BOFF | B2: 44088 | E2: ROTULO | F2: 3269 | G2: 80X100 | H2: 29.3 | I2: OK | J2: G10 | K2: 1500 | L2: 4834.5
E3: ROTULO | F3: 3270 | G3: 80X100 | H3: 28 | I3: OK | J3: G10 | K3: 1500 | L3: 4620
E4: ROTULO | F4: 3271 | G4: 80X100 | H4: 28.44 | I4: OK | J4: G10 | K4: 1500 | L4: 4692.6
A5: BP COMP | B5: 44112 | C5: 44120 | D5: 4896 | E5: POLIESTER | F5: 1183 | G5: 30X15 | H5: 10 | I5: OK | J5: LABEL | K5: 1512 | L5: 1300
A6: ARCO | B6: 44134 | C6: 44132 | D6: 5164 | E6: COUCHE | F6: 2604 | G6: 105X55 | H6: 21600 | I6: OK | J6: G10 | K6: 1525 | L6: 434
A7: AMF INFO | B7: 44126 | C7: 44127 | D7: 5174 | E7: BOPP | F7: 3129 | G7: 50X18 | H7: 20 | I7: OK | J7: GV | K7: 1528 | L7: 179
A8: ESTERELIZARE | B8: 44126 | C8: 44134 | D8: 5208 | E8: COUCHE | F8: 2691 | G8: 100X50 | H8: 132.8 | I8: OK | J8: GV | K8: 1535 | L8: 2100
A9: AMF INFO | B9: 44125 | C9: 44127 | D9: 5187 | E9: COUCHE | F9: 2646 | G9: 50X35 | H9: 250 | I9: OK | J9: GV | K9: 1527 | L9: 1975
F10: 1350 | G10: 50X35 | H10: 50 | I10: OK | J10: GV | K10: 1527 | L10: 395
A11: DTECH | B11: 44127 | C11: 44134 | D11: 5255 | E11: COUCHE | F11: 1467 | G11: 85X50 | H11: 5.6 | I11: OK | J11: GV | K11: 1530 | L11: 127.5
A12: AMF INFO | B12: 44134 | C12: 44134 | D12: 5227 | E12: COUCHE | F12: 1467 | G12: 85X50 | H12: 5.6 | I12: OK | J12: GV | K12: 1537 | L12: 89.5
A13: IPACOL | B13: 44134 | C13: 44134 | D13: 5304 | E13: COUCHE | F13: 950 | G13: 100X65 | H13: 17 | I13: OK | J13: GV | K13: 1538 | L13: 765
A17: AMF | B17: 44089 | C17: 44109 | D17: 4706 | E17: COUCHE | F17: 3174 | G17: 35X26.5 | H17: 120 | I17: OK | J17: G10 | K17: 1492 | L17: 618
E18: REMOV | F18: 3175 | G18: 35X26.5 | H18: 128 | I18: OK | J18: G10 | K18: 1492 | L18: 774
A19: ECOMETAIS | B19: 44102 | C19: 44111 | D19: 4835 | E19: COUCHE | F19: 1007 | G19: 100X38 | H19: 31.5 | I19: OK | J19: G10 | K19: 1503 | L19: 534
A20: TR CARTUCHOS | B20: 44102 | C20: 44111 | D20: 4832 | E20: COUCHE | F20: 754 | G20: 100x30 | H20: 31.25 | I20: OK | J20: G10 | K20: 1504
A21: TECNOLOGICA | B21: 44110 | C21: 44118 | D21: 4849 | E21: TC | F21: 3276 | G21: 45X140 | H21: 5.11 | I21: OK | J21: G10 | K21: 1506 | L21: 1310
E22: TC | F22: 3277 | G22: 35X115 | H22: 5.41 | I22: OK | J22: G10 | K22: 1506 | L22: 1210
A23: WINELANDS | B23: 44112 | C23: 44110 | D23: 1505 | E23: COUCHE | F23: 2162 | G23: 28X28 | H23: 39 | I23: OK | J23: G10 | K23: 1505 | L23: 810
A24: MA ACESS | B24: 44104 | C24: 44112 | D24: 4964 | E24: COUCHE | F24: 2561 | G24: 77X32 | H24: 199.3 | I24: OK | J24: GV | K24: 1511 | L24: 2000
A25: AMF | B25: 44105 | C25: 44105 | D25: 4802 | E25: COUCHE | F25: 1869 | G25: 33X21 | H25: 80 | I25: OK | J25: FACA | L25: 264
A26: BARAO | B26: 44106 | C26: 44106 | D26: 4981 | E26: COUCHE | F26: 2415 | G26: 33X39 | H26: 10 | I26: OK | J26: LASER | L26: 62
A27: URSULA | B27: 44105 | C27: 44105 | D27: 4926 | E27: BOPP | F27: 3219 | G27: 109X25 | H27: 6 | I27: OK | J27: LASER | L27: 140
A28: PLASMOSUL | B28: 44107 | C28: 44106 | D28: 4993 | E28: REMOV | F28: 3016 | G28: 50X30 | H28: 15 | I28: OK | J28: FACA | L28: 171.6
E29: COUCHE | F29: 843 | G29: 34X23 | H29: 4 | I29: OK | J29: FACA | L29: 20.96
E30: COUCHE | F30: 1186 | G30: 100X66 | H30: 5 | I30: OK | J30: LASER | L30: 181.8
A31: GAMACOR | B31: 44106 | C31: 44109 | D31: 4996 | E31: COUCHE | F31: 1862 | G31: 100X35 | H31: 10 | I31: OK | J31: LASER | L31: 239
A32: DELTA FIRE | B32: 44109 | C32: 44109 | D32: 5002 | E32: BOPP | F32: 1853 | G32: 100X35 | H32: 2 | I32: OK | J32: LASER
E33: BOPP | F33: 2771 | G33: 35X21 | H33: 50 | I33: OK | J33: LASER
E34: BOPP | F34: 2775 | G34: 70X40 | H34: 1 | I34: OK | J34: LASER | L34: 412.55
A35: DUKE | B35: 44110 | C35: 44111 | D35: 5003 | E35: COUCHE | F35: 2800 | G35: 45X45 | H35: 4 | I35: OK | J35: LASER | K35: PERS 08/10 | L35: 208
A36: CARLIN | B36: 44111 | C36: 44110 | D36: 5029 | E36: COUCHE | F36: 2837 | G36: 45X60 | H36: 3.8 | I36: OK | J36: LASER | L36: 104.65
A37: CODETECH | B37: 44112 | C37: 44120 | D37: 5036 | E37: B.BORR | F37: 2719 | G37: 80X80 | H37: 14 | I37: OK | J37: GV | K37: 1513
E38: B.BORR | F38: 2842 | G38: 100X90 | H38: 5 | I38: OK | J38: LASER | L38: 1250
A39: CODETECH | B39: 44113 | C39: 44110 | D39: 5037 | E39: BOPP | F39: 3006 | G39: 60X40 | H39: 6 | I39: OK | J39: LASER | L39: 115
A40: VILLAGGIO | B40: 44113 | C40: 44112 | D40: 5049 | E40: COUCHE | F40: 3309 | G40: 50X70 | H40: 5 | I40: OK | J40: FACA | K40: PERS 09/10 | L40: 170
A41: WINELANDS | B41: 44112 | C41: 44117 | D41: 5022 | E41: COUCHE | F41: 2149 | G41: 70X40 | H41: 32.5 | I41: ok | J41: GV | K41: 1514 | L41: 750
A42: AMF INFO | B42: 44113 | C42: 44112 | D42: 5048 | E42: COUCHE | F42: 3038 | G42: 24X20 | H42: 25 | I42: ok | J42: LASER | L42: 76.25
A43: G3 | B43: 44106 | C43: 44105 | D43: 5066 | E43: COUCHE | F43: 1397 | G43: 50X30 | H43: 35 | I43: OK | J43: FACA | L43: 280
A44: MUNDOQUAN | B44: 44111 | C44: 44124 | D44: 5054 | E44: COUCHE | F44: 951 | G44: 100X150 | H44: 10 | I44: OK | J44: FACA | L44: 890.12
A45: ZANLINE | B45: 44113 | C45: 44127 | D45: 5071 | E45: COUCHE | F45: 951 | G45: 100X150 | H45: 20 | I45: OK | J45: FACA | K45: FACA | L45: 670
A46: SUPERFLEXO | B46: 44110 | C46: 44111 | D46: 1522 | E46: COUCHE | F46: 951 | G46: 100X150 | H46: 6.18 | I46: OK | J46: SF | K46: 1522
A47: NEOGAS | B47: 44113 | C47: 44111 | D47: 5055 | E47: COUCHE | F47: 838 | G47: 100X40 | H47: 3 | I47: OK | J47: FACA | L47: 72
E48: COUCHE | F48: 3294 | G48: 65X25 | H48: 3 | I48: OK | J48: LASER | L48: 36.3
A49: DOMAMA | B49: 44112 | D49: 5067 | E49: COUCHE | F49: 2515 | G49: 55X28 | H49: 15 | I49: OK | J49: FACA | L49: 217.5
B50: 44112 | D50: 5067 | E50: COUCHE | F50: 1924 | G50: 100X40 | H50: 3 | I50: OK | J50: FACA | L50: 72
A51: COMLINK | B51: 44117 | C51: 44117 | D51: 5072 | E51: C.BORR | F51: 788 | G51: 100X80 | H51: 10 | I51: OK | J51: FACA/LASER | L51: 747
B52: 44112 | C52: 44113 | D52: 5072 | E52: COUCHE | F52: 908 | G52: 50X20 | H52: 10.5 | I52: OK | J52: FACA | L52: 100
A53: FIXPAR | B53: 44112 | C53: 44109 | D53: 5078 | E53: C.VERM | F53: 2903 | G53: 50X70 | H53: 3 | I53: OK | J53: FACA | L53: 65.4
B54: 44112 | D54: 5078 | E54: C. AZUL | F54: 3171 | G54: 50X70 | H54: 3 | I54: OK | J54: FACA | L54: 65.4
A55: PANIZZON | B55: 44112 | C55: 44112 | D55: 5079 | E55: COUCHE | F55: 1545 | G55: 100X68 | H55: 15 | I55: OK | J55: FACA | L55: 426
B56: 44112 | D56: 5079 | E56: C. ROSA | F56: 2818 | G56: 100X68 | H56: 10 | I56: OK | J56: FACA | L56: 350
B57: 44112 | D57: 5079 | E57: C. CINZA | F57: 2449 | G57: 100X68 | H57: 10 | I57: OK | J57: FACA | L57: 492
A58: ESTILO RADICAL | B58: 44113 | C58: 44106 | D58: 5082 | E58: COUCHE | F58: 855 | G58: 50X40 | H58: 40 | I58: OK | J58: FACA | L58: 508.4
A59: NUBITECH | B59: 44117 | C59: 44112 | D59: 5062 | E59: COUCHE | F59: 1126 | G59: 100X100 | H59: .8 | I59: OK | J59: FACA | L59: 65.6
E60: COUCHE | F60: 908 | G60: 50X20 | H60: 7 | I60: OK | J60: FACA | L60: 84
E61: COUCHE | F61: 3295 | G61: 50X25 | H61: 2.5 | I61: OK | J61: LASER | L61: 37.2
A62: TOLEDO´S | B62: 44117 | C62: 44111 | D62: 5077 | E62: COUCHE | F62: 744 | G62: 100X70 | H62: 2.5 | I62: OK | J62: LASER | L62: 157.5
A63: TOLEDO´S | B63: 44117 | C63: 44109 | D63: 5098 | E63: C.BORR | F63: 2590 | G63: 100X40 | H63: 0.25 | I63: OK | J63: FACA | L63: 7
A64: ESB | B64: 44118 | C64: 44118 | D64: 5080 | E64: B.BORR | F64: 2329 | G64: 105X105 | H64: 4 | I64: OK | J64: LASER | L64: 474.8
A65: DUKE | B65: 44118 | C65: 44130 | D65: 5073 | E65: COUCHE | F65: 2891 | G65: 60X60 | H65: 2 | I65: OK | J65: LASER | L65: 130
E66: COUCHE | F66: 2800 | G66: 45X45 | H66: 2 | I66: OK | J66: LASER | L66: 104
A67: SULPACK | B67: 44119 | C67: 44112 | D67: 5084 | E67: BOPP | F67: 1401 | G67: 50X22 | H67: 3 | I67: OK | J67: LASER | L67: 105
E68: BOPP | F68: 1155 | G68: 12X20 | H68: 2 | I68: OK | J68: LASER | L68: 65
E69: COUCHE | F69: 838 | G69: 100X40 | H69: 2 | I69: OK | J69: FACA | L69: 48
E70: AMARELA | F70: 3300 | G70: 100X30 | H70: 2 | I70: OK | J70: LASER | L70: 104
A71: BIOLUZ | B71: 44119 | C71: 44119 | D71: 5086 | E71: COUCHE | F71: 3301 | G71: 30X5 | H71: 6 | I71: OK | J71: LASER | L71: 69.9
A72: ESTILO RADICAL | B72: 44113 | C72: 44106 | D72: 5088 | E72: COUCHE | F72: 855 | G72: 50X40 | H72: 40 | I72: OK | J72: FACA | L72: 440
A73: WELOZE | B73: 44117 | C73: 44110 | D73: 5091 | E73: COUCHE | F73: 2396 | G73: 25X15 | H73: 10 | I73: OK | J73: FACA
E74: COUCHE | F74: 1545 | G74: 100X68 | H74: 20 | I74: OK | J74: FACA | L74: 634.8
A75: AMF | B75: 44119 | C75: 44120 | D75: 5092 | E75: COUCHE | F75: 1139 | G75: 108X87 | H75: 5 | I75: OK | J75: LASER | L75: 362.5
B76: 44113 | C76: 44113 | D76: 5092 | E76: COUCHE | F76: 2759 | G76: 30X38 | H76: 21 | I76: OK | J76: FACA | L76: 108.15
A77: SHEILA | B77: 44119 | C77: 44120 | E77: PROMOM | G77: 100X75 | H77: 200 | I77: OK | J77: LASER
A78: TIRABITIA | B78: 44120 | C78: 44112 | D78: 5094 | E78: TAG | F78: 2477 | G78: 52,5X60 | H78: 6 | I78: OK | J78: LASER | L78: 132
E79: BOPP | F79: 2412 | G79: 50X40 | H79: 4 | I79: OK | J79: FACA | L79: 68
A80: MODAZINE | B80: 44119 | C80: 44121 | D80: 5097 | E80: COUCHE | F80: 3302 | G80: 33X21 | H80: 75 | I80: OK | J80: FACA | L80: 305.25
E81: VERM | F81: 2017 | G81: 33X21 | H81: 200 | I81: OK | J81: FACA | L81: 800
E82: COUCHE | F82: 3303 | G82: 90X25 | H82: 37.5 | I82: OK | J82: FACA | L82: 443.25
A83: JULIAS CLOSET | B83: 44120 | C83: 44123 | D83: 5095 | E83: COUCHE | F83: 1104 | G83: 20X38 | H83: 16 | I83: OK | J83: LASER | L83: 352
E84: NYLON | F84: 2600 | G84: 29X76 | H84: 4 | I84: OK | J84: FACA | L84: 104
A85: SPIGOLON | B85: 44118 | D85: 5102 | E85: AMARELO | F85: 3101 | G85: 100X75 | H85: 2 | I85: OK | J85: FACA
E86: COUCHE | F86: 869 | G86: 33X25 | H86: 15 | I86: OK | J86: FACA
F87: 3102 | G87: 33X25 | H87: 15 | I87: OK | J87: FACA
B88: 44124 | F88: 3305 | G88: 95X40 | H88: 3 | I88: OK | J88: LASER | L88: 609
A89: SIMONE FRANCO | B89: 44119 | C89: 44118 | D89: 5084 | E89: COUCHE | F89: 869 | G89: 33X25 | H89: 10 | I89: OK | J89: FACA
E90: NYLON | F90: 2600 | G90: 29X76 | H90: 8 | I90: OK | J90: FACA | L90: 305
A91: AMF | B91: 44110 | C91: 44110 | D91: 5116 | E91: COUCHE | F91: 2762 | G91: 25X16 | H91: 50 | I91: OK | J91: FACA
E92: BOPP | F92: 2724 | G92: 25X16 | H92: 50 | I92: OK | J92: FACA | L92: 357.5
A93: AMF | B93: 44124 | C93: 44119 | D93: 5116 | E93: COUCHE | F93: 2762 | G93: 25X16 | H93: 70 | I93: OK | J93: FACA | L93: 199.5
A94: AMF | B94: 44110 | C94: 44110 | D94: 4982 | E94: BOPP | F94: 2724 | G94: 25X16 | H94: 50 | I94: OK | J94: FACA | L94: 215
A95: JLAGO | B95: 44111 | C95: 44111 | E95: AMA | F95: 2105 | G95: 50X40 | H95: 2.5 | I95: OK | J95: FACA
E96: ROSA | F96: 3307 | G96: 50X40 | H96: 2.5 | I96: OK | J96: FACA
E97: AZUL | F97: 2106 | G97: 50X40 | H97: 2.5 | I97: OK | J97: FACA
E98: BOPP | F98: 3308 | G98: 50X40 | H98: 12400 | I98: OK | J98: FACA
A99: JONES | C99: 44131 | E99: TERMICO | F99: 2115 | G99: 39X40 | H99: 600 | I99: OK | J99: FACA
A100: LAIMED | B100: 44118 | C100: 44111 | D100: 5113 | E100: COUCHE | F100: 1098 | G100: 90X80 | H100: 4 | I100: OK | J100: FACA | L100: 148.48
A101: AMF INFO | B101: 44120 | C101: 44111 | D101: 5118 | E101: BOPP | F101: 1405 | G101: 15X10 | H101: 60 | I101: OK | J101: LASER | L101: 192
A102: AMF INFO | B102: 44123 | C102: 44125 | D102: 5122 | E102: TAG | F102: 2781 | G102: 55X75 | H102: 4 | I102: OK | J102: LASER | L102: 80
A103: AMF INFO | B103: 44123 | C103: 44125 | D103: 5125 | E103: PROMOM | F103: 3304 | G103: 100X75 | H103: 7 | I103: OK | J103: LASER | K103: PERSO | L103: 385
...

Sheet NOVEMBRO20
A1: CLIENTE | B1: Data Entr | C1: Data Prod | D1: O/F | E1: MATERIAL | F1: CÓDIGO | G1: ETIQUETA | H1: QUANT | I1: OK | J1: PRODUZIDO POR | K1: O/C | L1: VALOR
A2: BRASILEIRINHO | B2: 44134 | C2: 44160 | D2: 5139 | E2: COUCHE | F2: 2805 | G2: 100X50 | H2: 5.7 | I2: OK | J2: G10 | K2: 1524 | L2: 160
A3: ECOMETAIS | B3: 44134 | C3: 44160 | D3: 5181 | E3: COUCHE | F3: 1007 | G3: 100X38 | H3: 30 | I3: OK | J3: G10 | K3: 1526 | L3: 534
A4: AMF INFO | B4: 44165 | C4: 44160 | D4: 5419 | E4: COUCHE | F4: 3264 | G4: 33X22 | H4: 38.65 | I4: OK | J4: G10 | K4: 1549 | L4: 232.5
A5: AMF | B5: 44119 | C5: 44161 | D5: 5092 | E5: COUCHE | F5: 1139 | G5: 108X87 | H5: 20740 | I5: OK | J5: G10 | K5: 1532 | L5: 362.5
A8: MAQENGE | B8: 44131 | C8: 44138 | D8: 5266 | E8: COUCHE | F8: 2720 | G8: 47X22 | H8: 51 | I8: OK | J8: GV | K8: 1531 | L8: 174.9
E9: COUCHE | F9: 1467 | G9: 85X50 | H9: 26.4 | I9: OK | J9: GV | K9: 1530 | L9: 540
A10: AUTO TRAVI | B10: 44125 | C10: 44138 | D10: 5289 | E10: COUCHE | F10: 2740 | G10: 90X32 | H10: 20 | I10: OK | J10: GV | K10: 1534 | L10: 325.6
A11: ALO MAMAE | B11: 44134 | C11: 44138 | D11: 5292 | E11: COUCHE | F11: 3315 | G11: 30X50 | H11: 10 | I11: OK | J11: GV | K11: 1533 | L11: 140
A12: G3 | B12: 44134 | C12: 44138 | D12: 5268 | E12: COUCHE | F12: 3295 | G12: 50X25 | H12: 22.5 | I12: OK | J12: GV | K12: 1536 | L12: 222.75
A13: HOSP. SC | B13: 44146 | C13: 44145 | D13: 5409 | E13: BOPP | F13: 1491 | G13: 100X23 | H13: 10 | I13: OK | J13: GV | K13: 1546 | L13: 213.3
A14: INJET | B14: 44134 | C14: 44165 | D14: 5325 | E14: B.BORR | F14: 2494 | G14: 25X25 | H14: 10 | I14: OK | J14: GV | K14: 1540 | L14: 550
A15: PECCIN | B15: 44134 | C15: 44144 | D15: 4941 | E15: TAG | F15: 2328 | G15: 50X10 | H15: 50 | I15: OK | J15: GV | K15: 1541 | L15: 2400
A16: DOLCE VITA | B16: 44130 | C16: 44144 | D16: 5252 | E16: COUCHE | F16: 3078 | G16: 75X27 | H16: 30 | I16: OK | J16: GV | K16: 1529 | L16: 465
A17: AMF | B17: 44152 | C17: 44152 | D17: 5370 | E17: COUCHE | F17: 784 | G17: 30X15 | H17: 200 | I17: OK | J17: GV | K17: 1547 | L17: 760
A18: FRAMA | B18: 44153 | C18: 44158 | D18: 5446 | E18: C.BORR | F18: 2584 | G18: 50X50 | H18: 100 | I18: OK | J18: GV | K18: 1550 | L18: 1200
A19: AMF INFO | B19: 44154 | C19: 44152 | D19: 5372 | E19: BOPP | F19: 1405 | G19: 15X10 | H19: 60 | I19: OK | J19: GV | K19: 1551 | L19: 204
A20: VESA | B20: 44166 | C20: 44152 | D20: 5462 | E20: C.BORR | F20: 1481 | G20: 105X105 | H20: 18.5 | I20: OK | J20: GV | K20: 1552 | L20: 870
A21: PLASMOSUL | B21: 44153 | C21: 44160 | D21: 5447 | E21: BOPP | F21: 3335 | G21: 100X90 | H21: 5 | I21: OK | J21: GV | K21: 1555 | L21: 181.54
A22: DIFLORES | B22: 44154 | C22: 44152 | D22: 5460 | E22: TAG | F22: 2993 | G22: 35X64 | H22: 21 | I22: OK | J22: GV | K22: 1556 | L22: 270
A23: SUSIN | B23: 44152 | C23: 44152 | D23: 5465 | E23: COUCHE | F23: 343 | G23: 50X22 | H23: 17.5 | I23: OK | J23: GV | K23: 1557 | L23: 175
A24: HOSP. SC | B24: 44159 | C24: 44153 | D24: 5490 | E24: BOPP | F24: 1491 | G24: 100X23 | H24: 20 | I24: OK | J24: GV | K24: 1562 | L24: 426.6
A25: TRACIATTI | B25: 44153 | C25: 44153 | D25: 5485 | E25: COUCHE | F25: 1292 | G25: 40X25 | H25: 30 | I25: OK | J25: GV | K25: 1559 | L25: 525
A26: SULPACK | B26: 44159 | C26: 44154 | D26: 5494 | E26: BOPP | F26: 1401 | G26: 50X22 | H26: 9 | I26: OK | J26: GV | K26: 1563 | L26: 315
E27: BOPP | F27: 1155 | G27: 12X20 | H27: 12 | I27: OK | J27: GV | K27: 1563 | L27: 162.5
A28: RANDON | B28: 44161 | C28: 44155 | D28: 5167 | E28: TERMICO | F28: 2606 | G28: 25X75 | H28: 6.4 | I28: OK | J28: GV | K28: 1564 | L28: 178.2
A29: IMEXPORT | B29: 44159 | C29: 44158 | D29: 5498 | E29: COUCHE | F29: 2854 | G29: 104X125 | H29: 10.2 | I29: OK | J29: GV | K29: 1565 | L29: 690
A30: AMF INFO | B30: 44154 | C30: 44159 | D30: 5372 | E30: BOPP | F30: 1405 | G30: 15X10 | H30: 40 | I30: OK | J30: GV | K30: 1551 | L30: 204
A31: PARAPASSO | B31: 44165 | C31: 44158 | D31: 5541 | E31: COUCHE | F31: 2029 | G31: 35X30 | H31: 12 | I31: OK | J31: GV | K31: 1566 | L31: 180
A32: FERPLAST | B32: 44165 | C32: 44160 | D32: 5499 | E32: COUCHE | F32: 1215 | G32: 40X34 | H32: 40 | I32: OK | J32: GV | K32: 1567 | L32: 420
A33: ZBM | B33: 44167 | C33: 44160 | D33: 5538 | E33: COUCHE | F33: 2811 | G33: 44X60 | H33: 15 | I33: OK | J33: GV | K33: 1569 | L33: 255
A34: PILOTAGGIO | B34: 44166 | D34: 5574 | E34: COUCHE | F34: 3347 | G34: 35X64 | H34: 6 | I34: OK | J34: GV | K34: 1570
E35: AMARELA | F35: 1514 | G35: 35X64 | H35: 6 | I35: OK | J35: GV | K35: 1570 | L35: 78
A36: DOLCEMONTE | B36: 44169 | C36: 44162 | D36: 5405 | E36: COUCHE | F36: 992 | G36: 30X30 | H36: 20 | I36: OK | J36: GV | K36: 1571 | L36: 190
A37: CASA DO IMIGR | B37: 44169 | C37: 44162 | D37: 5555 | E37: TAG | F37: 3350 | G37: 90X35 | H37: 10 | I37: OK | J37: GV | K37: 1574 | L37: 270
A41: AMF INFO | B41: 44134 | C41: 44141 | D41: 5344 | E41: VERM | F41: 3329 | G41: 25X16 | H41: 1 | I41: OK | J41: FACA | L41: 8
A42: RACHELES | B42: 44132 | D42: 5283 | E42: COUCHE | F42: 2645 | G42: 34X60 | H42: 10 | J42: LASER | L42: 105
A43: RANDON | B43: 44125 | D43: 5167 | E43: TERMICO | F43: 2606 | G43: 25X75 | H43: 4 | J43: LASER | L43: 118
A44: INJET | B44: 44140 | C44: 44139 | D44: 5325 | E44: B.BORR | F44: 2494 | G44: 25x25 | H44: 10 | J44: PERSO | L44: 550
A45: TRENDS | B45: 44140 | C45: 44139 | D45: 5349 | E45: COUCHE | F45: 838 | G45: 100X40 | H45: 10 | I45: OK | J45: FACA
E46: COUCHE | F46: 1397 | G46: 50X30 | H46: 30 | I46: OK | J46: FACA
E47: COUCHE | F47: 908 | G47: 50X20 | H47: 10.5 | I47: OK | J47: FACA
C48: 44139 | E48: COUCHE | F48: 879 | G48: 100X60 | H48: 10.5 | I48: OK | J48: FACA | L48: 0
A49: BENTO AGROPET | B49: 44140 | D49: 5336 | E49: TAG AM | F49: 2433 | G49: 95X35 | H49: 5 | J49: LASER | L49: 66.45
A50: AMF INFO | B50: 44147 | D50: 5373 | E50: TAG | F50: 3074 | G50: 32X70 | H50: 5 | J50: LASER | L50: 50
A51: SOGIMA | B51: 44120 | D51: 5096 | E51: COUCHE | F51: 2149 | G51: 70X40 | H51: 15 | J51: LASER | K51: ???? | L51: 142.6
A52: DI ZANETTE | B52: 44145 | C52: 44144 | D52: 5380 | E52: COUCHE | F52: 2039 | G52: 40X55 | H52: 51 | I52: OK | J52: FACA | L52: 800
A53: DOLCEMONT | B53: 44152 | D53: 5405 | E53: COUCHE | F53: 992 | G53: 30X30 | H53: 20 | J53: LASER
E54: COUCHE | F54: 3210 | G54: 66X25 | H54: 30 | I54: OK | J54: LASER | L54: 465
B55: 44152 | C55: 44144 | D55: 5405 | E55: COUCHE | F55: 2039 | G55: 40X55 | H55: 15 | I55: OK | J55: FACA | L55: 535
A56: MODAZINE | B56: 44146 | C56: 44152 | D56: 5410 | E56: COUCHE | F56: 3303 | G56: 90X25 | H56: 45 | I56: OK | J56: FACA | L56: 531.9
A57: INJET | B57: 44152 | D57: 5411 | E57: COUCHE | F57: 97 | G57: 80X90 | H57: 1.5 | J57: LASER | L57: 86.1
A58: NEUSA | B58: 44146 | C58: 44140 | D58: 5416 | E58: BOPP | F58: 2172 | G58: 33X25 | H58: 20 | I58: OK | J58: FACA | L58: 260
A59: ACOMOLD | B59: 44146 | C59: 44139 | D59: 5402 | E59: COUCHE | F59: 2515 | G59: 55X28 | H59: 10 | I59: OK | J59: FACA | L59: 125
D60: 5402 | E60: COUCHE | F60: 838 | G60: 100X40 | H60: 10 | I60: OK | J60: FACA | L60: 240
A61: AMF INFO | B61: 44146 | D61: 5418 | E61: COUCHE | F61: 1139 | G61: 108X87 | H61: 15 | J61: G10 | K61: 1532 | L61: 543.75
C62: 44140 | D62: 5418 | E62: COUCHE | F62: 2759 | G62: 30X38 | H62: 21 | I62: OK | J62: FACA | L62: 114.45
A63: MONIQUEL | B63: 44140 | C63: 44139 | D63: 5426 | E63: COUCHE | F63: 869 | G63: 33X25 | H63: 10 | I63: OK | J63: FACA | L63: 80
A64: UP TO GO | B64: 44140 | C64: 44139 | D64: 5433 | E64: COUCHE | F64: 2664 | G64: 15X30 | H64: 10 | I64: OK | J64: FACA | L64: 43
A65: BANCO SANGUE | B65: 44148 | C65: 44139 | D65: 5439 | E65: BOPP | F65: 2467 | G65: 100X80 | H65: 3 | I65: OK | J65: FACA | L65: 274.83
F66: 2357 | G66: 55X28 | H66: 5 | I66: OK | J66: FACA | L66: 80
A67: HUGO PIETRO | B67: 44153 | C67: 44145 | D67: 5441 | E67: COUCHE | F67: 2264 | G67: 80X60 | H67: 60 | I67: OK | J67: FACA | L67: 1050
A68: MASTER EGGS | B68: 44148 | C68: 44140 | D68: 5443 | E68: COUCHE | F68: 1397 | G68: 50X30 | H68: 50 | I68: OK | J68: FACA | L68: 470
A69: BIOLUZ | B69: 44148 | C69: 44140 | D69: 5445 | E69: COUCHE | F69: 838 | G69: 100X40 | H69: 10 | I69: OK | J69: FACA
E70: BOPP | F70: 3131 | G70: 35X40 | H70: 30 | I70: OK | J70: FACA | L70: 733.6
A71: TIFFANY | B71: 44151 | C71: 44141 | D71: 5452 | E71: COUCHE | F71: 855 | G71: 50X40 | H71: 20 | I71: OK | J71: FACA | L71: 210
A72: CLINICA FEMINA | B72: 44151 | C72: 44141 | D72: 5454 | E72: COUCHE | F72: 2266 | G72: 90X25 | H72: 15 | I72: OK | J72: FACA | L72: 193.5
A73: COMLINK | B73: 44141 | C73: 44141 | D73: 5455 | E73: BOPP | F73: 3334 | G73: 20X10 | H73: 30 | I73: OK | J73: FACA | L73: 135
A74: SECTA | B74: 44151 | C74: 44141 | D74: 5459 | E74: BOPP | F74: 1599 | G74: 90X25 | H74: 4.5 | I74: OK | J74: FACA | L74: 128.25
A75: CRIPPA | B75: 44152 | C75: 44148 | D75: 5464 | E75: COUCHE | F75: 1098 | G75: 90X80 | H75: 40 | I75: OK | J75: FACA | L75: 1200
A76: TOP LIMP | B76: 44152 | C76: 44145 | D76: 5463 | E76: AMARELO | F76: 2765 | G76: 55X28 | H76: 7.5 | I76: OK | J76: FACA | L76: 101.25
E77: COUCHE | F77: 2515 | G77: 55X28 | H77: 15 | I77: OK | J77: FACA | L77: 187.5
A78: UNIMED | B78: 44153 | C78: 44147 | D78: 5467 | E78: COUCHE | F78: 2740 | G78: 90X36 | H78: 14 | I78: OK | J78: FACA | L78: 207.2
A79: AMF INFO | B79: 44153 | C79: 44145 | D79: 5296 | E79: COUCHE | F79: 1786 | G79: 90X25 | H79: 6 | I79: OK | J79: FACA | L79: 61.5
A80: PEDRO SANZ | B80: 44152 | C80: 44145 | D80: 5471 | E80: BOPP | F80: 2050 | G80: 100X75 | H80: 6 | I80: OK | J80: FACA | L80: 204
A81: DUKE | B81: 44146 | C81: 44145 | D81: 5481 | E81: COUCHE | F81: 2891 | G81: 60X60 | H81: 4.55 | I81: OK | J81: PERSO | L81: 260
A82: ALTAIR/FARMB | B82: 44148 | C82: 44152 | D82: 5476 | E82: TC | F82: 3282 | G82: 45X85 | H82: 1 | I82: OK | J82: PERSO | L82: 270
A83: GAILLE | B83: 44153 | C83: 44146 | D83: 5486 | E83: NYLON | F83: 2600 | G83: 29X76 | H83: 20 | I83: OK | J83: FACA | L83: 560
E84: COUCHE | F84: 951 | G84: 100X150 | H84: 11.5 | I84: OK | J84: FACA | L84: 840
A85: COESTER | B85: 44154 | C85: 44147 | D85: 5492 | E85: BOPP | F85: 1483 | G85: 100X40 | H85: 10 | I85: OK | J85: FACA | L85: 460
A86: HUGO DEBASTIANI | B86: 44154 | C86: 44147 | D86: 5497 | E86: COUCHE | F86: 908 | G86: 50X20 | H86: 3.5 | I86: OK | J86: FACA | L86: 42
E87: COUCHE | F87: 1397 | G87: 50X30 | H87: 10 | I87: OK | J87: FACA | L87: 200
A88: AFETTO | B88: 44155 | C88: 44152 | D88: 5516 | E88: REMOV | F88: 2983 | G88: 100X60 | H88: 40.6 | I88: OK | J88: FACA | L88: 1468
A89: LAMINA | B89: 44155 | C89: 44152 | D89: 5519 | E89: COUCHE | F89: 2761 | G89: 100X80 | H89: 40 | I89: OK | J89: FACA | L89: 1640
A90: SULPACK | B90: 44159 | C90: 44147 | D90: 5494 | E90: COUCHE | F90: 838 | G90: 100X40 | H90: 1 | I90: OK | J90: FACA | L90: 24
A91: DI FARR | B91: 44158 | C91: 44158 | D91: 1397 | E91: COUCHE | F91: 1397 | G91: 50X30 | H91: 50 | I91: OK | J91: FACA | L91: 600
A92: RR VISION | B92: 44151 | C92: 44152 | D92: 5535 | E92: COUCHE | F92: 1397 | G92: 50X30 | H92: 5 | I92: OK | J92: FACA | L92: 110
E93: COUCHE | F93: 879 | G93: 100X60 | H93: 1.4 | I93: OK | J93: FACA | L93: 38
A94: MARC. BELA VISTA | B94: 44159 | C94: 44152 | D94: 5542 | E94: REMOV | F94: 2358 | G94: 100X60 | H94: 10.5 | I94: OK | J94: FACA | L94: 580
A95: TER BRASIL | B95: 44159 | C95: 44153 | D95: 5540 | E95: COUCHE | F95: 1126 | G95: 100X100 | H95: 10 | I95: OK | J95: FACA | L95: 720
A96: HOSP.CIRCULO | B96: 44160 | C96: 44154 | D96: 5544 | E96: COUCHE | F96: 838 | G96: 100X40 | H96: 10 | I96: OK | J96: FACA | L96: 280
A97: PETRYMAR | B97: 44160 | C97: 44155 | D97: 5547 | E97: COUCHE | F97: 753 | G97: 100X50 | H97: 20 | I97: OK | J97: FACA | L97: 520
A98: TR CARTUCHOS | B98: 44153 | C98: 44153 | D98: 5549 | E98: COUCHE | F98: 1397 | G98: 50X30 | H98: 22.5 | I98: OK | J98: FACA | L98: 189
A99: PROVOQ | B99: 44161 | C99: 44153 | D99: 5553 | E99: COUCHE | F99: 1960 | G99: 35X40 | H99: 12 | I99: OK | J99: FACA | L99: 166.8
A100: BONNA VITA | B100: 44153 | C100: 44153 | D100: 5554 | E100: COUCHE | F100: 1397 | G100: 50X30 | H100: 2.5 | I100: OK | J100: FACA | L100: 24.25
A101: CLIZA | B101: 44155 | C101: 44155 | D101: 5557 | E101: COUCHE | F101: 951 | G101: 100X150 | H101: 20 | I101: OK | J101: FACA | L101: 1340
A102: BRASSUD | B102: 44161 | C102: 44158 | D102: 5561 | E102: COUCHE | F102: 1960 | G102: 35X40 | H102: 21 | I102: OK | J102: FACA | L102: 406
A103: FIBRASIL | B103: 44153 | C103: 44153 | D103: 5572 | E103: COUCHE | F103: 2740 | G103: 90X36 | H103: 5 | I103: OK | J103: FACA | L103: 95
A104: AMF INFO | B104: 44162 | C104: 44154 | D104: 5577 | E104: COUCHE | F104: 879 | G104: 100X60 | H104: 9.1 | I104: OK | J104: FACA | L104: 191.1
A105: MODAZINE | B105: 44154 | C105: 44154 | D105: 5582 | E105: COUCHE | F105: 3303 | G105: 90X25 | H105: 45 | I105: OK | J105: FACA | L105: 540
...

Sheet DEZEMBRO20 
A1: CLIENTE | B1: Data Entr | C1: Data Prod | D1: O/F | E1: MATERIAL | F1: CÓDIGO | G1: ETIQUETA | H1: QUANT | I1: OK | J1: PRODUZIDO POR | K1: O/C | L1: VALOR
A2: LABEL
A3: BP COMPON | B3: 44180 | C3: 44179 | D3: 5650 | E3: POLIESTER | F3: 1183 | G3: 30X15 | H3: 10 | I3: OK | J3: LABEL | L3: 1300
A4: BP COMPON | B4: 44180 | C4: 44179 | D4: 5651 | E4: POLIESTER | F4: 1183 | G4: 30X15 | H4: 20 | I4: OK | J4: LABEL | L4: 1300
A6: G10
A7: MODAZINE | B7: 44183 | C7: 44173 | D7: 5682 | E7: COUCHE | F7: 3364 | G7: 105X161 | H7: 7.5 | I7: OK | J7: G10 | K7: 1587 | L7: 671.1
A8: MODAZINE | B8: 44183 | C8: 44173 | D8: 5642 | E8: TAG | F8: 3361 | G8: 35X62 | H8: 93.8 | I8: OK | J8: G10 | K8: 1588 | L8: 921.6
A9: ALTAIR/FARMB | B9: 44165 | C9: 44174 | D9: 5397 | E9: COUCHE | F9: 2749 | G9: 45X85 | H9: 10 | I9: OK | J9: G10 | K9: 1597 | L9: 1100 | M9: 2000
A10: ATP | B10: 44165 | D10: 5202 | E10: TC | F10: 2189 | G10: 100X35 | H10: 31 | I10: OK | J10: G10 | K10: 1605 | L10: 3900 | M10: recebido sheila
A11: LIVE | B11: 44155 | C11: 44184 | D11: 5886 | E11: TC | F11: 3269 | G11: 80X100 | H11: 20 | I11: OK | J11: G10 | K11: ANTIGO | M11: recebido sheila
F12: 3270 | G12: 80X100 | H12: 20.6 | I12: OK | J12: G10 | K12: ANTIGO | M12: recebido sheila
F13: 3271 | G13: 80X100 | H13: 20.6 | I13: OK | J13: G10 | K13: 1554 | L13: 14850 | M13: recebido sheila
A14: MODAZINE | B14: 44183 | C14: 44174 | D14: 3361 | E14: TAG | F14: 3361 | G14: 35X62 | H14: 93.8 | I14: OK | J14: G10 | L14: 812
A15: AMF INFO | B15: 44165 | C15: 44174 | D15: 5645 | E15: COUCHE | F15: 3264 | G15: 33x22 | H15: 35 | I15: OK | J15: G10 | K15: 1578 | L15: 232.5
A16: MODAZINE | B16: 43845 | C16: 44183 | D16: 5758 | E16: COUCHE | F16: 3364 | G16: 105X161 | H16: 11.95 | I16: OK | J16: G10 | K16: 1609 | L16: 671.7 | M16: 44211
A18: GRAFICA VITÓRIA
A19: REZLER | B19: 44179 | C19: 44179 | D19: 5678 | E19: B.BORR | F19: 2640 | G19: 80X50 | H19: 10.4 | I19: OK | J19: GV | K19: 1610 | L19: 460
A20: SEXY FANTASY | B20: 44179 | C20: 44181 | D20: 5649 | E20: COUCHE | F20: 2825 | G20: 106X85 | H20: 7.5 | I20: OK | J20: GV | K20: 1591 | L20: 267.95
A21: HOSP. SC | B21: 44175 | C21: 44173 | D21: 5680 | E21: BOPP | F21: 1491 | G21: 100X23 | H21: 71 | I21: OK | J21: GV | K21: 1589 | L21: 324.8
A22: TR CARTUCHOS | B22: 44176 | C22: 44173 | D22: 5596 | E22: COUCHE | F22: 1120 | G22: 80X40 | H22: 10 | I22: OK | J22: GV | K22: 1590 | L22: 175
A23: AMF INFO | B23: 44154 | C23: 44159 | D23: 5372 | E23: BOPP | F23: 1405 | G23: 15X10 | H23: 40 | I23: OK | J23: GV | K23: 1551 | L23: 204
A24: ESTERELIZARE | B24: 44179 | C24: 44168 | D24: 5432 | E24: COUCHE | F24: 2691 | G24: 100X50 | H24: 128.6 | I24: OK | J24: GV | K24: 1561 | L24: 2100 | M24: DEZEMBRO
A25: URSULA | B25: 44166 | C25: 44181 | D25: 5551 | E25: BOPP | F25: 3219 | G25: 109X25 | H25: 21 | I25: OK | J25: GV | K25: 1568 | L25: 560
A26: DOLCEMONTE | B26: 44169 | C26: 44173 | D26: 5405 | E26: COUCHE | F26: 3210 | G26: 66X25 | H26: 30 | I26: OK | J26: GV | K26: 1572 | L26: 465
A27: FILTERCASTILHOS | B27: 44169 | C27: 44173 | D27: 5536 | E27: C.BORR | F27: 3344 | G27: 100X86 | H27: 10.24 | I27: OK | J27: GV | K27: 1575 | L27: 460
E28: C.BORR | F28: 3345 | G28: 50X20 | H28: 21 | I28: OK | J28: GV | K28: 1576 | L28: 240
A29: RR VISION | B29: 44168 | C29: 44173 | D29: 5535 | E29: BOPP | F29: 2844 | G29: 48X10 | H29: 10 | I29: OK | J29: GV | K29: 1577 | L29: 60
A30: DUKE | B30: 44169 | C30: 44172 | D30: 5589 | E30: COUCHE | F30: 2800 | G30: 60X60 | H30: 3.5 | I30: OK | J30: GV | K30: 1579
E31: COUCHE | F31: 2891 | G31: 45X45 | H31: 10 | I31: OK | J31: GV | K31: 1579 | L31: 260
A32: MAR AZUL | B32: 44173 | D32: 5588 | E32: BOPP | F32: 2175 | G32: 30X80 | H32: 10 | I32: OK | J32: GV | K32: 1580 | L32: 185
A33: MCC | B33: 44172 | C33: 44167 | D33: 5636 | E33: C.BORR | F33: 2491 | G33: 100X90 | H33: 10.34 | I33: OK | J33: GV | K33: 1581 | L33: 450
A34: PEDRO SANZ | B34: 44172 | C34: 44169 | D34: 5470 | E34: BOPP | F34: 2555 | G34: 74X74 | H34: 10 | I34: OK | J34: GV | K34: 1582 | L34: 680
A35: ALTERNATIVA | B35: 44173 | C35: 44173 | D35: 5546 | E35: COUCHE | F35: 2357 | G35: 55X28 | H35: 5 | I35: OK | J35: GV | K35: 1583 | L35: 100
A36: RIVA | B36: 44172 | C36: 44174 | D36: 5690 | E36: COUCHE | F36: 1862 | G36: 100X35 | H36: 21 | I36: OK | J36: GV | K36: 1584 | L36: 522.9
A37: FRUTI-FRANGO | B37: 44179 | C37: 44180 | D37: 5648 | E37: TAG | F37: 3367 | G37: 90X30 | H37: 5 | I37: OK | J37: GV | K37: 1596 | L37: 115
A38: SUPERCOR | B38: 44179 | C38: 44174 | D38: 5702 | E38: COUCHE | F38: 744 | G38: 100X70 | H38: 20 | I38: OK | J38: GV | K38: 1598 | L38: 702
A39: PORTAL USINAGEM | B39: 44181 | C39: 44180 | D39: 5725 | E39: COUCHE | F39: 1631 | G39: 60X60 | H39: 23250 | I39: OK | J39: GV | K39: 1599 | L39: 440
A40: CONEXAO URBANA | B40: 44181 | C40: 44183 | D40: 5534 | E40: COUCHE | F40: 2575 | G40: 33X50 | H40: 51.6 | I40: OK | J40: GV | K40: 1600 | L40: 260
A41: DIAN TECIDOS | B41: 44181 | C41: 44180 | D41: 5637 | E41: COUCHE | F41: 1215 | G41: 40X34 | H41: 6 | I41: OK | J41: GV | K41: 1601 | L41: 72
A42: DIAN TECIDOS | B42: 44181 | E42: COUCHE | F42: 1513 | G42: 50X80 | H42: 5 | I42: não | J42: GV | K42: 1602 | L42: 0
A43: AMF INFO | B43: 44169 | C43: 44181 | D43: 5605 | E43: TAG | F43: 2708 | G43: 31X145 | H43: 10.8 | I43: OK | J43: GV | K43: 1604 | L43: 196
A44: EBS | B44: 44182 | C44: 44180 | D44: 5569 | E44: BOPP.BORR | F44: 2329 | G44: 105X105 | H44: 4 | I44: OK | J44: GV | K44: 1611 | L44: 474.8
A46: FACA
A47: ABBOCARE | B47: 44125 | C47: 44172 | D47: 5286 | E47: B.BORR | F47: 2468 | G47: 100X80 | H47: 6 | I47: OK | J47: FACA | L47: 208
A48: WAGNER | B48: 44154 | C48: 44172 | D48: 5502 | E48: B.BORR | F48: 3341 | G48: 50X50 | H48: 5 | I48: OK | J48: FACA | L48: 127.1
A49: ESB | B49: 44168 | C49: 44172 | D49: 5620 | E49: B.BORR | F49: 3348 | G49: 100X100 | H49: 2 | I49: OK | J49: FACA | L49: 237.6
A50: RODER | B50: 44166 | C50: 44166 | D50: 5699 | E50: COUCHE | F50: 2762 | G50: 25X16 | H50: 0.2 | I50: OK | J50: FACA
C51: 44166 | E51: AZUL | F51: 2819 | G51: 50X40 | H51: 0.2 | I51: OK | J51: FACA | L51: 4.8
A52: AAO | B52: 03/12 | C52: 30/11 | D52: 5696 | E52: COUCHE | F52: 838 | G52: 100X40 | H52: 10 | I52: OK | J52: FACA | L52: 280
A53: COMPUMIX | B53: 03/12 | C53: 02/12 | D53: 5697 | E53: COUCHE | F53: 753 | G53: 100X50 | H53: 10.4 | I53: OK
A54: GRUPO EURO | B54: 44169 | C54: 44165 | D54: 5673 | E54: COUCHE | F54: 838 | G54: 100X40 | H54: 20 | I54: OK | J54: FACA | L54: 600
A55: BARRA DA SAIA | B55: 44169 | C55: 44166 | D55: 5672 | E55: COUCHE | F55: 908 | G55: 50X20 | H55: 28 | I55: OK | J55: FACA | L55: 178.5
A56: VESA | B56: 44166 | C56: 44181 | D56: 5462 | E56: COUCHE | F56: 838 | G56: 100X40 | H56: 300 | I56: OK | J56: FACA | L56: 11700
A57: LAMINA | B57: 44172 | C57: 44166 | D57: 4501 | E57: COUCHE | F57: 885 | G57: 70X50 | H57: 91.7 | I57: OK | J57: FACA | L57: 1350
A58: HOSP. UNIMED | B58: 44172 | C58: 44166 | D58: 5679 | E58: COUCHE | F58: 2740 | G58: 90X36 | H58: 9 | I58: OK | J58: FACA | L58: 133.2
A59: MODAZINE | B59: 44172 | C59: 44168 | D59: 5682 | E59: VERM | F59: 2017 | G59: 33X21 | H59: 50 | I59: OK | J59: FACA
E60: AMAR | F60: 3363 | G60: 33X21 | H60: 75 | I60: OK | J60: FACA
E61: COUCHE | F61: 3302 | G61: 33X21 | H61: 25 | I61: OK | J61: FACA
E62: COUCHE | F62: 3303 | G62: 90X25 | H62: 30 | I62: OK | J62: FACA | L62: 974.25
A63: HYVA | B63: 44174 | C63: 44169 | D63: 5704 | E63: C.BORR | F63: 2244 | G63: 100X60 | H63: 30.1 | I63: OK | J63: FACA | L63: 1395
A64: HYVA | B64: 44174 | C64: 44169 | D64: 5703 | E64: C.BORR | F64: 1712 | G64: 50X50 | H64: 12 | I64: OK | J64: FACA | L64: 222
A65: PANIZZON | B65: 44176 | C65: 44175 | D65: 5618 | E65: COU | F65: 1545 | G65: 100X68 | H65: 20 | I65: OK | J65: FACA
E66: VERDE | F66: 2448 | G66: 100X68 | H66: 10 | I66: OK | J66: FACA
E67: ROSA | F67: 2818 | G67: 100X68 | H67: 10 | I67: OK | J67: FACA
E68: AZUL | F68: 2576 | G68: 100X68 | H68: 10 | I68: OK | J68: FACA
E69: LARANJA | F69: 2589 | G69: 100X68 | H69: 10 | I69: OK | J69: FACA | L69: 2172
A70: MODAZINE | B70: 44187 | C70: 44167 | D70: 5583 | E70: COUCHE | F70: 3303 | G70: 90X25 | H70: 45 | I70: OK | J70: FACA | L70: 540
A71: FERRARI | B71: 44174 | C71: 44169 | D71: 5683 | E71: AMAR | F71: 3365 | G71: 100X50 | H71: 5.6 | I71: OK | J71: FACA
E72: VERDE | F72: 3366 | G72: 100X50 | H72: 5.6 | I72: OK | J72: FACA | L72: 344
A73: FANTASTIC | B73: 44174 | C73: 44166 | D73: 5707 | E73: COUCHE | F73: 1869 | G73: 33X21 | H73: 15 | I73: OK | J73: FACA | L73: 105
A74: TOP LIMP | B74: 44174 | C74: 44173 | D74: 5614 | E74: COUCHE | F74: 2515 | G74: 55X28 | H74: 15 | I74: OK | J74: FACA
E75: AMARELO | F75: 2765 | G75: 55X28 | H75: 10 | I75: OK | J75: FACA | L75: 322.5
A76: ESTILO RADICAL | B76: 43836 | C76: 44166 | D76: 5684 | E76: COUCHE | F76: 855 | G76: 50X40 | H76: 40 | I76: OK | J76: FACA | L76: 508.4
A77: CASA E CIA | B77: 44174 | C77: 44167 | D77: 5713 | E77: COUCHE | F77: 616 | G77: 40X30 | H77: 20 | I77: OK | J77: FACA | L77: 250
A78: AMARAL | B78: 44174 | C78: 44173 | D78: 5783 | E78: COUCHE | F78: 2515 | G78: 55X28 | H78: 10 | I78: OK | J78: FACA | L78: 145
A79: FLORENZA | B79: 44175 | C79: 44169 | D79: 5722 | E79: COUCHE | F79: 838 | G79: 100X40 | H79: 10 | I79: OK | J79: FACA | L79: 210
A80: HUGO PIETRO | B80: 44176 | C80: 44168 | D80: 5726 | E80: COUCHE | F80: 2264 | G80: 80X60 | H80: 60.2 | I80: OK | J80: FACA | L80: 1050
A81: HOSP. SAUDE | B81: 44175 | C81: 44176 | D81: 5721 | E81: COUCHE | F81: 2738 | G81: 73X30 | H81: 11.25 | I81: OK | J81: PERS
F82: 2737 | G82: 87X45 | H82: 16.5 | I82: OK | J82: FACA | K82: 90X40
F83: 2742 | G83: 87X45 | H83: 5.6 | I83: OK | J83: FACA | K83: 90X40 | L83: 1025
A84: BANCO DE SANGUE | B84: 44176 | C84: 44173 | D84: 5727 | E84: COUCHE | F84: 2515 | G84: 55X28 | H84: 2.5 | I84: OK | J84: FACA
E85: BOPP | F85: 2467 | G85: 100X80 | H85: 3 | I85: OK | J85: FACA | L85: 307.08
A86: HYVA | B86: 44176 | C86: 44173 | D86: 5729 | E86: C.BORR | F86: 2244 | G86: 100X60 | H86: 8.4 | I86: OK | J86: FACA | L86: 1302
A87: APOMEDIL | B87: 44176 | C87: 44173 | D87: 5732 | E87: COUCHE | F87: 2515 | G87: 55X28 | H87: 32.5 | I87: OK | J87: FACA | L87: 1075
A88: PETRYMAR | B88: 44176 | C88: 44169 | D88: 5734 | E88: COUCHE | F88: 753 | G88: 100X50 | H88: 20 | I88: OK | J88: FACA | L88: 520
A89: AMF INFO | B89: 44179 | C89: 44172 | D89: 5740 | E89: COUCHE | F89: 1786 | G89: 90X25 | H89: 6 | I89: OK | J89: FACA | L89: 120
A90: DUKE | B90: 44138 | C90: 44169 | D90: 5278 | E90: COUCHE | F90: 2800 | G90: 45X45 | H90: 4.8 | I90: OK | J90: LASER | L90: 260
A91: GAMACOR | B91: 44180 | C91: 44172 | D91: 5755 | E91: COUCHE | F91: 1862 | G91: 100X35 | H91: 15 | I91: OK | J91: FACA | L91: 358.5
A92: UNIMED | B92: 44180 | C92: 44173 | D92: 5756 | E92: COUCHE | F92: 2740 | G92: 90X36 | H92: 19 | I92: OK | J92: FACA | L92: 281.2
A93: MODAZINE | B93: 44180 | C93: 44172 | D93: 5758 | E93: COUCHE | F93: 3302 | G93: 33X21 | H93: 20 | I93: OK | J93: FACA | L93: 81.4
A94: ESTOQUE | B94: 44172 | C94: 44172 | D94: 5758 | E94: COUCHE | F94: 1869 | G94: 33X21 | H94: 10 | I94: OK | J94: FACA | L94: 0
A95: COMPUMIX | B95: 44169 | C95: 44169 | D95: 5281 | E95: COUCHE | F95: 1555 | G95: 50X30 | H95: 100 | I95: OK | J95: FACA | L95: 800
A96: KIPERFIL | B96: 44180 | C96: 44173 | D96: 5761 | E96: COUCHE | F96: 838 | G96: 100X40 | H96: 10 | I96: OK | J96: FACA | L96: 260
A97: RIO PRATA | B97: 44180 | C97: 44175 | D97: 5750 | E97: COUCHE | F97: 855 | G97: 70X50 | H97: 5 | I97: OK | J97: FACA | L97: 127.5
E98: TAG | F98: 2550 | G98: 100X70 | H98: 2 | I98: OK | J98: LASER | L98: 71
A99: AMF INFO | B99: 44176 | C99: 44174 | D99: 5772 | E99: COUCHE | F99: 822 | G99: 50X50 | H99: 51 | I99: OK | J99: FACA | L99: 600
A100: ORIGIN | B100: 44181 | C100: 44175 | D100: 5773 | E100: COUCHE | F100: 1468 | G100: 100X75 | H100: 2 | I100: OK | J100: FACA | L100: 61.8
A101: FIBRASIL | B101: 44176 | C101: 44174 | D101: 5774 | E101: COUCHE | F101: 2740 | G101: 90X36 | H101: 6 | I101: OK | J101: FACA | L101: 114
A102: LC SOLUCOES | B102: 44176 | C102: 44174 | D102: 5776 | E102: COUCHE | F102: 822 | G102: 50X50 | H102: 150 | I102: OK | J102: FACA | L102: 1875
A103: RODER | B103: 44182 | C103: 44175 | D103: 5778 | E103: COUCHE | F103: 2762 | G103: 25X16 | H103: 20 | I103: OK | J103: FACA | L103: 35.55
...

Sheet JANEIRO21
A1: CLIENTE | B1: Data Entr | C1: Data Prod | D1: O/F | E1: MATERIAL | F1: CÓDIGO | G1: ETIQUETA | H1: QUANT | I1: OK | J1: PRODUZIDO POR | K1: O/C | L1: VALOR
A2: GRAFICA 10
A3: ALTAIR/FARMB | C3: 44223 | D3: 5397 | E3: TC | F3: 3282 | G3: 45X85 | H3: 5430 | I3: OK | J3: G10 | K3: 1607 | L3: 1100
A4: HIDROQUIMICA | B4: 44182 | C4: 44207 | D4: 5625 | E4: TC | F4: 3349 | G4: 100X200 | H4: 4.8 | I4: OK | J4: G10 | K4: 1606 | L4: 1675
A5: AMF | B5: 44230 | C5: 44222 | D5: 5988 | E5: TAG | F5: 2780 | G5: 41X75 | H5: 161 | I5: OK | J5: G10 | K5: 1615 | L5: 1837.5
A7: GRAFICA VITÓRIA
A8: ESTERELIZARE | B8: 44182 | C8: 44208 | D8: 5753 | E8: COUCHE | F8: 2691 | G8: 100X50 | H8: 130.4 | I8: OK | J8: GV | K8: 1603 | L8: 2100
A9: RANDON | B9: 44182 | C9: 44202 | D9: 5777 | E9: TERMICO | F9: 2606 | G9: 25X75 | H9: 7.5 | I9: OK | J9: GV | K9: 1612 | L9: 148.5
A10: MAQENGE | B10: 43848 | C10: 44209 | D10: 5810 | E10: COUCHE | F10: 2720 | G10: 47X22 | H10: 72 | I10: OK | J10: GV | K10: 1616
E11: COUCHE | F11: 1467 | G11: 85X50 | H11: 52.8 | I11: OK | J11: GV | K11: 1616 | L11: 1536.5
A12: ORIGIN | B12: 43841 | C12: 44210 | D12: 5858 | E12: COUCHE | F12: 2578 | G12: 60X20 | H12: 20 | I12: OK | J12: GV | K12: 1617 | L12: 310
A13: AMF | B13: 44210 | C13: 44214 | D13: 5991 | E13: COUCHE | F13: 784 | G13: 30X15 | H13: 200 | I13: OK | J13: GV | K13: 1618 | L13: 810
B14: 44210 | C14: 44225 | D14: 5980 | E14: B.BORR | F14: 2335 | G14: 30X15 | H14: 15 | I14: OK | J14: GV | K14: 1618 | L14: 747
A15: SOGIMA | B15: 43848 | C15: 44218 | D15: 5096 | E15: COUCHE | F15: 2149 | G15: 70X40 | H15: 15 | I15: OK | J15: GV | K15: 1619 | L15: 213.9
A16: AMF INFO | B16: 43848 | D16: 5901 | E16: B.BORR | F16: 1405 | G16: 15X10 | H16: 460 | I16: NÃO | J16: GV | K16: 1620 | L16: 340
A17: ZBM | B17: 44217 | C17: 44215 | D17: 5915 | E17: LARANJA | F17: 3393 | G17: 44X60 | H17: 20 | I17: OK | J17: GV | K17: 1621 | L17: 376.2
A18: HOSP. SC | B18: 44221 | C18: 44218 | D18: 5930 | E18: BOPP | F18: 1491 | G18: 100X23 | H18: 18 | I18: OK | J18: GV | K18: 1622 | L18: 470
A19: FERPLAST | B19: 44221 | C19: 44221 | D19: 5924 | E19: COUCHE | F19: 1215 | G19: 40X34 | H19: 51.4 | I19: OK | J19: GV | K19: 1624 | L19: 600.5
A20: ARCO | B20: 43841 | C20: 44217 | D20: 5866 | E20: COUCHE | F20: 2604 | G20: 105X55 | H20: 69.6 | I20: OK | J20: GV | K20: 1625 | L20: 470
A21: MATRIMETAL | B21: 44225 | C21: 44219 | D21: 6064 | E21: COUCHE | F21: 2022 | G21: 80X30 | H21: 13 | I21: OK | J21: GV | K21: 1626 | L21: 229.35
A22: DUKE | B22: 44222 | D22: 6096 | E22: COUCHE | F22: 2800 | G22: 45X45 | H22: 40 | I22: OK | J22: GV | K22: 1629 | L22: 312
A23: HOFFMANN | B23: 44225 | C23: 44225 | D23: 6108 | E23: COUCHE | F23: 1215 | G23: 40X34 | H23: 106 | I23: OK | J23: GV | K23: 1631 | L23: 707
A25: FACA E LASER
A26: AMF INFO | B26: 44183 | C26: 44200 | D26: 5863 | E26: B.BORR | F26: 3389 | G26: 80X140 | H26: 5.27 | I26: OK | J26: LASER | L26: 540
A27: DIAN TECIDOS | B27: 44181 | C27: 44200 | E27: COUCHE | F27: 1513 | G27: 50X80 | H27: 1 | I27: OK | J27: GV | K27: 1602 | L27: 60
A28: DIFLORES | B28: 5691 | C28: 44201 | D28: 5691 | E28: 210GR | F28: 2993 | G28: 35X64 | H28: 21 | I28: OK | J28: LASER | L28: 283.5
A29: SILVANA | B29: 43838 | C29: 44201 | D29: 5852 | E29: B.BORR | F29: 2743 | G29: 95X12 | H29: 5 | I29: OK | J29: LASER | L29: 72.5
A30: LOJA HIP | B30: 43838 | C30: 44202 | D30: 5853 | E30: COUCHE | F30: 1556 | G30: 55X25 | H30: 21 | I30: OK | J30: LASER | L30: 250
A31: HEMOVITA | B31: 44202 | C31: 44202 | D31: 5953 | E31: TERMICO | F31: 3081 | G31: 100X120 | H31: 6.65 | I31: OK | J31: LASER | L31: 678.3
A32: INJET | B32: 43848 | C32: 44207 | D32: 5710 | E32: COUCHE | F32: 97 | G32: 80X90 | H32: 1 | I32: OK | J32: LASER
E33: COUCHE | F33: 1467 | G33: 85X50 | H33: 1.6 | I33: OK | J33: LASER | L33: 98
A34: DOLCEMONTE | B34: 43859 | C34: 44207 | D34: 5754 | E34: COUCHE | F34: 3210 | G34: 66X25 | H34: 62.2 | I34: OK | J34: LASER
A35: DOLCEMONTE | B35: 44225 | C35: 44207 | D35: 5998 | E35: COUCHE | F35: 3214 | G35: 10x9 | H35: 80 | I35: OK | J35: LASER | L35: 1521
A36: DOLCEMONTE | C36: 44218 | D36: 5754 | E36: COUCHE | F36: 992 | G36: 30X30 | H36: 32 | I36: OK | J36: FACA BATIDA | L36: 285
E37: COUCHE | F37: 3376 | G37: 90X90 | H37: 4 | I37: OK | J37: FACA BATIDA | L37: 166
A38: FOODCHAIN | B38: 43841 | C38: 44222 | D38: 5760 | E38: BOPP | F38: 1169 | G38: 100X30 | H38: 13.75 | I38: OK | J38: FACA BATIDA
E39: BOPP | F39: 3370 | G39: 33X10 | H39: 10 | I39: OK | J39: FACA BATIDA
A40: RIGOTTO | B40: 43848 | C40: 44223 | D40: 5819 | E40: COUCHE | F40: 2357 | G40: 55X28 | H40: 6.25 | I40: OK | J40: FACA BATIDA | L40: 100
A41: EMPLAC | B41: 43848 | C41: 44222 | D41: 5708 | E41: COUCHE | F41: 3005 | G41: 90X60 | H41: 1.4 | I41: OK | J41: FACA BATIDA | L41: 34.1
A42: MODA VIVA | B42: 43848 | C42: 44222 | D42: 5468 | E42: COUCHE | F42: 2415 | G42: 33X39 | H42: 34 | I42: OK | J42: FACA BATIDA | L42: 155
A43: CARLIN | B43: 44218 | C43: 44221 | D43: 5029 | E43: COUCHE | F43: 2837 | G43: 45X60 | H43: 7.5 | I43: OK | J43: LASER | L43: 104.65
A44: FERPLAST | C44: 44224 | D44: 5924 | E44: COUCHE | F44: 2114 | G44: 80X45 | H44: 10 | I44: OK | J44: FACA BATIDA | L44: 442.95
A45: CORSUL | B45: 44218 | C45: 44224 | D45: 5917 | E45: COUCHE | F45: 2347 | G45: 50X150 | H45: 5 | I45: OK | J45: LASER | K45: NÃO | L45: 347
A46: AMF INFO | B46: 44222 | C46: 44221 | D46: 5987 | E46: TAG | F46: 2781 | G46: 55X75 | H46: 22.85 | I46: OK | J46: LASER | L46: 329
A47: AMF INFO | B47: 44225 | C47: 44224 | D47: 6031 | E47: VERMELHO | F47: 1548 | G47: 13X13 | H47: 60 | I47: OK | J47: LASER | K47: NÃO | L47: 140
A48: FICA F&C | B48: 44225 | C48: 44222 | D48: 6055 | E48: TAG | F48: 2081 | G48: 35X51 | H48: 5 | I48: OK | J48: LASER | L48: 84
A49: BOISUL | B49: 44225 | C49: 44223 | D49: 6068 | E49: TAG PLAST | F49: 2631 | G49: 75X263 | H49: 4.28 | I49: OK | J49: LASER
E50: B.BORR | F50: 2632 | G50: 103X94 | H50: 5 | J50: SEM PAPEL
E51: COUCHE | F51: 2039 | G51: 40X55 | H51: 6 | I51: OK | J51: LASER | L51: 1457.25
A52: MAGAZINE | B52: 44225 | C52: 44222 | D52: 6100 | E52: TAG | F52: 1195 | G52: 50X75 | H52: 2 | I52: OK | J52: LASER | L52: 83.16
E53: TAG | F53: 1112 | G53: 50X75 | H53: 4 | I53: OK | J53: LASER | L53: 149.68
A54: FARMBERRY | B54: 44223 | C54: 44223 | D54: 6111 | E54: TC | F54: 3282 | G54: 45X85 | H54: 4.98 | I54: OK | J54: PERSONAL
E55: TC | F55: 2749 | G55: 45X85 | H55: 0.45 | I55: OK | J55: PERSONAL | L55: 975
A56: AMF INFO | B56: 43838 | C56: 44201 | D56: 5816 | E56: COUCHE | F56: 1869 | G56: 33X21 | H56: 80 | I56: OK | J56: FACA | L56: 296
A57: AMF INFO | B57: 43838 | C57: 44201 | D57: 5817 | E57: COUCHE | F57: 1468 | G57: 100X75 | H57: 21 | I57: OK | J57: FACA | L57: 612
A58: AMF INFO | B58: 43838 | C58: 44200 | D58: 5878 | E58: COUCHE | F58: 2762 | G58: 25X16 | H58: 50 | I58: OK | J58: FACA | L58: 150
A59: SPRAY JET | B59: 43841 | C59: 44202 | D59: 5892 | E59: TERMICO | F59: 2847 | G59: 100x150 | H59: 5 | I59: OK | J59: FACA | L59: 646.5
A60: VF ACESS | B60: 43841 | C60: 44200 | D60: 5897 | E60: COUCHE | F60: 879 | G60: 100X60 | H60: 10.5 | I60: OK | J60: FACA | L60: 441
A61: CRIPPA | B61: 44209 | C61: 44202 | D61: 5939 | E61: COUCHE | F61: 1098 | G61: 90X80 | H61: 40 | I61: OK | J61: FACA | L61: 1200
A62: GAMACOR | B62: 44209 | C62: 44203 | D62: 5943 | E62: COUCHE | F62: 1862 | G62: 100X35 | H62: 15 | I62: OK | J62: FACA | L62: 359.5
A63: GLOBALTECH | B63: 44209 | C63: 44203 | D63: 5958 | E63: COUCHE | F63: 616 | G63: 40X30 | H63: 10 | I63: OK | J63: FACA | L63: 125
A64: SUPERLACK | B64: 44209 | C64: 44203 | D64: 5961 | E64: COUCHE | F64: 838 | G64: 100X40 | H64: 5 | I64: OK | J64: FACA | L64: 140
A65: DOLCEMONTE | B65: 44210 | C65: 44207 | D65: 5998 | E65: COUCHE | F65: 2039 | G65: 40x55 | H65: 60 | I65: OK | J65: FACA | L65: 630
A66: VESA | C66: 44208 | D66: 5462 | E66: COUCHE | F66: 838 | G66: 100X40 | H66: 300 | I66: OK | J66: FACA | L66: 11700
A67: FERPLAST | B67: 44209 | C67: 44210 | D67: 5924 | E67: COUCHE | F67: 951 | G67: 100X150 | H67: 10 | I67: OK | J67: FACA | L67: 889.3
A68: SORVELANDIA | B68: 44209 | C68: 44204 | D68: 5938 | E68: COUCHE | F68: 2039 | G68: 40X55 | H68: 81 | I68: OK | J68: FACA | L68: 1080
A69: ECOMACH | B69: 44210 | C69: 44209 | D69: 5980 | E69: B.BORR | F69: 2050 | G69: 100X75 | H69: 3 | I69: OK | J69: FACA | L69: 294
A70: AMF INFO | B70: 44211 | C70: 44210 | D70: 5988 | E70: COUCHE | F70: 855 | G70: 50X40 | H70: 150 | I70: OK | J70: FACA | L70: 1320
A71: AMF INFO | B71: 44211 | C71: 44209 | D71: 5989 | E71: COUCHE | F71: 1126 | G71: 100X100 | H71: 6 | I71: OK | J71: FACA
E72: COUCHE | F72: 822 | G72: 50X50 | H72: 50 | I72: OK | J72: FACA | L72: 824.4
A73: AMF INFO | B73: 44211 | C73: 44210 | D73: 5990 | E73: COUCHE | F73: 2759 | G73: 30X38 | H73: 21 | I73: OK | J73: FACA | L73: 114.45
A74: AMF INFO | B74: 44211 | C74: 44214 | D74: 5992 | E74: COUCHE | F74: 879 | G74: 100X60 | H74: 50.4 | I74: OK | J74: FACA
E75: COUCHE | F75: 2186 | G75: 90X40 | H75: 50 | I75: OK | J75: FACA | L75: 1787.5
A76: AMF INFO | B76: 44211 | C76: 44209 | D76: 5994 | E76: COUCHE | F76: 855 | G76: 50X40 | H76: 50 | I76: OK | J76: FACA | L76: 440
A77: BOSS | B77: 44211 | C77: 44209 | D77: 6001 | E77: B.BORR | F77: 1095 | G77: 100X50 | H77: 3.2 | I77: OK | J77: FACA | L77: 113.6
A78: DTECH | B78: 44214 | C78: 44215 | D78: 6007 | E78: COUCHE | F78: 2762 | G78: 25X16 | H78: 100 | I78: OK | J78: FACA | L78: 430
A79: HUGO PIETRO | B79: 44215 | C79: 44217 | D79: 6021 | E79: COUCHE | F79: 2264 | G79: 80X60 | H79: 60.2 | I79: OK | J79: FACA | L79: 1050
A80: VITAMED | B80: 44215 | D80: 6025 | E80: COUCHE | F80: 838 | G80: 100X40 | H80: 40 | I80: OK | J80: FACA | L80: 1400
A81: UNIMED | B81: 44215 | C81: 44214 | D81: 6032 | E81: COUCHE | F81: 2740 | G81: 90X36 | H81: 19 | I81: OK | J81: FACA | L81: 281.2
A82: LOVATO | B82: 44209 | C82: 44208 | D82: 6033 | E82: COUCHE | F82: 1468 | G82: 100X75 | H82: 15 | I82: OK | J82: FACA | L82: 625.95
A83: RUBINETTOS | B83: 44217 | C83: 44215 | D83: 5916 | E83: COUCHE | F83: 753 | G83: 100x50 | H83: 5.6 | I83: OK | J83: FACA | L83: 156.95
A84: MAQENGE | B84: 44214 | C84: 44207 | D84: 5810 | E84: COUCHE | F84: 1467 | G84: 85X50 | H84: 4.8 | I84: OK | J84: LASER | L84: 119.52
A85: AMF INFO | B85: 44207 | C85: 44207 | D85: 6044 | E85: COUCHE | F85: 822 | G85: 50X50 | H85: 12 | I85: OK | J85: FACA | L85: 144
E86: COUCHE | F86: 869 | G86: 33X25 | H86: 10 | I86: OK | J86: FACA | L86: 36
A87: ECO METAIS | B87: 44216 | C87: 44221 | D87: 5912 | E87: COUCHE | F87: 1007 | G87: 100X38 | H87: 30 | I87: OK | J87: FACA NOVA | L87: 356
A88: JONES | B88: 44216 | C88: 44216 | E88: TERMICO | F88: 2115 | G88: 40X40 | H88: 198 | I88: OK | J88: FACA
A89: SEXY FANTASY | B89: 44216 | C89: 44210 | D89: 6035 | E89: COUCHE | F89: 1087 | G89: 28X55 | H89: 50 | I89: OK | J89: FACA | L89: 525
E90: COUCHE | F90: 2639 | G90: 15X30 | H90: 20 | I90: OK | J90: FACA | L90: 70
A91: HYVA | B91: 44217 | C91: 44216 | D91: 5729 | E91: C.BORR | F91: 2244 | G91: 100X60 | H91: 6.3 | I91: OK | J91: FACA | L91: 1348.6
A92: HYVA | B92: 44217 | D92: 6046 | E92: C.BORR | F92: 1712 | G92: 50X50 | H92: 22.5 | I92: OK | J92: FACA
E93: C.BORR | F93: 2244 | G93: 100X60 | H93: 20.3 | I93: OK | J93: FACA | L93: 1300
A94: CIRCULO | B94: 44217 | C94: 44215 | D94: 6015 | E94: COUCHE | F94: 838 | G94: 100X40 | H94: 10 | I94: OK | J94: FACA | L94: 280
A95: DOLCE VITA | B95: 44218 | D95: 6047 | E95: BOPP | F95: 3334 | G95: 20X10 | H95: 60 | I95: OK | J95: FACA
E96: COUCHE | F96: 855 | G96: 50X40 | H96: 8 | I96: OK | J96: FACA
E97: COUCHE | F97: 1397 | G97: 50X30 | H97: 10 | I97: OK | J97: FACA
E98: COUCHE | F98: 885 | G98: 70X50 | H98: 2.8 | I98: OK | J98: FACA
E99: COUCHE | F99: 869 | G99: 33X25 | H99: 20 | I99: OK | J99: FACA
E100: COUCHE | F100: 3234 | G100: 50X20 | H100: 14 | I100: OK | J100: FACA
E101: COUCHE | F101: 1786 | G101: 90x25 | H101: 40 | I101: OK | J101: FACA | L101: 2067.64
A102: SEXY FANTASY | B102: 44218 | D102: 5649 | E102: COUCHE | F102: 1087 | G102: 28X55 | H102: 5 | I102: OK | J102: FACA | L102: 106.09
...

Sheet FEVEREIRO21
A1: CLIENTE | B1: Data Entr | C1: Data Prod | D1: O/F | E1: MATERIAL | F1: CÓDIGO | G1: ETIQUETA | H1: QUANT | I1: OK | J1: PRODUZIDO POR | K1: O/C | L1: VALOR
A2: GRAFICA 10
B3: 43866 | C3: 44230 | D3: 6123 | E3: TAG | F3: 3361 | G3: 35X62 | H3: 61.2 | I3: OK | J3: G10 | L3: 1218
A4: MODAZINE | B4: 44232 | C4: 44230 | D4: 5940 | E4: TAG | F4: 3361 | G4: 35X62 | H4: 68.4 | I4: OK | J4: G10 | L4: 1218
A5: MODAZINE | B5: 44249 | D5: 6349 | E5: TAG | F5: 3361 | G5: 35X62 | H5: 60 | J5: G10 | K5: 1634 | L5: 1218
D6: 6350 | E6: TAG | F6: 3361 | G6: 35X62 | H6: 60 | L6: 1218
A7: FARMBERRY | B7: 44232 | E7: TC | F7: 2749 | G7: 45X85 | H7: 22 | J7: G10 | K7: 1635 | L7: 2420
A8: MODAZINE | B8: 44258 | D8: EXTRA | E8: TAG | F8: 3361 | G8: 35X62 | H8: 145 | J8: G10 | K8: 1638 | L8: 0
A9: TECNOLOGICA | B9: 44265 | D9: 6367 | E9: TERMICA | F9: 2043 | G9: 50X22 | H9: 10 | J9: G10 | K9: 1639 | L9: 490
A12: GRAFICA VITÓRIA
A13: PLASMOSUL | B13: 44225 | D13: 6098 | E13: COUCHE | F13: 3239 | G13: 90X40 | H13: 5 | J13: GV | K13: 1630 | L13: 79.8
A14: AMF INFO | B14: 44229 | C14: 44230 | D14: 6129 | E14: COUCHE | F14: 784 | G14: 30X15 | H14: 340 | I14: OK | J14: GV | K14: 1632 | L14: 810
A15: HUGO PIETRO | B15: 44229 | C15: 44231 | D15: 6130 | E15: COUCHE | F15: 1271 | G15: 30X22 | H15: 99 | I15: OK | J15: GV | K15: 1633 | L15: 445
A16: ESTERELIZARE | B16: 44253 | D16: 6421 | E16: COUCHE | F16: 2691 | G16: 100X50 | H16: 132 | J16: GV | K16: 1642 | L16: 2064
A19: FACA E LASER
A20: AMF INFO | B20: 43848 | D20: 5901 | E20: BOPP | F20: 1405 | G20: 15X10 | H20: 80 | I20: OK | J20: LASER | L20: 340 | M20: 1000 | N20: 80.000OK
C21: 44242 | H21: 20 | I21: OK
A22: AMF INFO | B22: 44224 | C22: 44242 | D22: 6131 | E22: BOPP | F22: 1405 | G22: 15X10 | H22: 300 | I22: OK
A23: SULPACK | B23: 44223 | C23: 44228 | D23: 6106 | E23: BOPP | F23: 1401 | G23: 50X22 | H23: 12 | I23: OK | J23: LASER | L23: 315
A24: AMF INFO | B24: 44222 | C24: 44228 | D24: 5986 | E24: TAG | F24: 3401 | G24: 50X120 | H24: 5 | I24: OK | J24: LASER | L24: 130
A25: HYVA | B25: 44228 | C25: 44228 | D25: 6149 | E25: TC | F25: 3444 | G25: 100X130 | H25: 1 | I25: OK | J25: LASER | L25: 160.7
A26: AMF INFO | B26: 44229 | C26: 44228 | D26: 6117 | E26: COUCHE | F26: 1869 | G26: 33X21 | H26: 80 | I26: OK | J26: FACA | L26: 296
A27: ARCANJO FONDUE | B27: 44230 | D27: 6178 | E27: C.BORR | F27: 2564 | G27: 50X70 | H27: 5 | I27: OK | J27: FACA | K27: PERS 8/02 | L27: 150
A28: DOMAMA | B28: 44230 | C28: 44228 | D28: 6184 | E28: COUCHE | F28: 2515 | G28: 55X28 | H28: 10 | I28: OK | J28: FACA
E29: COUCHE | F29: 838 | G29: 100X40 | H29: 10 | I29: OK | J29: FACA | L29: 385
A30: PETRYMAR | B30: 44230 | C30: 44228 | D30: 6188 | E30: COUCHE | F30: 753 | G30: 100X50 | H30: 15.2 | I30: OK | J30: FACA | L30: 411
A31: PEDRO SANZ | B31: 44230 | C31: 44238 | D31: 6187 | E31: BOPP | F31: 2555 | G31: 74X74 | H31: 10 | I31: OK | J31: LASER | L31: 680 | M31: 800
E32: BOPP | F32: 1627 | G32: 40X25 | H32: 5 | I32: OK | J32: LASER | L32: 123 | M32: 140
A33: MAQENGE | B33: 44232 | C33: 44232 | D33: 6146 | E33: COUCHE | F33: 1467 | G33: 85X50 | H33: 50.4 | I33: OK | J33: FACA
E34: COUCHE | F34: 2720 | G34: 47X22 | H34: 30 | I34: OK | J34: FACA | L34: 1419.9
A35: GAMACOR | B35: 44231 | C35: 44228 | D35: 6202 | E35: COUCHE | F35: 1862 | G35: 100X35 | H35: 15 | I35: OK | J35: FACA | L35: 358.5
A36: JONES | B36: 44231 | C36: 44238 | E36: TERMICO | F36: 2115 | G36: 40X40 | H36: 400 | I36: OK | J36: FACA
A37: ESTOQUE | B37: 44238 | C37: 44238 | E37: TERMICO | F37: 2115 | G37: 40X40 | H37: 20 | I37: OK | J37: FACA
A38: STELLABLU | B38: 44231 | C38: 44228 | D38: 6211 | E38: PROMOM | F38: 1019 | G38: 34X51 | H38: 3 | I38: OK | J38: LASER | L38: 50
A39: J PRIME | B39: 44231 | C39: 44228 | D39: 6214 | E39: COUCHE | F39: 838 | G39: 100X40 | H39: 10 | I39: OK | J39: FACA
E40: COUCHE | F40: 855 | G40: 50X40 | H40: 10 | I40: OK | J40: FACA | L40: 437
A41: ECO METAIS | B41: 44232 | C41: 44228 | D41: 6218 | E41: COUCHE | F41: 1007 | G41: 100X38 | H41: 10 | I41: OK | J41: FACA | L41: 178
A42: HYDROL | B42: 44232 | C42: 44228 | D42: 6219 | E42: COUCHE | F42: 1126 | G42: 100X100 | H42: 5.2 | I42: OK | J42: FACA | L42: 288.5
A43: CRIPPA | B43: 44232 | C43: 44228 | D43: 6222 | E43: COUCHE | F43: 1098 | G43: 90X80 | H43: 40 | I43: OK | J43: FACA | L43: 1200
A44: RESET | B44: 44232 | C44: 44228 | D44: 6221 | E44: COUCHE | F44: 1087 | G44: 28X55 | H44: 0.2 | I44: OK | J44: FACA | L44: 1.74
A45: G3 | B45: 44235 | C45: 44229 | D45: 6226 | E45: REMOVIVEL | F45: 3458 | G45: 40X30 | H45: 10 | I45: OK | J45: FACA | L45: 120
A46: ALEF | B46: 44235 | C46: 44229 | D46: 6229 | E46: COUCHE | F46: 1614 | G46: 40X40 | H46: 10 | I46: OK | J46: FACA | L46: 105
A47: INJET | B47: 44232 | C47: 44228 | D47: 6231 | E47: COUCHE | F47: 97 | G47: 80X90 | H47: 2.5 | I47: OK | J47: LASER | L47: 150
A48: URSULA | B48: 44232 | C48: 44229 | D48: 6234 | E48: BOPP | F48: 3219 | G48: 109X25 | H48: 30 | I48: OK | J48: LASER | L48: 840 | M48: 840
A49: AMF INFO | B49: 44235 | C49: 44229 | D49: 6159 | E49: COUCHE | F49: 2759 | G49: 30X38 | H49: 63 | I49: OK | J49: FACA | L49: 327
A50: PEDRO SANZ | B50: 44235 | C50: 44229 | D50: 6241 | E50: TC | F50: 2555 | G50: 74X74 | H50: 1 | I50: OK | J50: LASER | L50: 88.4
A51: VITAMED | B51: 44235 | C51: 44229 | D51: 6248 | E51: TC | F51: 3416 | G51: 100X75 | H51: 2.5 | I51: OK | J51: FACA | L51: 2175.4
E52: BOPP | F52: 2050 | G52: 100X75 | H52: 17.5 | I52: OK | J52: FACA
A53: MA ACESS | B53: 44235 | C53: 44230 | D53: 5205 | E53: COUCHE | F53: 2561 | G53: 77X32 | H53: 9 | I53: OK | J53: LASER | L53: 250
E54: C.BORR | F54: 3286 | G54: 103X93 | H54: 5 | I54: OK | J54: LASER | L54: 325
A55: NEUSA | B55: 44235 | C55: 44230 | D55: 6259 | E55: TC | F55: 2172 | G55: 33X25 | H55: 15 | I55: OK | J55: FACA
E56: TC | F56: 2560 | G56: 100X40 | H56: 1 | I56: OK | J56: FACA | L56: 230
A57: INJET | B57: 44236 | C57: 44228 | D57: 6263 | E57: COUCHE | F57: 97 | G57: 80X90 | H57: 2.5 | I57: OK | J57: FACA | L57: 145
A58: BRINCASA | B58: 44236 | C58: 44236 | D58: 6264 | E58: C.B | F58: 2481 | G58: 40X15 | H58: 500 | I58: OK | J58: FACA | L58: 1625 | M58: 4300
A59: AMF INFO | B59: 44236 | C59: 44229 | D59: 6256 | E59: PROMOM | F59: 3304 | G59: 100X75 | H59: 5 | I59: OK | J59: LASER | L59: 291.5
A60: MODAZINE | B60: 44249 | D60: 6123 | E60: COUCHE | F60: 3364 | G60: 105X161 | H60: 3.75 | I60: OK | J60: BATIDA | L60: 335.55
F61: 1904 | G61: 105X161 | H61: 0.5 | I61: OK | J61: BATIDA
A62: DUKE | B62: 44222 | C62: 44230 | D62: 6096 | E62: COUCHE | F62: 2800 | G62: 45X45 | H62: 6 | I62: OK | J62: PERSONALIZAR | L62: 312
A63: COSTUME | B63: 44237 | D63: 6201 | E63: COUCHE | F63: 2733 | G63: 100X75 | H63: 0.5 | I63: OK | J63: FACA | K63: PERSONAL | L63: 30.32
E64: COUCHE | F64: 1468 | G64: 100X75 | H64: 5 | I64: OK | J64: FACA | L64: 315
A65: STELLALBLU | B65: 44237 | C65: 44232 | D65: 6285 | E65: COUCHE | F65: 1140 | G65: 44X16 | H65: 4 | I65: OK | J65: LASER | L65: 36
A66: NEUSA | B66: 44238 | C66: 44230 | D66: 6289 | E66: BOPP | F66: 2560 | G66: 100X40 | H66: 5 | I66: OK | J66: FACA
E67: BOPP | F67: 2172 | G67: 33X25 | H67: 10 | I67: OK | J67: FACA | L67: 305
A68: UP TO GO | B68: 44238 | C68: 44230 | D68: 6291 | E68: COUCHE | F68: 2664 | G68: 15X30 | H68: 60 | I68: OK | J68: FACA
E69: COUCHE | F69: 753 | G69: 100X50 | H69: 2.4 | I69: OK | J69: FACA | L69: 324
A70: DOMAMA | B70: 44238 | C70: 44231 | D70: 6292 | E70: COUCHE | F70: 2515 | G70: 55X28 | H70: 20 | I70: OK | J70: FACA
E71: COUCHE | F71: 838 | G71: 100X40 | H71: 10 | I71: OK | J71: FACA | L71: 385
A72: DELTAFIRE | B72: 44232 | D72: 6206 | E72: BOPP | F72: 1853 | G72: 100X35 | H72: 2 | I72: OK | J72: FACA
E73: BOPP | F73: 2771 | G73: 35X21 | H73: 5 | I73: OK | J73: LASER
E74: BOPP | F74: 2775 | G74: 70X40 | H74: 2 | I74: OK | J74: LASER | L74: 514.46
A75: DELTAFIRE | B75: 44238 | C75: 44238 | D75: 6300 | E75: BOPP | F75: 2771 | G75: 35X21 | H75: 15 | I75: OK | J75: LASER | K75: PAPEL | L75: 116.047 | M75: 45 DO 6206
A76: IPACOL | B76: 44239 | C76: 44232 | D76: 6309 | E76: COUCHE | F76: 950 | G76: 100X65 | H76: 17.4 | I76: OK | J76: LASER | L76: 765
A77: SUPER PEÇAS | B77: 44237 | C77: 44236 | D77: 6275 | E77: COUCHE | F77: 1153 | G77: 25X54 | H77: 66 | I77: OK | J77: LASER | L77: 741.25
A78: ZANLINE | B78: 44239 | C78: 44235 | D78: 6310 | E78: COUCHE | F78: 951 | G78: 100X150 | H78: 20 | I78: OK | J78: FACA | L78: 1340
A79: SPIGOLON | B79: 44239 | D79: 6311 | E79: AMARELA | F79: 3189 | G79: 50X50 | H79: 3 | I79: OK | J79: FACA
E80: TAG | F80: 3184 | G80: 47,5X35 | H80: 21.5 | I80: OK | J80: LASER
E81: TAG | F81: 3502 | G81: 47,5X25 | H81: 12 | I81: OK | J81: LASER | L81: 0
E82: AMARELA | F82: 3102 | G82: 33X25 | H82: 15 | I82: OK | J82: FACA
E83: AMARELA | F83: 3101 | G83: 100X75 | H83: 1.5 | I83: OK | J83: FACA
E84: COUCHE | F84: 869 | G84: 33X25 | H84: 30 | I84: OK | J84: FACA
E85: AMARELA | F85: 3493 | G85: 90X35 | H85: 3 | I85: OK | J85: FACA | K85: 90X36 | L85: 962.55
A86: JULIANA | B86: 44239 | C86: 44231 | D86: 6315 | E86: COUCHE | F86: 838 | G86: 100X40 | H86: 25 | I86: OK | J86: FACA | L86: 445
A87: AFETTO | B87: 44239 | D87: 6306 | E87: COUCHE | F87: 1468 | G87: 100X75 | H87: 30 | I87: OK | J87: FACA
E88: AMARELA | F88: 2987 | G88: 100X60 | H88: 5.6 | I88: OK | J88: FACA
E89: VERDE | F89: 3486 | G89: 100X60 | H89: 14.7 | I89: OK | J89: FACA
E90: VERM | F90: 3487 | G90: 100X60 | H90: 5.6 | I90: OK | J90: FACA
E91: LARANJ | F91: 3488 | G91: 100X60 | H91: 5.6 | I91: OK | J91: FACA
E92: AMARELA | F92: 3489 | G92: 80X40 | H92: 5 | I92: OK | J92: LASER
E93: VERDE | F93: 3490 | G93: 80X40 | H93: 10 | I93: OK | J93: LASER
E94: VERM | F94: 3492 | G94: 80X40 | H94: 5 | I94: OK | J94: LASER
E95: LARANJ | F95: 3491 | G95: 80X40 | H95: 5 | I95: OK | J95: LASER | L95: 3742.5
A96: AFETTO | B96: 44239 | C96: 44232 | D96: 6323 | E96: AMARELA | F96: 2040 | G96: 40X30 | H96: 0.3 | I96: OK | J96: FACA
E97: VERM | F97: 3011 | G97: 40X30 | H97: 0.3 | I97: OK | J97: FACA | L97: 17.7
A98: UNIMED | B98: 44242 | C98: 44239 | D98: 6321 | E98: BOPP | F98: 2603 | G98: 55X25 | H98: 4 | I98: OK | J98: LASER
E99: COUCHE | F99: 2804 | G99: 56X23 | H99: 20 | I99: OK | J99: LASER | L99: 462
A100: VITAMED | B100: 44242 | C100: 44235 | D100: 6352 | E100: COUCHE | F100: 838 | G100: 100X40 | H100: 40 | I100: OK | J100: FACA | L100: 1400
A101: RESET | B101: 44232 | C101: 44232 | D101: 6331 | E101: COUCHE | F101: 869 | G101: 33X25 | H101: 20 | I101: OK | J101: FACA | L101: 110
A102: AMF INFO | B102: 44245 | D102: 6332 | E102: COUCHE | F102: 1139 | G102: 108X87 | H102: 11 | I102: OK | J102: BATIDA | L102: 393.73
A103: AMF INFO | B103: 44242 | C103: 44235 | D103: 6333 | E103: COUCHE | F103: 869 | G103: 33X25 | H103: 200 | I103: OK | J103: FACA | L103: 760
A104: FOUSBEI | B104: 44242 | C104: 44238 | D104: 6334 | E104: TAG | F104: 3498 | G104: 35X64 | H104: 1.5 | I104: OK | J104: LASER | L104: 33.75
...

Sheet ABRIL21
A1: CLIENTE | B1: Data Entr | C1: Data Prod | D1: O/F | E1: MATERIAL | F1: CÓDIGO | G1: ETIQUETA | H1: QUANT | I1: OK | J1: PRODUZIDO POR | K1: O/C | L1: VALOR
A2: GRAFICA 10
A3: FARMBERRY | B3: 44232 | C3: 44293 | E3: TC | F3: 2749 | G3: 45X85 | H3: 18.8 | I3: OK | J3: G10 | K3: 1635 | L3: 2420
A4: TECNOLOGICA | B4: 44265 | C4: 44293 | D4: 6367 | E4: TERMICA | F4: 2043 | G4: 50X22 | H4: 30 | I4: OK | J4: G10 | K4: 1639 | L4: 490
A5: TECNOLOGICA | B5: 44280 | C5: 44293 | D5: 6537 | E5: TERMICA | F5: 3538 | G5: 105X200 | H5: 0.7 | I5: OK | J5: G10 | K5: 1651 | L5: 525
A7: PERSONALIZAR
A8: FARM BERRY | B8: 44300 | C8: 44299 | D8: 6947 | E8: TC | F8: 3282 | G8: 45x85 | H8: 5 | I8: OK | J8: PERS. | L8: 650
F9: 2749 | G9: 45x85 | H9: 5 | I9: OK | J9: PERS. | L9: 650
A10: DUKE | B10: 44309 | C10: 44305 | D10: 6978 | E10: COUCHE | F10: 2800 | G10: 45X45 | H10: 5.8 | I10: OK | J10: PERS. | L10: 260
A11: INJET | B11: 44312 | C11: 44305 | D11: 6994 | E11: B.BORR | F11: 2494 | G11: 25X25 | H11: 20 | I11: OK | J11: PERS. | L11: 550
A13: =SUM(L8:L12) -> 2110
A14: LASER
A15: AMF INFO | B15: 44292 | C15: 44302 | D15: 6630 | E15: TAG | F15: 2780 | G15: 41X75 | H15: 150 | I15: OK | J15: LASER | L15: 1837.5
A16: AMF INFO | B16: 44292 | C16: 44295 | D16: 6809 | E16: C.BORR | F16: 3168 | G16: 100.1X76.1 | H16: 5 | I16: OK | J16: LASER | L16: 292
A17: KIDINS | B17: 44294 | C17: 44302 | D17: 6824 | E17: TAG | F17: 3584 | G17: 35X62 | H17: 5 | I17: OK | J17: LASER | L17: 225
A18: AMOSTRA | B18: 44305 | D18: 0 | E18: C.REMOV | G18: 105X64 | H18: 0.2 | J18: LASER | L18: 0
A19: HYVA | B19: 44308 | C19: 44305 | D19: 6951 | E19: TAG | F19: 2550 | G19: 100X50 | H19: 20 | I19: OK | J19: LASER | L19: 810
A20: ANALU | B20: 44309 | C20: 44306 | D20: 6987 | E20: COUCHE | F20: 3394 | G20: 90X50 | H20: 16 | I20: OK | J20: LASER | L20: 560
A21: RR VISION | B21: 44308 | C21: 44302 | D21: 6955 | E21: BOPP | F21: 2844 | G21: 48X10 | H21: 10 | I21: OK | J21: LASER | L21: 90
A22: CODETECH | B22: 44312 | C22: 44302 | D22: 6989 | E22: TAG | F22: 1316 | G22: 95X30 | H22: 5 | I22: OK | J22: LASER | L22: 40
A23: AMF INFO | B23: 44312 | C23: 44314 | D23: 6809 | E23: C.BORR | F23: 3168 | G23: 100.1X76.1 | H23: 5 | I23: OK | J23: LASER | L23: 292
A24: SEXY FANTASY | B24: 44313 | C24: 44306 | D24: 6997 | E24: AMARELO | F24: 3608 | G24: 10X10 | H24: 10 | I24: OK | J24: LASER
E25: VERMELHO | F25: 3610 | G25: 10X10 | H25: 5 | I25: OK | J25: LASER
E26: PINK | F26: 3607 | G26: 10X10 | H26: 5 | I26: OK | J26: LASER
E27: COUCHE | F27: 3609 | G27: 10X10 | H27: 10 | I27: OK | J27: LASER | L27: 192.8
A28: MOV. BRASTURBO | C28: 44316 | D28: 6976 | E28: C.BORR | F28: 3603 | G28: 100X123 | H28: 3.15 | I28: OK | J28: LASER | K28: AZUL | L28: 271.65
A29: MAR AZUL | B29: 44305 | C29: 44305 | D29: 7016 | E29: BOPP | F29: 2175 | G29: 30X80 | H29: 10 | I29: OK | J29: LASER | L29: 185
A30: IND. FER.LAZZAR | B30: 44316 | C30: 44312 | D30: 7045 | E30: COUCHE | F30: 1173 | G30: 100X25 | H30: 21 | I30: OK | J30: LASER | L30: 766.5
A31: POLIBOM | B31: 44314 | C31: 44313 | D31: 7060 | E31: COUCHE | F31: 3152 | G31: 100X200 | H31: 2 | I31: OK | J31: LASER | L31: 232.8
A32: POLIBOM | B32: 44314 | C32: 44313 | D32: 7061 | E32: COUCHE | F32: 3152 | G32: 100X200 | H32: 1 | I32: OK | J32: LASER | L32: 116.4
A33: ARCO | B33: 44316 | C33: 44313 | D33: 7077 | E33: COUCHE | F33: 2604 | G33: 105X55 | H33: 6.4 | I33: OK | J33: LASER | L33: 162.2
A34: OPTICA VISUAL | B34: 44316 | C34: 44315 | D34: 7109 | E34: BOPP | F34: 3634 | G34: 90X10 | H34: 12.5 | I34: OK | J34: LASER | L34: 388.75
A36: =SUM(L15:L35) -> 6462.6
A37: BATIDA
A38: FUTURE | B38: 44225 | E38: COUCHE | G38: 50X25 | H38: 0.2 | J38: BATIDA | K38: AMOSTRA | L38: 0
A39: PEDRO SANZ | B39: 44293 | C39: 44292 | D39: 6790 | E39: COUCHE | F39: 2774 | G39: 100X120 | H39: 5.25 | I39: OK | J39: BATIDA | L39: 308.7
C40: 44286 | E40: BOPP | F40: 2555 | G40: 74X74 | H40: 8 | I40: OK | J40: BATIDA | L40: 340
A41: RONI | B41: 44300 | C41: 44306 | D41: 6870 | E41: BOPP | F41: 2798 | G41: 78X30 | H41: 10 | I41: OK | J41: BATIDA | K41: MATRIZART | L41: 132.5
A42: HOSP.UNIMED | B42: 44299 | C42: 44295 | D42: 6854 | E42: COUCHE | F42: 1271 | G42: 30X22 | H42: 18 | I42: OK | J42: BATIDA
A43: HOSP.UNIMED | B43: 44299 | C43: 44295 | D43: 6854 | E43: COUCHE | F43: 2804 | G43: 56X23 | H43: 36 | I43: OK | J43: BATIDA | L43: 436.61
A44: HOSP.POMPEIA | B44: 44299 | C44: 44295 | D44: 6855 | E44: C.BORR | F44: 3591 | G44: 100X45 | H44: 5 | I44: OK | J44: BATIDA | L44: 138.3
